Workbook

Sheet BBDD
A1: RUT | B1: Número de Documento | C1: Nombre Empresa | D1: Código de Ficha | E1: Email | F1: Email Personal | G1: Nombre Completo | H1: Cargo | I1: Nombre Supervisor | J1: Nombre Área | K1: Tipo de Contrato | L1: Fecha Ingreso Compañía | M1: Nomina de Pago | N1: Nombre Gerencia | O1: Lugar de Trabajo | P1: Tipo contratación
A2: 17382227 | B2: 17.382.227-8 | C2: Orizon S.A | D2: F1 | E2: humberto.galaz@gmail.com | F2: humberto.galaz@gmail.com | G2: Galaz Segovia Humberto Elias | H2: Supervisor(A) De Turno Pt | I2: Stephanie Nicole Navarro Marmiez | J2: Gerencia Logistica | K2: Plazo fijo | L2: 45964 | M2: Coronel Rol Tierra | N2: Gerencia Corp. Supply Chain | O2: Coronel | P2: Temporada (Con ocasión Temporada de Pesca)
A3: 18501236 | B3: 18.501.236-0 | C3: Orizon S.A | D3: F1 | E3: urquiola.loredana@gmail.com | F3: urquiola.loredana@gmail.com | G3: Espinoza Saez Katherine Loredana | H3: Ingeniero Programador Planificación Mantención | I3: Sebastian Ignacio Olate Vega | J3: Departamento Ingeniería | K3: Plazo fijo | L3: 45962 | M3: Coronel Rol Tierra | N3: Gerencia Corp. Negocio Seafood | O3: Coronel | P3: Rol General (Cargo permanente o proyección indefinido)
A4: 17861981 | B4: 17.861.981-0 | C4: Orizon S.A | D4: F3 | E4: carla.roca@orizon.cl | F4: carla.roca@orizon.cl | G4: Roca Galindo Carla Eugenia | H4: Supervisor(A) De Turno Pt | I4: Osvaldo Mardones Beltran | J4: Gerencia Logistica | K4: Plazo fijo | L4: 45962 | M4: Coronel Rol Tierra | N4: Gerencia Corp. Supply Chain | O4: Coronel | P4: Temporada (Con ocasión Temporada de Pesca)
A5: 20438291 | B5: 20.438.291-3 | C5: Orizon S.A | D5: F3 | E5: valediaze05@hotmail.com | F5: valediaze05@hotmail.com | G5: Diaz Elgueta Valentina Isabel | H5: Monitor(A) Calidad Ch | I5: Larisa Andrea Burgos Zavala | J5: Gerencia Gestión Integrada y Calidad | K5: Plazo fijo | L5: 45966 | M5: Coronel Rol Eventual | N5: Gerencia Corp. Negocio Seafood | O5: Coronel | P5: Temporada (Con ocasión Temporada de Pesca)
A6: 18821915 | B6: 18.821.915-2 | C6: Orizon S.A | D6: F3 | E6: monsalvezerik@gmail.com | F6: monsalvezerik@gmail.com | G6: Monsalvez Nuñez Erik Antonio | H6: Monitor(A) De Calidad | I6: Larisa Andrea Burgos Zavala | J6: Gerencia Gestión Integrada y Calidad | K6: Plazo fijo | L6: 45966 | M6: Coronel Rol Eventual | N6: Gerencia Corp. Negocio Seafood | O6: Coronel | P6: Temporada (Con ocasión Temporada de Pesca)
A7: 19139667 | B7: 19.139.667-7 | C7: Orizon S.A | D7: F3 | E7: ANTO.LOZANO95@GMAIL.COM | F7: ANTO.LOZANO95@GMAIL.COM | G7: Lozano Aniñir Antonia | H7: Monitor(A) De Calidad | I7: Larisa Andrea Burgos Zavala | J7: Gerencia Gestión Integrada y Calidad | K7: Plazo fijo | L7: 45966 | M7: Coronel Rol Eventual | N7: Gerencia Corp. Negocio Seafood | O7: Coronel | P7: Temporada (Con ocasión Temporada de Pesca)
A8: 20362461 | B8: 20.362.461-1 | C8: Orizon S.A | D8: F5 | E8: yocelynmarianeladelcarmen18@gmail.com | F8: yocelynmarianeladelcarmen18@gmail.com | G8: Diaz Hidalgo Jocelyn Marianela Del Carmen | H8: Operador Elaboracion Php | I8: Marcos Antonio Nuñez Garcia | J8: Gerencia Producción Pesca | K8: Plazo fijo | L8: 45962 | M8: Coronel Rol Tierra | N8: Gerencia Corp. Negocio Seafood | O8: Coronel | P8: Temporada (Con ocasión Temporada de Pesca)
A9: 18816284 | B9: 18.816.284-3 | C9: Orizon S.A | D9: F3 | E9: RM.NUTDIET@GMAIL.COM | F9: RM.NUTDIET@GMAIL.COM | G9: Montaner Pereira Romina Fernanda | H9: Monitor(A) De Calidad | I9: Larisa Andrea Burgos Zavala | J9: Gerencia Gestión Integrada y Calidad | K9: Plazo fijo | L9: 45967 | M9: Coronel Rol Eventual | N9: Gerencia Corp. Negocio Seafood | O9: Coronel | P9: Temporada (Con ocasión Temporada de Pesca)
A10: 20362434 | B10: 20.362.434-4 | C10: Orizon S.A | D10: F1 | E10: Nksbastian@gmail.com | F10: Nksbastian@gmail.com | G10: Pastrana Ceballos Bastian Alonso | H10: Asistente Operaciones Pt | I10: Stephanie Nicole Navarro Marmiez | J10: Gerencia Logistica | K10: Plazo fijo | L10: 45964 | M10: Coronel Rol Tierra | N10: Gerencia Corp. Supply Chain | O10: Coronel | P10: Temporada (Con ocasión Temporada de Pesca)
A11: 15529956 | B11: 15.529.956-8 | C11: Orizon S.A | D11: F5 | E11: MARYCARRASCO117@GMAIL.COM | F11: MARYCARRASCO117@GMAIL.COM | G11: Carrasco Copelli Mariana Elizabeth | H11: Monitor(A) De Calidad | I11: Larisa Andrea Burgos Zavala | J11: Gerencia Gestión Integrada y Calidad | K11: Plazo fijo | L11: 45968 | M11: Coronel Rol Eventual | N11: Gerencia Corp. Negocio Seafood | O11: Coronel | P11: Temporada (Con ocasión Temporada de Pesca)
A12: 20196888 | B12: 20.196.888-7 | C12: Orizon S.A | D12: F1 | E12: javiierahidalgo@gmail.com | F12: javiierahidalgo@gmail.com | G12: Hidalgo Reyes Javiera Scarlet | H12: Asistente Operaciones Pt | I12: Osvaldo Mardones Beltran | J12: Gerencia Logistica | K12: Plazo fijo | L12: 45964 | M12: Coronel Rol Tierra | N12: Gerencia Corp. Supply Chain | O12: Escuadrón | P12: Temporada (Con ocasión Temporada de Pesca)
A13: 14213629 | B13: 14.213.629-5 | C13: Orizon S.A | D13: F1 | E13: juanhpi@gmail.com | F13: juanhpi@gmail.com | G13: Palma Ibarra Juan Hernaldo | H13: Mecanico Frigorista | I13: Carlos Javier Orellana Gonzalez | J13: Departamento Ingeniería | K13: Plazo fijo | L13: 45962 | M13: Coronel Rol Tierra | N13: Gerencia Corp. Negocio Seafood | O13: Escuadrón | P13: Rol General (Cargo permanente o proyección indefinido)
... A123: 9713420 | B123: 9.713.420-0 | C123: Orizon S.A | D123: F1 | E123: guillermo.ramirez@orizon.cl | F123: gramirezr1965@gmail.com | G123: Ramirez Rodriguez Guillermo Elias | H123: Asistente Produccion | I123: Roberto Carlos Carcamo Ojeda | J123: Gerencia Producción Pesca | K123: Indefinido | L123: 41640 | M123: Coronel Rol Tierra | N123: Gerencia Corp. Negocio Seafood | O123: Coronel | P123: Rol General (Cargo permanente o proyección indefinido)
A124: 16038547 | B124: 16.038.547-2 | C124: Orizon S.A | D124: F1 | G124: Herrera Araya Cristian Alexis | H124: Aspirante Tripulante | I124: Eduardo Esteban Gonzalez Martinez | J124: Gerencia de Flota y Abastecimiento de Materias Primas | K124: Obra | L124: 45681 | M124: Coronel Rol Flota | N124: Gerencia Corp. Negocio Seafood | O124: Coronel | P124: Temporada (Con ocasión Temporada de Pesca)
A125: 18417675 | B125: 18.417.675-0 | C125: Orizon S.A | D125: F1 | E125: ed.neira.h@gmail.com | F125: ed.neira.h@gmail.com | G125: Neira Henriquez Edinson Benicio | H125: Aspirante Tripulante | I125: Eduardo Esteban Gonzalez Martinez | J125: Gerencia de Flota y Abastecimiento de Materias Primas | K125: Obra | L125: 45826 | M125: Coronel Rol Flota | N125: Gerencia Corp. Negocio Seafood | O125: Coronel | P125: Temporada (Con ocasión Temporada de Pesca)
A126: 15614411 | B126: 15.614.411-8 | C126: Orizon S.A | D126: F1 | E126: carlos.ruiz@orizon.cl | F126: carlosruizlagos@gmail.com | G126: Ruiz Lagos Carlos Felipe | H126: Auditor(A) De Servicios | I126: Sebastian Antonio Ochoa Pizarro | J126: Depto Control Interno y Riesgos | K126: Indefinido | L126: 43836 | M126: Coronel Rol Tierra | N126: Gerencia General | O126: Coronel | P126: Rol General (Cargo permanente o proyección indefinido)
A127: 11722500 | B127: 11.722.500-3 | C127: Orizon S.A | D127: F1 | E127: jorge.oyarzun@orizon.cl | F127: joya1807@hotmail.com | G127: Oyarzun Araya Jorge Andres | H127: Auditor(A) De Servicios | I127: Sebastian Antonio Ochoa Pizarro | J127: Depto Control Interno y Riesgos | K127: Indefinido | L127: 44593 | M127: Coquimbo | N127: Gerencia General | O127: Coquimbo | P127: Rol General (Cargo permanente o proyección indefinido)
A128: 13685377 | B128: 13.685.377-5 | C128: Orizon S.A | D128: F1 | E128: javier.dominguez@nutrisco.com | F128: javierdominguez.garrido@gmail.com | G128: Dominguez Garrido Javier | H128: Auditor(A) Interno | I128: Sebastian Antonio Ochoa Pizarro | J128: Depto Control Interno y Riesgos | K128: Indefinido | L128: 41778 | M128: Santiago | N128: Gerencia General | O128: Santiago | P128: Rol General (Cargo permanente o proyección indefinido)
A129: 15529692 | B129: 15.529.692-5 | C129: Orizon S.A | D129: F1 | E129: cristian.lefimil@orizon.cl | F129: calglefi@gmail.com | G129: Lefimil Gonzalez Cristian Armando | H129: Auditor(A) Junior | I129: Carlos Felipe Ruiz Lagos | J129: Depto Control Interno y Riesgos | K129: Indefinido | L129: 43857 | M129: Coronel Rol Tierra | N129: Gerencia General | O129: Coronel | P129: Rol General (Cargo permanente o proyección indefinido)
A130: 12039485 | B130: 12.039.485-1 | C130: Orizon S.A | D130: F1 | E130: alex.diaz@orizon.cl | F130: DINGO669@HOTMAIL.COM | G130: Diaz Rubilar Alex Esteban | H130: Auxiliar Administrativo | I130: Rodrigo Alejandro Jofré Valdebenito | J130: Gerencia SST y Servicio a las Personas | K130: Indefinido | L130: 45558 | M130: Coronel Rol Tierra | N130: Gerencia Corp. Personas y SST | O130: Coronel | P130: Rol General (Cargo permanente o proyección indefinido)
A131: 17444650 | B131: 17.444.650-4 | C131: Orizon S.A | D131: F5 | E131: pili1744465042211@gmail.com | F131: pili1744465042211@gmail.com | G131: Guerrero Vega Ingrid Del Pilar | H131: Auxiliar Aseo | I131: Luis Jose Vasquez Sandoval | J131: Gerencia Producción Pesca | K131: Plazo fijo | L131: 45938 | M131: Coronel Rol Tierra | N131: Gerencia Corp. Negocio Seafood | O131: Coronel | P131: Temporada (Con ocasión Temporada de Pesca)
A132: 17232589 | B132: 17.232.589-0 | C132: Orizon S.A | D132: F5 | E132: andreaguajardo1111@gmail.com | F132: andreaguajardo1111@gmail.com | G132: Meneses Guajardo Margarita Andrea | H132: Auxiliar Aseo | I132: Marcos Antonio Nuñez Garcia | J132: Gerencia Producción Pesca | K132: Plazo fijo | L132: 45938 | M132: Coronel Rol Tierra | N132: Gerencia Corp. Negocio Seafood | O132: Coronel | P132: Temporada (Con ocasión Temporada de Pesca)
A133: 8978847 | B133: 8.978.847-1 | C133: Orizon S.A | D133: F1 | E133: pedroconchagutierrez19@gmail.com | F133: pedroconchagutierrez19@gmail.com | G133: Concha Gutierrez Pedro Pablo | H133: Ayudante Bodega Pt | I133: Luis Javier Piñones Segovia | J133: Gerencia Sales Harinas y Aceite | K133: Indefinido | L133: 40513 | M133: Coquimbo | N133: Gerencia Corp. Supply Chain | O133: Coquimbo | P133: Rol General (Cargo permanente o proyección indefinido)
A134: 14131725 | B134: 14.131.725-3 | C134: Orizon S.A | D134: F1 | E134: ivanf6587@gmail.com | F134: ivanf6587@gmail.com | G134: Flores Galleguillos Ivan Andres | H134: Ayudante Bodega Pt | I134: Luis Javier Piñones Segovia | J134: Gerencia Sales Harinas y Aceite | K134: Indefinido | L134: 44929 | M134: Coquimbo | N134: Gerencia Corp. Supply Chain | O134: Coquimbo | P134: Rol General (Cargo permanente o proyección indefinido)
A135: 14385954 | B135: 14.385.954-1 | C135: Orizon S.A | D135: F4 | E135: ulises730@gmail.com | F135: ulises730@gmail.com | G135: Galvez Alfaro Ulises Andres | H135: Ayudante Bodega Pt | I135: Luis Javier Piñones Segovia | J135: Gerencia Sales Harinas y Aceite | K135: Plazo fijo | L135: 45761 | M135: Coquimbo | N135: Gerencia Corp. Supply Chain | O135: Coquimbo | P135: Rol General (Cargo permanente o proyección indefinido)
A136: 17624797 | B136: 17.624.797-5 | C136: Orizon S.A | D136: F1 | E136: danieltapia.m90@gmail.com | F136: danieltapia.m90@gmail.com | G136: Tapia Miranda Daniel Jordan Constantino | H136: Ayudante Bodega Pt | I136: Luis Javier Piñones Segovia | J136: Gerencia Sales Harinas y Aceite | K136: Indefinido | L136: 45334 | M136: Coquimbo | N136: Gerencia Corp. Supply Chain | O136: Coquimbo | P136: Rol General (Cargo permanente o proyección indefinido)
... A306: 21295688 | B306: 21.295.688-0 | C306: Nutrisco S.A. | D306: F1 | E306: fiorella.montoya@nutrisco.com | F306: fiorella.montoya.p@gmail.com | G306: Montoya Portella Fiorella | H306: Gerente Corporativa De Sostenibilidad | I306: Rigoberto Rojo Rojas | J306: Gerencia Corp. Sostenibilidad | K306: Indefinido | L306: 45474 | M306: Rol Privado | N306: Gerencia Corp. Sostenibilidad | O306: Santiago | P306: Rol General (Cargo permanente o proyección indefinido)
A307: 10844186 | B307: 10.844.186-0 | C307: Nutrisco S.A. | D307: F1 | E307: cristian.larrain@nutrisco.com | G307: Larrain Reyes Cristian | H307: Gerente Corporativo Comercial Y Marketing | I307: Rigoberto Rojo Rojas | J307: Gerencia Corp Comercial y Marketing | K307: Indefinido | L307: 42681 | M307: Rol Privado | N307: Gerencia Corp. Comercial y Marketing | O307: Santiago | P307: Rol General (Cargo permanente o proyección indefinido)
A308: 10093016 | B308: 10.093.016-1 | C308: Nutrisco S.A. | D308: F1 | E308: juancarlos.macaya@nutrisco.com | F308: jc.macayag@gmail.com | G308: Macaya Gastigar Juan Carlos | H308: Gerente Corporativo De Administracion | I308: Rigoberto Rojo Rojas | J308: Gerencia Corp. Administracion | K308: Indefinido | L308: 40513 | M308: Rol Privado | N308: Gerencia Corp. de Administracion | O308: Santiago | P308: Rol General (Cargo permanente o proyección indefinido)
A309: 13271928 | B309: 13.271.928-4 | C309: Nutrisco S.A. | D309: F1 | E309: michel.bouiey@nutrisco.com | F309: mbouiey@uc.cl | G309: Bouiey Sierra Michel | H309: Gerente Corporativo De Finanzas Y Tecnologia | I309: Rigoberto Rojo Rojas | J309: Gerencia Corp. Finanzas y Tecnología | K309: Indefinido | L309: 45047 | M309: Rol Privado | N309: Gerencia Corp. Finanzas y Tecnologia | O309: Santiago | P309: Rol General (Cargo permanente o proyección indefinido)
A310: 11833668 | B310: 11.833.668-2 | C310: Nutrisco S.A. | D310: F1 | E310: francisca.prieto@nutrisco.com | F310: franciscaprietoarroyo@gmail.com | G310: Prieto Arroyo María Francisca | H310: Gerente Corporativo De Personas Y Sst | I310: Rigoberto Rojo Rojas | J310: Gerencia Corp. Personas | K310: Indefinido | L310: 45523 | M310: Rol Privado | N310: Gerencia Corp. Personas y SST | O310: Santiago | P310: Rol General (Cargo permanente o proyección indefinido)
A311: 13134939 | B311: 13.134.939-4 | C311: Nutrisco S.A. | D311: F1 | E311: gerardo.barrera@nutrisco.com | F311: gbarreras77@gmail.com | G311: Barrera Sanzana Gerardo | H311: Gerente Corporativo De Supply Chain | I311: Rigoberto Rojo Rojas | J311: Gerencia Supply Chain | K311: Indefinido | L311: 42917 | M311: Rol Privado | N311: Gerencia Corp. Supply Chain | O311: Santiago | P311: Rol General (Cargo permanente o proyección indefinido)
A312: 13724355 | B312: 13.724.355-5 | C312: Nutrisco S.A. | D312: F1 | E312: ignacio.garrido@nutrisco.com | F312: igarrido_ing@hotmail.com | G312: Garrido Concha Ignacio Andrés | H312: Gerente De Abastecimiento | I312: Gerardo Barrera Sanzana | J312: Gerencia de Abastecimiento | K312: Indefinido | L312: 45505 | M312: Rol Privado | N312: Gerencia Corp. Negocio Seafood | O312: Coronel | P312: Rol General (Cargo permanente o proyección indefinido)
A313: 11978482 | B313: 11.978.482-4 | C313: Nutrisco S.A. | D313: F1 | E313: claudia.zamorano@nutrisco.com | F313: claudiazamoranor@hotmail.com | G313: Zamorano Raventos Claudia | H313: Gerente De Administracion De Activos Y Seguros | I313: Juan Carlos Macaya Gastigar | J313: Gerencia de Administración, Activos y Seguros Planta | K313: Indefinido | L313: 41609 | M313: Rol Privado | N313: Gerencia Corp. de Administracion | O313: Santiago | P313: Rol General (Cargo permanente o proyección indefinido)
A314: 12010509 | B314: 12.010.509-4 | C314: Nutrisco S.A. | D314: F1 | E314: bayardo.vado@nutrisco.com | F314: bayardovado@gmail.com | G314: Vado Uribe Bayardo | H314: Gerente De Contabilidad | I314: Juan Carlos Macaya Gastigar | J314: Gerencia Contabilidad | K314: Indefinido | L314: 43276 | M314: Rol Privado | N314: Gerencia Corp. de Administracion | O314: Santiago | P314: Rol General (Cargo permanente o proyección indefinido)
A315: 13425908 | B315: 13.425.908-6 | C315: Orizon S.A | D315: F1 | E315: jorge.buzeta@orizon.cl | F315: jbuzetan@gmail.com | G315: Buzeta Negroni Jorge Andres | H315: Gerente De Flota Y Abastecimiento De Mmpp Pesca | I315: Fernando Ayala Burgemeister | J315: Gerencia de Flota y Abastecimiento de Materias Primas | K315: Indefinido | L315: 41330 | M315: Rol Privado | N315: Gerencia Corp. Negocio Seafood | O315: Coronel | P315: Rol General (Cargo permanente o proyección indefinido)
A316: 16155554 | B316: 16.155.554-1 | C316: Nutrisco S.A. | D316: F1 | E316: constanza.aravena@nutrisco.com | F316: constanza.aravena3@gmail.com | G316: Aravena Sandoval María Constanza | H316: Gerente De Logistica | I316: Gerardo Barrera Sanzana | J316: Gerencia Supply Chain | K316: Indefinido | L316: 45523 | M316: Rol Privado | N316: Gerencia Corp. Supply Chain | O316: 4 Esquinas | P316: Rol General (Cargo permanente o proyección indefinido)
A317: 24741043 | B317: 24.741.043-0 | C317: Nutrisco S.A. | D317: F1 | E317: mariaflorencia.barua@nutrisco.com | F317: florbarua@gmail.com | G317: Barua . M.Florencia | H317: Gerente De Marketing | I317: Cristian Larrain Reyes | J317: Gerencia de Marketing | K317: Indefinido | L317: 44522 | M317: Rol Privado | N317: Gerencia Corp. Comercial y Marketing | O317: Santiago | P317: Rol General (Cargo permanente o proyección indefinido)
A318: 10034310 | B318: 10.034.310-k | C318: Nutrisco S.A. | D318: F1 | E318: ignacio.astete@nutrisco.com | G318: Astete Heimpell Ignacio Arturo | H318: Gerente De Negocio North America | I318: Rigoberto Rojo Rojas | J318: Nutrisco North America LLC | K318: Indefinido | L318: 45341 | M318: Rol Privado | N318: Gerencia Nutrisco North America LLC | O318: Santiago | P318: Rol General (Cargo permanente o proyección indefinido)
A319: 13257001 | B319: 13.257.001-9 | C319: Nutrisco S.A. | D319: F1 | E319: crescente.valle@nutrisco.com | F319: crescente.valle@gmail.com | G319: Valle Rivera Crescente | H319: Gerente De Negocios Frutas Y Verduras | I319: Rigoberto Rojo Rojas | J319: Frutas y Verduras | K319: Indefinido | L319: 45047 | M319: Rol Privado | N319: Gerencia Corp. de Frutas y Verduras | O319: Santiago | P319: Rol General (Cargo permanente o proyección indefinido)
A320: 16213768 | B320: 16.213.768-9 | C320: Nutrisco S.A. | D320: F1 | E320: martin.rodriguez@nutrisco.com | F320: rodriguezdmartin@gmail.com | G320: Rodriguez Diez Martin Ignacio | H320: Gerente De Negocios Frutas Y Verduras | I320: Cristian Larrain Reyes | J320: Gerencia Comercial Negocio Frutas y Verduras | K320: Indefinido | L320: 44900 | M320: Rol Privado | N320: Gerencia Corp. Comercial y Marketing | O320: Otro | P320: Rol General (Cargo permanente o proyección indefinido)
A321: 13392882 | B321: 13.392.882-0 | C321: Nutrisco S.A. | D321: F1 | E321: fernando.riveros@nutrisco.com | F321: fernando.riveros@gmail.com | G321: Riveros Ramirez Fernando | H321: Gerente De Tecnologia Y Gobierno De Datos | I321: Michel Bouiey Sierra | J321: Gerencia Tecnología y Gobierno de Datos | K321: Indefinido | L321: 43521 | M321: Rol Privado | N321: Gerencia Corp. Finanzas y Tecnologia | O321: Santiago | P321: Rol General (Cargo permanente o proyección indefinido)
A322: 12488186 | B322: 12.488.186-2 | C322: Nutrisco S.A. | D322: F1 | E322: rigoberto.rojo@nutrisco.com | F322: rojorigoberto@gmail.com | G322: Rojo Rojas Rigoberto | H322: Gerente General | I322: Rigoberto Rojo Rojas | J322: Gerencia General | K322: Indefinido | L322: 45047 | M322: Rol Privado | N322: Gerencia General | O322: Santiago | P322: Rol General (Cargo permanente o proyección indefinido)
A323: 7736569 | B323: 7.736.569-9 | C323: Orizon S.A | D323: F1 | E323: fernando.ayala@nutrisco.com | F323: fayalab@gmail.com | G323: Ayala Burgemeister Fernando | H323: Gerente Negocio Seafood | I323: Rigoberto Rojo Rojas | J323: Corporativo Seafood | K323: Indefinido | L323: 40513 | M323: Rol Privado | N323: Gerencia Corp. Negocio Seafood | O323: Coronel | P323: Rol General (Cargo permanente o proyección indefinido)
A324: 14734970 | B324: 14.734.970-k | C324: Nutrisco S.A. | D324: F1 | E324: jorge.dellano@nutrisco.com | F324: chicureo25@gmail.com | G324: De Llano Ozores Jorge | H324: Gerente Nutrisco Europa | I324: Cristian Larrain Reyes | J324: Gerencia Nutrisco Europa | K324: Indefinido | L324: 41927 | M324: Rol Privado | N324: Gerencia Corp. Comercial y Marketing | O324: Santiago | P324: Rol General (Cargo permanente o proyección indefinido)
A325: 16657501 | B325: 16.657.501-k | C325: Nutrisco S.A. | D325: F1 | E325: pilar.henriquez@nutrisco.com | F325: mpilar.henriquez@gmail.com | G325: Henriquez Arratia Maria Pilar | H325: Gerente Planificación | I325: Gerardo Barrera Sanzana | J325: Gerencia Supply Chain | K325: Indefinido | L325: 45803 | M325: Rol Privado | N325: Gerencia Corp. Supply Chain | O325: Santiago | P325: Rol General (Cargo permanente o proyección indefinido)
A326: 16002041 | B326: 16.002.041-5 | C326: Orizon S.A | D326: F1 | E326: rodrigo.sanchez@orizon.cl | F326: rodrigo.asr@gmail.com | G326: Sanchez Ramirez Rodrigo Antonio | H326: Gerente Produccion Pesca | I326: Fernando Ayala Burgemeister | J326: Gerencia Producción Pesca | K326: Indefinido | L326: 45474 | M326: Rol Privado | N326: Gerencia Corp. Negocio Seafood | O326: Coronel | P326: Rol General (Cargo permanente o proyección indefinido)
A327: 10420968 | B327: 10.420.968-8 | C327: Nutrisco S.A. | D327: F1 | E327: juanpablo.chavez@nutrisco.com | F327: juan.pablo.cha@gmail.com | G327: Chavez Urrutia Juan Pablo | H327: Gerente Sst Y Servicio A Las Personas | I327: María Francisca Prieto Arroyo | J327: Gerencia SST y Servicio a las Personas | K327: Indefinido | L327: 44805 | M327: Rol Privado | N327: Gerencia Corp. Personas y SST | O327: Coronel | P327: Rol General (Cargo permanente o proyección indefinido)
A328: 6773312 | B328: 6.773.312-6 | C328: Nutrisco S.A. | D328: F1 | E328: mauricio.carvacho@nutrisco.com | F328: Mauricio.Carvacho@gmail.com | G328: Carvacho Rivas Mauricio Alejandro | H328: Gerente Tesoreria | I328: Michel Bouiey Sierra | J328: Gerencia de Tesorería | K328: Indefinido | L328: 45203 | M328: Rol Privado | N328: Gerencia Corp. Finanzas y Tecnologia | O328: Santiago | P328: Rol General (Cargo permanente o proyección indefinido)
A329: 16140909 | B329: 16.140.909-k | C329: Nutrisco S.A. | D329: F1 | E329: moises.llao@nutrisco.com | F329: mellao@it.ucsc.cl | G329: Llao Morales Moises Elias | H329: Gestor(A) Compras | I329: Cristian Eraldo Sepulveda Moreno | J329: Gerencia Abastecimiento | K329: Indefinido | L329: 45708 | M329: Nutrisco SA | N329: Gerencia Corp. Supply Chain | O329: 4 Esquinas | P329: Rol General (Cargo permanente o proyección indefinido)
A330: 18414043 | B330: 18.414.043-8 | C330: Nutrisco S.A. | D330: F2 | E330: manfred.henning@nutrisco.com | F330: mhenningr@ingenieros.udd.cl | G330: Henning Retamal Manfred Adolfo | H330: Gestor(A) Compras | I330: Cristian Eraldo Sepulveda Moreno | J330: Gerencia Abastecimiento | K330: Indefinido | L330: 45717 | M330: Nutrisco SA | N330: Gerencia Corp. Supply Chain | O330: 4 Esquinas | P330: Rol General (Cargo permanente o proyección indefinido)
... A531: 16818256 | B531: 16.818.256-2 | C531: Orizon S.A | D531: F1 | E531: katherine.p.c.d@hotmail.cl | F531: katherine.p.c.d@hotmail.cl | G531: Cuevas Diaz Katherine Paola | H531: Monitor(A) De Calidad | I531: Larisa Andrea Burgos Zavala | J531: Gerencia Gestión Integrada y Calidad | K531: Indefinido | L531: 44805 | M531: Coronel Rol Tierra | N531: Gerencia Corp. Negocio Seafood | O531: Coronel | P531: Rol General (Cargo permanente o proyección indefinido)
A532: 11449083 | B532: 11.449.083-0 | C532: Orizon S.A | D532: F1 | G532: Leal Valenzuela Patricia Margaret | H532: Monitor(A) De Calidad | I532: Larisa Andrea Burgos Zavala | J532: Gerencia Gestión Integrada y Calidad | K532: Indefinido | L532: 42370 | M532: Coronel Rol Tierra | N532: Gerencia Corp. Negocio Seafood | O532: Coronel | P532: Rol General (Cargo permanente o proyección indefinido)
A533: 13953625 | B533: 13.953.625-8 | C533: Orizon S.A | D533: F1 | E533: analista.etiquetado@orizon.cl | F533: pmariomardones@gmail.com | G533: Marió Mardones Paulina Andrea | H533: Monitor(A) De Calidad | I533: Larisa Andrea Burgos Zavala | J533: Gerencia Gestión Integrada y Calidad | K533: Indefinido | L533: 43466 | M533: Coronel Rol Tierra | N533: Gerencia Corp. Negocio Seafood | O533: 4 Esquinas | P533: Rol General (Cargo permanente o proyección indefinido)
A534: 18069608 | B534: 18.069.608-3 | C534: Orizon S.A | D534: F1 | E534: carola.mellado@orizon.cl | F534: melladocarola7@gmail.com | G534: Mellado Fierro Carola Andrea | H534: Monitor(A) De Calidad | I534: Larisa Andrea Burgos Zavala | J534: Gerencia Gestión Integrada y Calidad | K534: Indefinido | L534: 44460 | M534: Coronel Rol Tierra | N534: Gerencia Corp. Negocio Seafood | O534: Escuadrón | P534: Rol General (Cargo permanente o proyección indefinido)
A535: 18135151 | B535: 18.135.151-9 | C535: Orizon S.A | D535: F1 | E535: joelariel545@gmail.com | F535: joelariel545@gmail.com | G535: Medina Luengo Joel Ariel | H535: Monitor(A) De Calidad | I535: Larisa Andrea Burgos Zavala | J535: Gerencia Gestión Integrada y Calidad | K535: Indefinido | L535: 44805 | M535: Coronel Rol Tierra | N535: Gerencia Corp. Negocio Seafood | O535: Coronel | P535: Rol General (Cargo permanente o proyección indefinido)
A536: 10021264 | B536: 10.021.264-1 | C536: Orizon S.A | D536: F1 | E536: Jmonsalvez66.jm@gmail.com | F536: Jmonsalvez66.jm@gmail.com | G536: Monsalvez Gutierrez Juan Antonio | H536: Monitor(A) De Calidad | I536: Larisa Andrea Burgos Zavala | J536: Gerencia Gestión Integrada y Calidad | K536: Indefinido | L536: 40513 | M536: Coronel Rol Tierra | N536: Gerencia Corp. Negocio Seafood | O536: Coronel | P536: Rol General (Cargo permanente o proyección indefinido)
A537: 12703195 | B537: 12.703.195-9 | C537: Orizon S.A | D537: F1 | E537: foxtrot.angers@gmail.com | F537: foxtrot.angers@gmail.com | G537: Rios Soto Angelo Enrique | H537: Monitor(A) De Calidad | I537: Larisa Andrea Burgos Zavala | J537: Gerencia Gestión Integrada y Calidad | K537: Indefinido | L537: 42618 | M537: Coronel Rol Tierra | N537: Gerencia Corp. Negocio Seafood | O537: Coronel | P537: Rol General (Cargo permanente o proyección indefinido)
A538: 19332061 | B538: 19.332.061-9 | C538: Orizon S.A | D538: F1 | E538: Cristina.riffocastro@gmail.com | F538: Cristina.riffocastro@gmail.com | G538: Riffo Castro Cristina Deisy | H538: Monitor(A) De Calidad | I538: Larisa Andrea Burgos Zavala | J538: Gerencia Gestión Integrada y Calidad | K538: Indefinido | L538: 45017 | M538: Coronel Rol Tierra | N538: Gerencia Corp. Negocio Seafood | O538: Coronel | P538: Rol General (Cargo permanente o proyección indefinido)
A539: 15529872 | B539: 15.529.872-3 | C539: Orizon S.A | D539: F1 | E539: jmmendiburo@gmail.com | F539: jmmendiburo@gmail.com | G539: Sanchez Recabarren Claudia Carolyn | H539: Monitor(A) De Calidad | I539: Larisa Andrea Burgos Zavala | J539: Gerencia Gestión Integrada y Calidad | K539: Indefinido | L539: 43831 | M539: Coronel Rol Tierra | N539: Gerencia Corp. Negocio Seafood | O539: Coronel | P539: Rol General (Cargo permanente o proyección indefinido)
A540: 18134850 | B540: 18.134.850-k | C540: Orizon S.A | D540: F1 | E540: scarlet.venegas@hotmail.com | F540: scarlet.venegas@hotmail.com | G540: Venegas Unzueta Scarlet Elizabeth | H540: Monitor(A) De Calidad | I540: Larisa Andrea Burgos Zavala | J540: Gerencia Gestión Integrada y Calidad | K540: Obra | L540: 44896 | M540: Coronel Rol Eventual | N540: Gerencia Corp. Negocio Seafood | O540: Coronel | P540: Temporada (Con ocasión Temporada de Pesca)
A541: 17844420 | B541: 17.844.420-4 | C541: Orizon S.A | D541: F1 | E541: lavindaza.daniel@gmail.com | F541: lavindaza.daniel@gmail.com | G541: Lavin Daza Daniel Antonio | H541: Monitor(A) De Calidad | I541: Larisa Andrea Burgos Zavala | J541: Gerencia Gestión Integrada y Calidad | K541: Indefinido | L541: 44137 | M541: Coronel Rol Tierra | N541: Gerencia Corp. Negocio Seafood | O541: Coronel | P541: Rol General (Cargo permanente o proyección indefinido)
A542: 18108706 | B542: 18.108.706-4 | C542: Orizon S.A | D542: F1 | E542: gisellecarolinevc@gmail.com | F542: gisellecarolinevc@gmail.com | G542: Villa Calvo Caroline Giselle | H542: Monitor(A) De Calidad | I542: Larisa Andrea Burgos Zavala | J542: Gerencia Gestión Integrada y Calidad | K542: Indefinido | L542: 44805 | M542: Coronel Rol Tierra | N542: Gerencia Corp. Negocio Seafood | O542: Coronel | P542: Rol General (Cargo permanente o proyección indefinido)
A543: 8680798 | B543: 8.680.798-k | C543: Orizon S.A | D543: F1 | E543: luisedunavarrod@gmail.com | F543: luisedunavarrod@gmail.com | G543: Navarro Diaz Luis Eduardo | H543: Monitor(A) De Calidad | I543: Larisa Andrea Burgos Zavala | J543: Gerencia Gestión Integrada y Calidad | K543: Indefinido | L543: 44781 | M543: Coronel Rol Tierra | N543: Gerencia Corp. Negocio Seafood | O543: Coronel | P543: Rol General (Cargo permanente o proyección indefinido)
A544: 19297515 | B544: 19.297.515-8 | C544: Orizon S.A | D544: F3 | E544: MARILYNAREVALO25@GMAIL.COM | F544: MARILYNAREVALO25@GMAIL.COM | G544: Arevalo Vargas Marilyn Luzmira | H544: Monitor(A) De Calidad | I544: Roberto Carlos Carcamo Ojeda | J544: Gerencia Gestión Integrada y Calidad | K544: Obra | L544: 45600 | M544: Coronel Rol Eventual | N544: Gerencia Corp. Negocio Seafood | O544: Coronel | P544: Temporada (Con ocasión Temporada de Pesca)
... A1314: 18502460 | B1314: 18.502.460-1 | C1314: Orizon S.A | D1314: F1 | E1314: sergio.cardoza@orizon.cl | F1314: scardozar@gmail.com | G1314: Cardoza Rivas Sergio Andres | H1314: Sales Manager De Norteamerica | I1314: Ignacio Arturo Astete Heimpell | J1314: Nutrisco North America LLC | K1314: Indefinido | L1314: 44013 | M1314: Rol Privado | N1314: Gerencia Nutrisco North America LLC | O1314: Santiago | P1314: Rol General (Cargo permanente o proyección indefinido)
A1315: 2466242 | B1315: 2.466.242-k | C1315: Orizon S.A | D1315: F1 | E1315: alejandro.garcia@orizoneu.com | G1315: García Lorenzo Alejandro | H1315: Sales Manager Ue | I1315: Jorge De Llano Ozores | J1315: Gerencia Nutrisco Europa | K1315: Indefinido | L1315: 45323 | M1315: Rol Privado | N1315: Gerencia Corp. Comercial y Marketing | O1315: Santiago | P1315: Rol General (Cargo permanente o proyección indefinido)
A1316: 12281916 | B1316: 12.281.916-7 | C1316: Orizon S.A | D1316: F1 | E1316: karina.gamboa@orizon.cl | F1316: karina.gamboa2324@gmail.com | G1316: Gamboa Zamorano Karina Andrea | H1316: Secretaria | I1316: Cristian Larrain Reyes | J1316: Gerencia Corp Comercial y Marketing | K1316: Indefinido | L1316: 44774 | M1316: Santiago | N1316: Gerencia Corp. Comercial y Marketing | O1316: Santiago | P1316: Rol General (Cargo permanente o proyección indefinido)
A1317: 8058278 | B1317: 8.058.278-1 | C1317: Orizon S.A | D1317: F1 | E1317: anamaria.vidal@orizon.cl | F1317: anamara.vidal@gmail.com | G1317: Vidal Henriquez Ana Maria | H1317: Secretaria | I1317: Fernando Ayala Burgemeister | J1317: Corporativo Seafood | K1317: Indefinido | L1317: 40513 | M1317: Coronel Rol Tierra | N1317: Gerencia Corp. Negocio Seafood | O1317: Coronel | P1317: Rol General (Cargo permanente o proyección indefinido)
A1318: 11896344 | B1318: 11.896.344-k | C1318: Orizon S.A | D1318: F1 | E1318: marcelo.villa@orizon.cl | F1318: marcelovilla614@gmail.com | G1318: Villa Quilodran Marcelo Ariel | H1318: Secretario Tecnico De Mantenimiento | I1318: Alexis Antonio Rivera Perez | J1318: Gerencia de Flota y Abastecimiento de Materias Primas | K1318: Indefinido | L1318: 40513 | M1318: Coronel Rol Tierra | N1318: Gerencia Corp. Negocio Seafood | O1318: Coronel | P1318: Rol General (Cargo permanente o proyección indefinido)
A1319: 17214075 | B1319: 17.214.075-0 | C1319: Nutrisco S.A. | D1319: F2 | E1319: barbara.aguilera@nutrisco.com | F1319: barbara.ahormazabal@gmail.com | G1319: Aguilera Hormazabal Barbara Michelle | H1319: Subgerente Abastecimiento Bienes | I1319: Ignacio Andrés Garrido Concha | J1319: Gerencia Abastecimiento | K1319: Indefinido | L1319: 44774 | M1319: Nutrisco SA | N1319: Gerencia Corp. Supply Chain | O1319: Coronel | P1319: Rol General (Cargo permanente o proyección indefinido)
A1320: 13953300 | B1320: 13.953.300-3 | C1320: Nutrisco S.A. | D1320: F1 | E1320: andres.morales@nutrisco.com | F1320: amoralesrios@gmail.com | G1320: Morales Ríos Andrés Agustín | H1320: Subgerente Abastecimiento Servicios | I1320: Ignacio Andrés Garrido Concha | J1320: Gerencia Supply Chain | K1320: Indefinido | L1320: 45505 | M1320: Rol Privado | N1320: Gerencia Corp. Supply Chain | O1320: Coronel | P1320: Rol General (Cargo permanente o proyección indefinido)
A1321: 15655852 | B1321: 15.655.852-4 | C1321: Nutrisco S.A. | D1321: F1 | E1321: alvaro.perez@nutrisco.com | F1321: alvaro.perez.campos@gmail.com | G1321: Perez Campos Alvaro | H1321: Subgerente Control De Gestion | I1321: Juan Carlos Macaya Gastigar | J1321: Subgerencia Control de Gestión | K1321: Indefinido | L1321: 41426 | M1321: Rol Privado | N1321: Gerencia Corp. de Administracion | O1321: Santiago | P1321: Rol General (Cargo permanente o proyección indefinido)
A1322: 15677251 | B1322: 15.677.251-8 | C1322: Nutrisco S.A. | D1322: F1 | E1322: karina.soto@nutrisco.com | F1322: karinaucsc@gmail.com | G1322: Soto Merino Ada Karina | H1322: Subgerente de Asuntos Públicos | I1322: Fiorella Montoya Portella | J1322: Relacionamiento Comunitario | K1322: Indefinido | L1322: 45768 | M1322: Rol Privado | N1322: Gerencia Corp. Sostenibilidad | O1322: Coronel | P1322: Rol General (Cargo permanente o proyección indefinido)
A1323: 17703620 | B1323: 17.703.620-k | C1323: Nutrisco S.A. | D1323: F1 | E1323: rafael.eyzaguirre@nutrisco.com | F1323: Rjem1991@gmail.com | G1323: Eyzaguirre Martinez Rafael Jose | H1323: Subgerente de Business intelligence y Desarrollo de Productos | I1323: Cristian Larrain Reyes | J1323: SubGerencia de Desarrollo y Business Intelligence | K1323: Indefinido | L1323: 43080 | M1323: Rol Privado | N1323: Gerencia Corp. Comercial y Marketing | O1323: Santiago | P1323: Rol General (Cargo permanente o proyección indefinido)
A1324: 16744490 | B1324: 16.744.490-3 | C1324: Nutrisco S.A. | D1324: F1 | E1324: sebastian.ochoa@nutrisco.com | F1324: s.ochoa.pizarro@gmail.com | G1324: Ochoa Pizarro Sebastian Antonio | H1324: Subgerente de Cumplimiento y Auditoria Interna | I1324: Rigoberto Rojo Rojas | J1324: Depto Control Interno y Riesgos | K1324: Indefinido | L1324: 45859 | M1324: Rol Privado | N1324: Gerencia General | O1324: Santiago | P1324: Rol General (Cargo permanente o proyección indefinido)
A1325: 16219383 | B1325: 16.219.383-k | C1325: Nutrisco S.A. | D1325: F1 | E1325: javier.millas@nutrisco.com | F1325: javier.millasf@gmail.com | G1325: Millas Fernandez Javier Andres | H1325: Subgerente De Logistica Y Customer Service | I1325: María Constanza Aravena Sandoval | J1325: Gerencia Supply Chain | K1325: Indefinido | L1325: 45768 | M1325: Nutrisco SA | N1325: Gerencia Corp. Supply Chain | O1325: 4 Esquinas | P1325: Rol General (Cargo permanente o proyección indefinido)
A1326: 16304122 | B1326: 16.304.122-7 | C1326: Nutrisco S.A. | D1326: F1 | E1326: matias.llopis@nutrisco.com | F1326: matollopis@gmail.com | G1326: Llopis Godoy Matias Andres | H1326: Subgerente De Planificacion Y Gestion Comercial | I1326: Maria Pilar Henriquez Arratia | J1326: Gerencia Supply Chain | K1326: Indefinido | L1326: 43080 | M1326: Rol Privado | N1326: Gerencia Corp. Supply Chain | O1326: Santiago | P1326: Rol General (Cargo permanente o proyección indefinido)
A1327: 13634001 | B1327: 13.634.001-8 | C1327: Nutrisco S.A. | D1327: F1 | E1327: JOSE.COLLAO@nutrisco.com | F1327: jose.collaob@gmail.com | G1327: Collao Bolados Jose Jesus | H1327: Subgerente De Seguridad Y Salud En El Trabajo | I1327: Juan Pablo Chavez Urrutia | J1327: Gerencia SST y Servicio a las Personas | K1327: Indefinido | L1327: 45044 | M1327: Rol Privado | N1327: Gerencia Corp. Personas y SST | O1327: Coronel | P1327: Rol General (Cargo permanente o proyección indefinido)
... A1356: 13899807 | B1356: 13.899.807-k | C1356: Orizon S.A | D1356: F1 | E1356: cesar.godoy@orizon.cl | F1356: cesargodoybononato@gmail.com | G1356: Godoy Bononato Cesar Mauricio | H1356: Supervisor(A) Mantencion Flota | I1356: Alexis Antonio Rivera Perez | J1356: Gerencia de Flota y Abastecimiento de Materias Primas | K1356: Indefinido | L1356: 42723 | M1356: Coronel Rol Tierra | N1356: Gerencia Corp. Negocio Seafood | O1356: Coronel | P1356: Rol General (Cargo permanente o proyección indefinido)
A1357: 9081691 | B1357: 9.081.691-8 | C1357: Orizon S.A | D1357: F1 | E1357: jose.hernandez@orizon.cl | G1357: Hernandez Mansilla Jose Eduardo | H1357: Supervisor(A) Mantencion Flota | I1357: Alexis Antonio Rivera Perez | J1357: Gerencia de Flota y Abastecimiento de Materias Primas | K1357: Indefinido | L1357: 40513 | M1357: Coronel Rol Tierra | N1357: Gerencia Corp. Negocio Seafood | O1357: Coronel | P1357: Rol General (Cargo permanente o proyección indefinido)
A1358: 14212240 | B1358: 14.212.240-5 | C1358: Orizon S.A | D1358: F1 | E1358: jose.pineda@orizon.cl | F1358: jpinedaenator@gmail.com | G1358: Pineda Venegas Jose Ernesto | H1358: Supervisor(A) Mantencion Flota | I1358: Alexis Antonio Rivera Perez | J1358: Gerencia de Flota y Abastecimiento de Materias Primas | K1358: Indefinido | L1358: 42887 | M1358: Coronel Rol Tierra | N1358: Gerencia Corp. Negocio Seafood | O1358: Coronel | P1358: Rol General (Cargo permanente o proyección indefinido)
A1359: 17225677 | B1359: 17.225.677-5 | C1359: Orizon S.A | D1359: F1 | E1359: daissy.martinez@orizon.cl | F1359: daissy.martinez.r@gmail.com | G1359: Martinez Rojas Daissy Del Carmen | H1359: Supervisor(A) Tributario | I1359: Bayardo Vado Uribe | J1359: Gerencia Contabilidad | K1359: Indefinido | L1359: 43045 | M1359: Santiago | N1359: Gerencia Corp. de Administracion | O1359: Santiago | P1359: Rol General (Cargo permanente o proyección indefinido)
A1360: 26697795 | B1360: 26.697.795-6 | C1360: Orizon S.A | D1360: F1 | E1360: tomas.ruano@orizon.cl | F1360: truano2@gmail.com | G1360: Ruano Goitia Tomás | H1360: Tecnico Ti | I1360: Pedro Burgos Lara | J1360: Gerencia Tecnología y Gobierno de Datos | K1360: Indefinido | L1360: 45413 | M1360: Santiago | N1360: Gerencia Corp. Finanzas y Tecnologia | O1360: Santiago | P1360: Rol General (Cargo permanente o proyección indefinido)
A1361: 9797341 | B1361: 9.797.341-5 | C1361: Orizon S.A | D1361: F1 | E1361: juanantonio.meza@orizon.cl | F1361: JAMEZAS1@GMAIL.COM | G1361: Meza Sagredo Juan Antonio | H1361: Tesorero | I1361: Carlos Javier Belmar Durán | J1361: Gerencia de Tesorería | K1361: Indefinido | L1361: 44606 | M1361: Santiago | N1361: Gerencia Corp. Finanzas y Tecnologia | O1361: Santiago | P1361: Rol General (Cargo permanente o proyección indefinido)
A1362: 9774216 | B1362: 9.774.216-2 | C1362: Orizon S.A | D1362: F1 | E1362: pabloandresa.1963@gmail.com | F1362: pabloandresa.1963@gmail.com | G1362: Aburto Clasing Pablo Andres | H1362: Tripulante | I1362: Carlos Enrique Muñoz Cortes | J1362: Gerencia de Flota y Abastecimiento de Materias Primas | K1362: Indefinido | L1362: 44200 | M1362: Coronel Rol Flota | N1362: Gerencia Corp. Negocio Seafood | O1362: Coronel | P1362: Rol General (Cargo permanente o proyección indefinido)
A1363: 10591641 | B1363: 10.591.641-8 | C1363: Orizon S.A | D1363: F1 | E1363: haroldocacerese@gmail.com | F1363: haroldocacerese@gmail.com | G1363: Caceres Estrada Haroldo Manuel | H1363: Tripulante | I1363: Eduardo Esteban Gonzalez Martinez | J1363: Gerencia de Flota y Abastecimiento de Materias Primas | K1363: Indefinido | L1363: 43812 | M1363: Coronel Rol Flota | N1363: Gerencia Corp. Negocio Seafood | O1363: Coronel | P1363: Rol General (Cargo permanente o proyección indefinido)
A1364: 16999609 | B1364: 16.999.609-1 | C1364: Orizon S.A | D1364: F1 | E1364: leocabreraco@gmail.com | F1364: leocabreraco@gmail.com | G1364: Cabrera Cortes Audito Leopoldo | H1364: Tripulante | I1364: Mario Rolando Martinez Gutierrez | J1364: Gerencia de Flota y Abastecimiento de Materias Primas | K1364: Indefinido | L1364: 44200 | M1364: Coronel Rol Flota | N1364: Gerencia Corp. Negocio Seafood | O1364: Coronel | P1364: Rol General (Cargo permanente o proyección indefinido)
A1365: 7346296 | B1365: 7.346.296-7 | C1365: Orizon S.A | D1365: F1 | G1365: Espinoza Daza Raul Angel | H1365: Tripulante | I1365: Carlos Alberto Varela Artigues | J1365: Gerencia de Flota y Abastecimiento de Materias Primas | K1365: Indefinido | L1365: 40513 | M1365: Coronel Rol Flota | N1365: Gerencia Corp. Negocio Seafood | O1365: Coronel | P1365: Rol General (Cargo permanente o proyección indefinido)
A1366: 8209270 | B1366: 8.209.270-6 | C1366: Orizon S.A | D1366: F1 | E1366: robertopalma1961@gmail.com | F1366: robertopalma1961@gmail.com | G1366: Palma Cardenas Roberto | H1366: Tripulante | I1366: Abdel Nayib Ahuile Gorayeb | J1366: Gerencia de Flota y Abastecimiento de Materias Primas | K1366: Indefinido | L1366: 40513 | M1366: Coronel Rol Flota | N1366: Gerencia Corp. Negocio Seafood | O1366: Coronel | P1366: Rol General (Cargo permanente o proyección indefinido)
A1367: 11904476 | B1367: 11.904.476-6 | C1367: Orizon S.A | D1367: F1 | E1367: cesarpinoa.ap@gmail.com | F1367: cesarpinoa.ap@gmail.com | G1367: Pino Alarcon Cesar Alejandro | H1367: Tripulante | I1367: Jose Fernando Daza Pincheira | J1367: Gerencia de Flota y Abastecimiento de Materias Primas | K1367: Indefinido | L1367: 40513 | M1367: Coronel Rol Flota | N1367: Gerencia Corp. Negocio Seafood | O1367: Coronel | P1367: Rol General (Cargo permanente o proyección indefinido)
A1368: 7769901 | B1368: 7.769.901-5 | C1368: Orizon S.A | D1368: F1 | E1368: joseangelreyescartes@gmail.com | F1368: joseangelreyescartes@gmail.com | G1368: Reyes Cartes Jose Angel | H1368: Tripulante | I1368: Carlos Alberto Varela Artigues | J1368: Gerencia de Flota y Abastecimiento de Materias Primas | K1368: Indefinido | L1368: 40513 | M1368: Coronel Rol Flota | N1368: Gerencia Corp. Negocio Seafood | O1368: Coronel | P1368: Rol General (Cargo permanente o proyección indefinido)
A1369: 10376049 | B1369: 10.376.049-6 | C1369: Orizon S.A | D1369: F2 | E1369: nelson.acero.cp@gmail.com | F1369: nelson.acero.cp@gmail.com | G1369: Cifuentes Peña Nelson Del Carmen | H1369: Tripulante | I1369: Mario Rolando Martinez Gutierrez | J1369: Gerencia de Flota y Abastecimiento de Materias Primas | K1369: Indefinido | L1369: 45562 | M1369: Coronel Rol Flota | N1369: Gerencia Corp. Negocio Seafood | O1369: Coronel | P1369: Rol General (Cargo permanente o proyección indefinido)
A1370: 8285453 | B1370: 8.285.453-3 | C1370: Orizon S.A | D1370: F2 | E1370: estradamoragajose@gmail.com | F1370: estradamoragajose@gmail.com | G1370: Estrada Moraga Jose Gabino | H1370: Tripulante | I1370: Elvis Daniel Macaya Mendez | J1370: Gerencia de Flota y Abastecimiento de Materias Primas | K1370: Indefinido | L1370: 45611 | M1370: Coronel Rol Flota | N1370: Gerencia Corp. Negocio Seafood | O1370: Coronel | P1370: Rol General (Cargo permanente o proyección indefinido)
A1371: 11685172 | B1371: 11.685.172-5 | C1371: Orizon S.A | D1371: F1 | E1371: valenzuelaperez70@gmail.com | F1371: valenzuelaperez70@gmail.com | G1371: Valenzuela Perez Marco Antonio | H1371: Tripulante | I1371: Jose Fernando Daza Pincheira | J1371: Gerencia de Flota y Abastecimiento de Materias Primas | K1371: Indefinido | L1371: 42278 | M1371: Coronel Rol Flota | N1371: Gerencia Corp. Negocio Seafood | O1371: Coronel | P1371: Rol General (Cargo permanente o proyección indefinido)
A1372: 15211865 | B1372: 15.211.865-1 | C1372: Orizon S.A | D1372: F1 | E1372: miguelgarcias3777@gmail.com | F1372: miguelgarcias3777@gmail.com | G1372: Garcias Riffo Miguel Angel | H1372: Tripulante | I1372: Carlos Enrique Muñoz Cortes | J1372: Gerencia de Flota y Abastecimiento de Materias Primas | K1372: Indefinido | L1372: 45749 | M1372: Coronel Rol Flota | N1372: Gerencia Corp. Negocio Seafood | O1372: Coronel | P1372: Rol General (Cargo permanente o proyección indefinido)
A1373: 10072688 | B1373: 10.072.688-2 | C1373: Orizon S.A | D1373: F1 | E1373: billylosrios2@gmail.com | F1373: billylosrios2@gmail.com | G1373: Bustos Delgado Elbert Billy | H1373: Tripulante | I1373: Carlos Enrique Muñoz Cortes | J1373: Gerencia de Flota y Abastecimiento de Materias Primas | K1373: Indefinido | L1373: 45603 | M1373: Coronel Rol Flota | N1373: Gerencia Corp. Negocio Seafood | O1373: Coronel | P1373: Rol General (Cargo permanente o proyección indefinido)
A1374: 15175822 | B1374: 15.175.822-3 | C1374: Orizon S.A | D1374: F2 | E1374: pedroroa124@gmail.com | F1374: pedroroa124@gmail.com | G1374: Hernandez Roa Pedro Antonio | H1374: Tripulante | I1374: Carlos Enrique Muñoz Cortes | J1374: Gerencia de Flota y Abastecimiento de Materias Primas | K1374: Indefinido | L1374: 45603 | M1374: Coronel Rol Flota | N1374: Gerencia Corp. Negocio Seafood | O1374: Coronel | P1374: Rol General (Cargo permanente o proyección indefinido)
A1375: 20362196 | B1375: 20.362.196-5 | C1375: Orizon S.A | D1375: F2 | E1375: bryan.faundez.roa@gmail.com | F1375: bryan.faundez.roa@gmail.com | G1375: Faundez Roa Bryan Alejandro | H1375: Tripulante | I1375: Jose Fernando Daza Pincheira | J1375: Gerencia de Flota y Abastecimiento de Materias Primas | K1375: Indefinido | L1375: 45600 | M1375: Coronel Rol flota | N1375: Gerencia Corp. Negocio Seafood | O1375: Coronel | P1375: Rol General (Cargo permanente o proyección indefinido)
...

Sheet Atención 2025
A1: Número | B1: RUT | C1: Nombre | D1: Cargo | E1: Área | F1: Contrato | G1: Nómina | H1: Gerencia Corporativa | I1: Lugar | J1: Tipo Contratación | K1: Ingreso | L1: Razón | M1: Ficha | N1: E-mail | O1: Fecha | P1: Canal | Q1: Consulta | R1: Observación | S1: Respuesta | T1: Estado
A2: 19577640 | B2: =VLOOKUP(A2,BBDD!$1:$1048653,2,0) -> 19.577.640-7 | C2: =VLOOKUP(A2,BBDD!$1:$1048653,7,0) -> Faundez Roa Jorge Nicolás | D2: =VLOOKUP(A2,BBDD!$1:$1048653,8,0) -> Tripulante | E2: =VLOOKUP(A2,BBDD!$1:$1048653,10,0) -> Gerencia de Flota y Abastecimiento de Materias Primas | F2: =VLOOKUP(A2,BBDD!$1:$1048653,11,0) -> Indefinido | G2: =VLOOKUP(A2,BBDD!$1:$1048653,13,0) -> Coronel Rol flota | H2: =VLOOKUP(A2,BBDD!$1:$1048653,14,0) -> Gerencia Corp. Negocio Seafood | I2: =VLOOKUP(A2,BBDD!$1:$1048653,16,0) -> Rol General (Cargo permanente o proyección indefinido) | J2: =VLOOKUP(A2,BBDD!$1:$1048653,17,0) | K2: =VLOOKUP(A2,BBDD!$1:$1048653,12,0) -> 45611 | L2: =VLOOKUP(A2,BBDD!$1:$1048653,3,0) -> Orizon S.A | M2: =VLOOKUP(A2,BBDD!$1:$1048653,4,0) -> F2 | N2: =VLOOKUP(A2,BBDD!$1:$1048653,5,0) -> nicolasfaundezr@hotmail.com | O2: 45953 | P2: Oficina | Q2: Beneficios | R2: Inscripción Navidad | T2: Cerrado
A3: 19800216 | B3: =VLOOKUP(A3,BBDD!$1:$1048653,2,0) -> 19.800.216-k | C3: =VLOOKUP(A3,BBDD!$1:$1048653,7,0) -> Saez Torres Estefania Alejandra | D3: =VLOOKUP(A3,BBDD!$1:$1048653,8,0) -> Operario Apoyo Elaboracion | E3: =VLOOKUP(A3,BBDD!$1:$1048653,10,0) -> Gerencia Producción Pesca | F3: =VLOOKUP(A3,BBDD!$1:$1048653,11,0) -> Plazo fijo | G3: =VLOOKUP(A3,BBDD!$1:$1048653,13,0) -> Coronel Rol Eventual | H3: =VLOOKUP(A3,BBDD!$1:$1048653,14,0) -> Gerencia Corp. Negocio Seafood | I3: =VLOOKUP(A3,BBDD!$1:$1048653,16,0) -> Temporada (Con ocasión Temporada de Pesca) | J3: =VLOOKUP(A3,BBDD!$1:$1048653,17,0) | K3: =VLOOKUP(A3,BBDD!$1:$1048653,12,0) -> 45941 | L3: =VLOOKUP(A3,BBDD!$1:$1048653,3,0) -> Orizon S.A | M3: =VLOOKUP(A3,BBDD!$1:$1048653,4,0) -> F1 | N3: =VLOOKUP(A3,BBDD!$1:$1048653,5,0) -> saeztorres16@gmail.com | O3: 45953 | P3: Oficina | Q3: Asistencia | R3: Accidente leve | S3: Derivado a SST | T3: Cerrado
A4: 17320823 | B4: =VLOOKUP(A4,BBDD!$1:$1048653,2,0) -> 17.320.823-5 | C4: =VLOOKUP(A4,BBDD!$1:$1048653,7,0) -> Fonseca Cardenas Melisa Isabel | D4: =VLOOKUP(A4,BBDD!$1:$1048653,8,0) -> Administrativo(A) Prod Sap Y Sernapesca | E4: =VLOOKUP(A4,BBDD!$1:$1048653,10,0) -> Gerencia Producción Pesca | F4: =VLOOKUP(A4,BBDD!$1:$1048653,11,0) -> Indefinido | G4: =VLOOKUP(A4,BBDD!$1:$1048653,13,0) -> Coronel Rol Tierra | H4: =VLOOKUP(A4,BBDD!$1:$1048653,14,0) -> Gerencia Corp. Negocio Seafood | I4: =VLOOKUP(A4,BBDD!$1:$1048653,16,0) -> Rol General (Cargo permanente o proyección indefinido) | J4: =VLOOKUP(A4,BBDD!$1:$1048653,17,0) | K4: =VLOOKUP(A4,BBDD!$1:$1048653,12,0) -> 42738 | L4: =VLOOKUP(A4,BBDD!$1:$1048653,3,0) -> Orizon S.A | M4: =VLOOKUP(A4,BBDD!$1:$1048653,4,0) -> F1 | N4: =VLOOKUP(A4,BBDD!$1:$1048653,5,0) -> melissa.fonseca@orizon.cl | O4: 45953 | P4: Oficina | Q4: Vestimenta y EPP | R4: Reserva por LM | T4: Cerrado
A5: 16138010 | B5: =VLOOKUP(A5,BBDD!$1:$1048653,2,0) -> 16.138.010-5 | C5: =VLOOKUP(A5,BBDD!$1:$1048653,7,0) -> Saldias Soto Robinson Antonio | D5: =VLOOKUP(A5,BBDD!$1:$1048653,8,0) -> Despachador(A) Logistico | E5: =VLOOKUP(A5,BBDD!$1:$1048653,10,0) -> Gerencia Sales Harinas y Aceite | F5: =VLOOKUP(A5,BBDD!$1:$1048653,11,0) -> Indefinido | G5: =VLOOKUP(A5,BBDD!$1:$1048653,13,0) -> Coronel Rol Tierra | H5: =VLOOKUP(A5,BBDD!$1:$1048653,14,0) -> Gerencia Corp. Supply Chain | I5: =VLOOKUP(A5,BBDD!$1:$1048653,16,0) -> Rol General (Cargo permanente o proyección indefinido) | J5: =VLOOKUP(A5,BBDD!$1:$1048653,17,0) | K5: =VLOOKUP(A5,BBDD!$1:$1048653,12,0) -> 44896 | L5: =VLOOKUP(A5,BBDD!$1:$1048653,3,0) -> Orizon S.A | M5: =VLOOKUP(A5,BBDD!$1:$1048653,4,0) -> F1 | N5: =VLOOKUP(A5,BBDD!$1:$1048653,5,0) -> robinson.saldias@orizon.cl | O5: 45953 | P5: E-mail | Q5: Asignación Familiar | S5: Correo enviado | T5: Cerrado
A6: 13853030 | B6: =VLOOKUP(A6,BBDD!$1:$1048653,2,0) -> 13.853.030-2 | C6: =VLOOKUP(A6,BBDD!$1:$1048653,7,0) -> Burgos Zavala Larisa Andrea | D6: =VLOOKUP(A6,BBDD!$1:$1048653,8,0) -> Jefe(A) De Inocuidad E Higiene Consumo Humano | E6: =VLOOKUP(A6,BBDD!$1:$1048653,10,0) -> Gerencia Gestión Integrada y Calidad | F6: =VLOOKUP(A6,BBDD!$1:$1048653,11,0) -> Indefinido | G6: =VLOOKUP(A6,BBDD!$1:$1048653,13,0) -> Coronel Rol Tierra | H6: =VLOOKUP(A6,BBDD!$1:$1048653,14,0) -> Gerencia Corp. Negocio Seafood | I6: =VLOOKUP(A6,BBDD!$1:$1048653,16,0) -> Rol General (Cargo permanente o proyección indefinido) | J6: =VLOOKUP(A6,BBDD!$1:$1048653,17,0) | K6: =VLOOKUP(A6,BBDD!$1:$1048653,12,0) -> 40513 | L6: =VLOOKUP(A6,BBDD!$1:$1048653,3,0) -> Orizon S.A | M6: =VLOOKUP(A6,BBDD!$1:$1048653,4,0) -> F1 | N6: =VLOOKUP(A6,BBDD!$1:$1048653,5,0) -> larisa.burgos@orizon.cl | O6: 45953 | P6: Oficina | Q6: Vestimenta y EPP | R6: Cambio Talla | T6: Cerrado
A7: 18384012 | B7: =VLOOKUP(A7,BBDD!$1:$1048653,2,0) -> 18.384.012-6 | C7: =VLOOKUP(A7,BBDD!$1:$1048653,7,0) -> Contreras Alegria Andrea Nicole | D7: =VLOOKUP(A7,BBDD!$1:$1048653,8,0) -> Analista De Producto Final | E7: =VLOOKUP(A7,BBDD!$1:$1048653,10,0) -> Gerencia Gestión Integrada y Calidad | F7: =VLOOKUP(A7,BBDD!$1:$1048653,11,0) -> Indefinido | G7: =VLOOKUP(A7,BBDD!$1:$1048653,13,0) -> Coronel Rol Tierra | H7: =VLOOKUP(A7,BBDD!$1:$1048653,14,0) -> Gerencia Corp. Negocio Seafood | I7: =VLOOKUP(A7,BBDD!$1:$1048653,16,0) -> Rol General (Cargo permanente o proyección indefinido) | J7: =VLOOKUP(A7,BBDD!$1:$1048653,17,0) | K7: =VLOOKUP(A7,BBDD!$1:$1048653,12,0) -> 45303 | L7: =VLOOKUP(A7,BBDD!$1:$1048653,3,0) -> Orizon S.A | M7: =VLOOKUP(A7,BBDD!$1:$1048653,4,0) -> F1 | N7: =VLOOKUP(A7,BBDD!$1:$1048653,5,0) -> andreanicolecontrerasalegria@gmail.com | O7: 45953 | P7: Teléfono | Q7: Asignación Familiar | R7: Incorporar carga | T7: Cerrado
A8: 18383966 | B8: =VLOOKUP(A8,BBDD!$1:$1048653,2,0) -> 18.383.966-7 | C8: =VLOOKUP(A8,BBDD!$1:$1048653,7,0) -> Riffo Contreras Gabriela Andrea | D8: =VLOOKUP(A8,BBDD!$1:$1048653,8,0) -> Administrativo(A) Prod Sap Y Sernapesca | E8: =VLOOKUP(A8,BBDD!$1:$1048653,10,0) -> Gerencia Producción Pesca | F8: =VLOOKUP(A8,BBDD!$1:$1048653,11,0) -> Indefinido | G8: =VLOOKUP(A8,BBDD!$1:$1048653,13,0) -> Coronel Rol Tierra | H8: =VLOOKUP(A8,BBDD!$1:$1048653,14,0) -> Gerencia Corp. Negocio Seafood | I8: =VLOOKUP(A8,BBDD!$1:$1048653,16,0) -> Rol General (Cargo permanente o proyección indefinido) | J8: =VLOOKUP(A8,BBDD!$1:$1048653,17,0) | K8: =VLOOKUP(A8,BBDD!$1:$1048653,12,0) -> 44553 | L8: =VLOOKUP(A8,BBDD!$1:$1048653,3,0) -> Orizon S.A | M8: =VLOOKUP(A8,BBDD!$1:$1048653,4,0) -> F1 | N8: =VLOOKUP(A8,BBDD!$1:$1048653,5,0) -> gabriela.riffo@orizon.cl | O8: 45953 | P8: Teléfono | Q8: Asignación Familiar | R8: Incorporar carga | T8: Cerrado
A9: 10117554 | B9: =VLOOKUP(A9,BBDD!$1:$1048653,2,0) -> 10.117.554-5 | C9: =VLOOKUP(A9,BBDD!$1:$1048653,7,0) -> Torres Torres Marcelo | D9: =VLOOKUP(A9,BBDD!$1:$1048653,8,0) -> Mecanico De Turno | E9: =VLOOKUP(A9,BBDD!$1:$1048653,10,0) -> Departamento Ingeniería | F9: =VLOOKUP(A9,BBDD!$1:$1048653,11,0) -> Indefinido | G9: =VLOOKUP(A9,BBDD!$1:$1048653,13,0) -> Coronel Rol Tierra | H9: =VLOOKUP(A9,BBDD!$1:$1048653,14,0) -> Gerencia Corp. Negocio Seafood | I9: =VLOOKUP(A9,BBDD!$1:$1048653,16,0) -> Rol General (Cargo permanente o proyección indefinido) | J9: =VLOOKUP(A9,BBDD!$1:$1048653,17,0) | K9: =VLOOKUP(A9,BBDD!$1:$1048653,12,0) -> 44525 | L9: =VLOOKUP(A9,BBDD!$1:$1048653,3,0) -> Orizon S.A | M9: =VLOOKUP(A9,BBDD!$1:$1048653,4,0) -> F1 | N9: =VLOOKUP(A9,BBDD!$1:$1048653,5,0) -> torres.marceloalejandro@gmail.com | O9: 45953 | P9: Teléfono | Q9: Beneficios | R9: Solicita mochila | T9: Cerrado
A10: 16348510 | B10: =VLOOKUP(A10,BBDD!$1:$1048653,2,0) -> 16.348.510-9 | C10: =VLOOKUP(A10,BBDD!$1:$1048653,7,0) -> Jara Gallardo Jose Miguel | D10: =VLOOKUP(A10,BBDD!$1:$1048653,8,0) -> Encargado De Trazabilidad Y Sistema De Pesaje | E10: =VLOOKUP(A10,BBDD!$1:$1048653,10,0) -> Gerencia Producción Pesca | F10: =VLOOKUP(A10,BBDD!$1:$1048653,11,0) -> Indefinido | G10: =VLOOKUP(A10,BBDD!$1:$1048653,13,0) -> Coronel Rol Tierra | H10: =VLOOKUP(A10,BBDD!$1:$1048653,14,0) -> Gerencia Corp. Negocio Seafood | I10: =VLOOKUP(A10,BBDD!$1:$1048653,16,0) -> Rol General (Cargo permanente o proyección indefinido) | J10: =VLOOKUP(A10,BBDD!$1:$1048653,17,0) | K10: =VLOOKUP(A10,BBDD!$1:$1048653,12,0) -> 41659 | L10: =VLOOKUP(A10,BBDD!$1:$1048653,3,0) -> Orizon S.A | M10: =VLOOKUP(A10,BBDD!$1:$1048653,4,0) -> F1 | N10: =VLOOKUP(A10,BBDD!$1:$1048653,5,0) -> jose.jara@orizon.cl | O10: 45953 | P10: Teléfono | Q10: Buk | T10: Cerrado
A11: 11353351 | B11: =VLOOKUP(A11,BBDD!$1:$1048653,2,0) -> 11.353.351-k | C11: =VLOOKUP(A11,BBDD!$1:$1048653,7,0) -> Guevara Letelier Narciso Wilfredo | D11: =VLOOKUP(A11,BBDD!$1:$1048653,8,0) -> Logistico Intermedio | E11: =VLOOKUP(A11,BBDD!$1:$1048653,10,0) -> Gerencia Abastecimiento | F11: =VLOOKUP(A11,BBDD!$1:$1048653,11,0) -> Indefinido | G11: =VLOOKUP(A11,BBDD!$1:$1048653,13,0) -> Coronel Rol Tierra | H11: =VLOOKUP(A11,BBDD!$1:$1048653,14,0) -> Gerencia Corp. Supply Chain | I11: =VLOOKUP(A11,BBDD!$1:$1048653,16,0) -> Rol General (Cargo permanente o proyección indefinido) | J11: =VLOOKUP(A11,BBDD!$1:$1048653,17,0) | K11: =VLOOKUP(A11,BBDD!$1:$1048653,12,0) -> 40513 | L11: =VLOOKUP(A11,BBDD!$1:$1048653,3,0) -> Orizon S.A | M11: =VLOOKUP(A11,BBDD!$1:$1048653,4,0) -> F1 | N11: =VLOOKUP(A11,BBDD!$1:$1048653,5,0) -> narciso.guevara@orizon.cl | O11: 45953 | P11: Teléfono | Q11: Reclutamiento y Selección | T11: Cerrado
A12: 9753137 | B12: =VLOOKUP(A12,BBDD!$1:$1048653,2,0) -> 9.753.137-4 | C12: =VLOOKUP(A12,BBDD!$1:$1048653,7,0) -> Manriquez Duran Fabian Gustavo | D12: =VLOOKUP(A12,BBDD!$1:$1048653,8,0) -> Contramaestre | E12: =VLOOKUP(A12,BBDD!$1:$1048653,10,0) -> Gerencia de Flota y Abastecimiento de Materias Primas | F12: =VLOOKUP(A12,BBDD!$1:$1048653,11,0) -> Indefinido | G12: =VLOOKUP(A12,BBDD!$1:$1048653,13,0) -> Coronel Rol Flota | H12: =VLOOKUP(A12,BBDD!$1:$1048653,14,0) -> Gerencia Corp. Negocio Seafood | I12: =VLOOKUP(A12,BBDD!$1:$1048653,16,0) -> Rol General (Cargo permanente o proyección indefinido) | J12: =VLOOKUP(A12,BBDD!$1:$1048653,17,0) | K12: =VLOOKUP(A12,BBDD!$1:$1048653,12,0) -> 40513 | L12: =VLOOKUP(A12,BBDD!$1:$1048653,3,0) -> Orizon S.A | M12: =VLOOKUP(A12,BBDD!$1:$1048653,4,0) -> F1 | N12: =VLOOKUP(A12,BBDD!$1:$1048653,5,0) -> fmanriquezd@gmail.com | O12: 45953 | P12: Teléfono | Q12: Seguro de Salud | R12: Consulta por tripulante Felix Toledo | T12: Cerrado
A13: 1 | B13: =VLOOKUP(A13,BBDD!$1:$1048653,2,0) -> Usuario Externo | C13: =VLOOKUP(A13,BBDD!$1:$1048653,7,0) -> Usuario Externo | D13: =VLOOKUP(A13,BBDD!$1:$1048653,8,0) -> Usuario Externo | E13: =VLOOKUP(A13,BBDD!$1:$1048653,10,0) -> Usuario Externo | F13: =VLOOKUP(A13,BBDD!$1:$1048653,11,0) -> Usuario Externo | G13: =VLOOKUP(A13,BBDD!$1:$1048653,13,0) -> Usuario Externo | H13: =VLOOKUP(A13,BBDD!$1:$1048653,14,0) -> Usuario Externo | I13: =VLOOKUP(A13,BBDD!$1:$1048653,16,0) -> Usuario Externo | J13: =VLOOKUP(A13,BBDD!$1:$1048653,17,0) | K13: =VLOOKUP(A13,BBDD!$1:$1048653,12,0) -> Usuario Externo | L13: =VLOOKUP(A13,BBDD!$1:$1048653,3,0) -> Usuario Externo | M13: =VLOOKUP(A13,BBDD!$1:$1048653,4,0) -> Usuario Externo | N13: =VLOOKUP(A13,BBDD!$1:$1048653,5,0) -> Usuario Externo | O13: 45953 | P13: Oficina | Q13: Reclutamiento y Selección | T13: Cerrado
A14: 1 | B14: =VLOOKUP(A14,BBDD!$1:$1048653,2,0) -> Usuario Externo | C14: =VLOOKUP(A14,BBDD!$1:$1048653,7,0) -> Usuario Externo | D14: =VLOOKUP(A14,BBDD!$1:$1048653,8,0) -> Usuario Externo | E14: =VLOOKUP(A14,BBDD!$1:$1048653,10,0) -> Usuario Externo | F14: =VLOOKUP(A14,BBDD!$1:$1048653,11,0) -> Usuario Externo | G14: =VLOOKUP(A14,BBDD!$1:$1048653,13,0) -> Usuario Externo | H14: =VLOOKUP(A14,BBDD!$1:$1048653,14,0) -> Usuario Externo | I14: =VLOOKUP(A14,BBDD!$1:$1048653,16,0) -> Usuario Externo | J14: =VLOOKUP(A14,BBDD!$1:$1048653,17,0) | K14: =VLOOKUP(A14,BBDD!$1:$1048653,12,0) -> Usuario Externo | L14: =VLOOKUP(A14,BBDD!$1:$1048653,3,0) -> Usuario Externo | M14: =VLOOKUP(A14,BBDD!$1:$1048653,4,0) -> Usuario Externo | N14: =VLOOKUP(A14,BBDD!$1:$1048653,5,0) -> Usuario Externo | O14: 45953 | P14: Oficina | Q14: Documentos | T14: Cerrado
A15: 1 | B15: =VLOOKUP(A15,BBDD!$1:$1048653,2,0) -> Usuario Externo | C15: =VLOOKUP(A15,BBDD!$1:$1048653,7,0) -> Usuario Externo | D15: =VLOOKUP(A15,BBDD!$1:$1048653,8,0) -> Usuario Externo | E15: =VLOOKUP(A15,BBDD!$1:$1048653,10,0) -> Usuario Externo | F15: =VLOOKUP(A15,BBDD!$1:$1048653,11,0) -> Usuario Externo | G15: =VLOOKUP(A15,BBDD!$1:$1048653,13,0) -> Usuario Externo | H15: =VLOOKUP(A15,BBDD!$1:$1048653,14,0) -> Usuario Externo | I15: =VLOOKUP(A15,BBDD!$1:$1048653,16,0) -> Usuario Externo | J15: =VLOOKUP(A15,BBDD!$1:$1048653,17,0) | K15: =VLOOKUP(A15,BBDD!$1:$1048653,12,0) -> Usuario Externo | L15: =VLOOKUP(A15,BBDD!$1:$1048653,3,0) -> Usuario Externo | M15: =VLOOKUP(A15,BBDD!$1:$1048653,4,0) -> Usuario Externo | N15: =VLOOKUP(A15,BBDD!$1:$1048653,5,0) -> Usuario Externo | O15: 45953 | P15: Teléfono | Q15: Beneficios | R15: Solicitud agenda Nutrisco Chile | T15: Cerrado
A16: 20195336 | B16: =VLOOKUP(A16,BBDD!$1:$1048653,2,0) -> 20.195.336-7 | C16: =VLOOKUP(A16,BBDD!$1:$1048653,7,0) -> Cabrera Ortega Carolina Belen | D16: =VLOOKUP(A16,BBDD!$1:$1048653,8,0) -> Asistente Operaciones Pt | E16: =VLOOKUP(A16,BBDD!$1:$1048653,10,0) -> Gerencia Logistica | F16: =VLOOKUP(A16,BBDD!$1:$1048653,11,0) -> Plazo fijo | G16: =VLOOKUP(A16,BBDD!$1:$1048653,13,0) -> Coronel Rol Tierra | H16: =VLOOKUP(A16,BBDD!$1:$1048653,14,0) -> Gerencia Corp. Supply Chain | I16: =VLOOKUP(A16,BBDD!$1:$1048653,16,0) -> Temporada (Con ocasión Temporada de Pesca) | J16: =VLOOKUP(A16,BBDD!$1:$1048653,17,0) | K16: =VLOOKUP(A16,BBDD!$1:$1048653,12,0) -> 45936 | L16: =VLOOKUP(A16,BBDD!$1:$1048653,3,0) -> Orizon S.A | M16: =VLOOKUP(A16,BBDD!$1:$1048653,4,0) -> F2 | N16: =VLOOKUP(A16,BBDD!$1:$1048653,5,0) -> carolinacabreraortega@gmail.com | O16: 45953 | P16: Teléfono | Q16: Finiquito | S16: Transferencia realizada | T16: Cerrado
A17: 15170747 | B17: =VLOOKUP(A17,BBDD!$1:$1048653,2,0) -> 15.170.747-5 | C17: =VLOOKUP(A17,BBDD!$1:$1048653,7,0) -> Hidalgo Alarcon Christian Alejandro | D17: =VLOOKUP(A17,BBDD!$1:$1048653,8,0) -> Mecanico De Turno | E17: =VLOOKUP(A17,BBDD!$1:$1048653,10,0) -> Departamento Ingeniería | F17: =VLOOKUP(A17,BBDD!$1:$1048653,11,0) -> Indefinido | G17: =VLOOKUP(A17,BBDD!$1:$1048653,13,0) -> Coronel Rol Tierra | H17: =VLOOKUP(A17,BBDD!$1:$1048653,14,0) -> Gerencia Corp. Negocio Seafood | I17: =VLOOKUP(A17,BBDD!$1:$1048653,16,0) -> Rol General (Cargo permanente o proyección indefinido) | J17: =VLOOKUP(A17,BBDD!$1:$1048653,17,0) | K17: =VLOOKUP(A17,BBDD!$1:$1048653,12,0) -> 45397 | L17: =VLOOKUP(A17,BBDD!$1:$1048653,3,0) -> Orizon S.A | M17: =VLOOKUP(A17,BBDD!$1:$1048653,4,0) -> F1 | N17: =VLOOKUP(A17,BBDD!$1:$1048653,5,0) -> CHRISTIANALEJ28@GMAIL.COM | O17: 45953 | P17: Oficina | Q17: Beneficios | R17: No puede ingresar link regalo | T17: Cerrado
A18: 15194019 | B18: =VLOOKUP(A18,BBDD!$1:$1048653,2,0) -> 15.194.019-6 | C18: =VLOOKUP(A18,BBDD!$1:$1048653,7,0) -> Rojas Olate Alejandro Humberto | D18: =VLOOKUP(A18,BBDD!$1:$1048653,8,0) -> Administrativo(A) Prod Sap Y Sernapesca | E18: =VLOOKUP(A18,BBDD!$1:$1048653,10,0) -> Gerencia Producción Pesca | F18: =VLOOKUP(A18,BBDD!$1:$1048653,11,0) -> Indefinido | G18: =VLOOKUP(A18,BBDD!$1:$1048653,13,0) -> Coronel Rol Tierra | H18: =VLOOKUP(A18,BBDD!$1:$1048653,14,0) -> Gerencia Corp. Negocio Seafood | I18: =VLOOKUP(A18,BBDD!$1:$1048653,16,0) -> Rol General (Cargo permanente o proyección indefinido) | J18: =VLOOKUP(A18,BBDD!$1:$1048653,17,0) | K18: =VLOOKUP(A18,BBDD!$1:$1048653,12,0) -> 42795 | L18: =VLOOKUP(A18,BBDD!$1:$1048653,3,0) -> Orizon S.A | M18: =VLOOKUP(A18,BBDD!$1:$1048653,4,0) -> F1 | N18: =VLOOKUP(A18,BBDD!$1:$1048653,5,0) -> Alejandro.Rojas@orizon.cl | O18: 45953 | P18: Oficina | Q18: Reclutamiento y Selección | T18: Cerrado
A19: 19532216 | B19: =VLOOKUP(A19,BBDD!$1:$1048653,2,0) -> 19.532.216-3 | C19: =VLOOKUP(A19,BBDD!$1:$1048653,7,0) -> Gonzalez Guiñez Cristopher Distefano | D19: =VLOOKUP(A19,BBDD!$1:$1048653,8,0) -> Operario Apoyo Elaboracion | E19: =VLOOKUP(A19,BBDD!$1:$1048653,10,0) -> Gerencia Producción Pesca | F19: =VLOOKUP(A19,BBDD!$1:$1048653,11,0) -> Plazo fijo | G19: =VLOOKUP(A19,BBDD!$1:$1048653,13,0) -> Coronel Rol Eventual | H19: =VLOOKUP(A19,BBDD!$1:$1048653,14,0) -> Gerencia Corp. Negocio Seafood | I19: =VLOOKUP(A19,BBDD!$1:$1048653,16,0) -> Temporada (Con ocasión Temporada de Pesca) | J19: =VLOOKUP(A19,BBDD!$1:$1048653,17,0) | K19: =VLOOKUP(A19,BBDD!$1:$1048653,12,0) -> 45931 | L19: =VLOOKUP(A19,BBDD!$1:$1048653,3,0) -> Orizon S.A | M19: =VLOOKUP(A19,BBDD!$1:$1048653,4,0) -> F5 | N19: =VLOOKUP(A19,BBDD!$1:$1048653,5,0) -> crisgonzalez@cftla.cl | O19: 45953 | P19: Oficina | Q19: Remuneraciones | R19: Cambio cuenta bancaria | T19: Cerrado
A20: 18414706 | B20: =VLOOKUP(A20,BBDD!$1:$1048653,2,0) -> 18.414.706-8 | C20: =VLOOKUP(A20,BBDD!$1:$1048653,7,0) -> Zapata Gutierrez Dieter Ismael | D20: =VLOOKUP(A20,BBDD!$1:$1048653,8,0) -> Laboratorista Aseguramiento Calidad | E20: =VLOOKUP(A20,BBDD!$1:$1048653,10,0) -> Gerencia Gestión Integrada y Calidad | F20: =VLOOKUP(A20,BBDD!$1:$1048653,11,0) -> Plazo fijo | G20: =VLOOKUP(A20,BBDD!$1:$1048653,13,0) -> Coronel Rol Tierra | H20: =VLOOKUP(A20,BBDD!$1:$1048653,14,0) -> Gerencia Corp. Negocio Seafood | I20: =VLOOKUP(A20,BBDD!$1:$1048653,16,0) -> Temporada (Con ocasión Temporada de Pesca) | J20: =VLOOKUP(A20,BBDD!$1:$1048653,17,0) | K20: =VLOOKUP(A20,BBDD!$1:$1048653,12,0) -> 45933 | L20: =VLOOKUP(A20,BBDD!$1:$1048653,3,0) -> Orizon S.A | M20: =VLOOKUP(A20,BBDD!$1:$1048653,4,0) -> F4 | N20: =VLOOKUP(A20,BBDD!$1:$1048653,5,0) -> DIETER.ZAPATA@GMAIL.COM | O20: 45953 | P20: Oficina | Q20: Contrato | R20: Cargar en Buk | S20: Contrato cargado Milton y Dieter ok | T20: Cerrado
A21: 15196579 | B21: =VLOOKUP(A21,BBDD!$1:$1048653,2,0) -> 15.196.579-2 | C21: =VLOOKUP(A21,BBDD!$1:$1048653,7,0) -> Huerta Miranda Mirian Andrea | D21: =VLOOKUP(A21,BBDD!$1:$1048653,8,0) -> Operario Apoyo Elaboracion | E21: =VLOOKUP(A21,BBDD!$1:$1048653,10,0) -> Gerencia Producción Pesca | F21: =VLOOKUP(A21,BBDD!$1:$1048653,11,0) -> Plazo fijo | G21: =VLOOKUP(A21,BBDD!$1:$1048653,13,0) -> Coronel Rol Eventual | H21: =VLOOKUP(A21,BBDD!$1:$1048653,14,0) -> Gerencia Corp. Negocio Seafood | I21: =VLOOKUP(A21,BBDD!$1:$1048653,16,0) -> Temporada (Con ocasión Temporada de Pesca) | J21: =VLOOKUP(A21,BBDD!$1:$1048653,17,0) | K21: =VLOOKUP(A21,BBDD!$1:$1048653,12,0) -> 45941 | L21: =VLOOKUP(A21,BBDD!$1:$1048653,3,0) -> Orizon S.A | M21: =VLOOKUP(A21,BBDD!$1:$1048653,4,0) -> F1 | N21: =VLOOKUP(A21,BBDD!$1:$1048653,5,0) -> andrehm416@gmail.com | O21: 45953 | P21: Oficina | Q21: Asistencia | T21: Cerrado
A22: 17228845 | B22: 17228845-6 | C22: =VLOOKUP(A22,BBDD!$1:$1048653,7,0) -> Espina Sandoval Debora Alejandra | D22: =VLOOKUP(A22,BBDD!$1:$1048653,8,0) -> Operario Apoyo Elaboracion | E22: =VLOOKUP(A22,BBDD!$1:$1048653,10,0) -> Gerencia Producción Pesca | F22: =VLOOKUP(A22,BBDD!$1:$1048653,11,0) -> Plazo fijo | G22: =VLOOKUP(A22,BBDD!$1:$1048653,13,0) -> Coronel Rol Eventual | H22: =VLOOKUP(A22,BBDD!$1:$1048653,14,0) -> Gerencia Corp. Negocio Seafood | I22: =VLOOKUP(A22,BBDD!$1:$1048653,16,0) -> Temporada (Con ocasión Temporada de Pesca) | J22: =VLOOKUP(A22,BBDD!$1:$1048653,17,0) | K22: =VLOOKUP(A22,BBDD!$1:$1048653,12,0) -> 45941 | L22: =VLOOKUP(A22,BBDD!$1:$1048653,3,0) -> Orizon S.A | M22: =VLOOKUP(A22,BBDD!$1:$1048653,4,0) -> F1 | N22: =VLOOKUP(A22,BBDD!$1:$1048653,5,0) -> espinadebora7@gmail.com | O22: 45953 | P22: Oficina | Q22: Remuneraciones | R22: Cambio cuenta bancaria | S22: Cambio realizado | T22: Cerrado
A23: 21658470 | B23: =VLOOKUP(A23,BBDD!$1:$1048653,2,0) -> 21.658.470-8 | C23: =VLOOKUP(A23,BBDD!$1:$1048653,7,0) -> Aravena Fuentealba Javier Natahel | D23: =VLOOKUP(A23,BBDD!$1:$1048653,8,0) -> Operador Elaboracion Php | E23: =VLOOKUP(A23,BBDD!$1:$1048653,10,0) -> Gerencia Producción Pesca | F23: =VLOOKUP(A23,BBDD!$1:$1048653,11,0) -> Plazo fijo | G23: =VLOOKUP(A23,BBDD!$1:$1048653,13,0) -> Coronel Rol Tierra | H23: =VLOOKUP(A23,BBDD!$1:$1048653,14,0) -> Gerencia Corp. Negocio Seafood | I23: =VLOOKUP(A23,BBDD!$1:$1048653,16,0) -> Temporada (Con ocasión Temporada de Pesca) | J23: =VLOOKUP(A23,BBDD!$1:$1048653,17,0) | K23: =VLOOKUP(A23,BBDD!$1:$1048653,12,0) -> 45933 | L23: =VLOOKUP(A23,BBDD!$1:$1048653,3,0) -> Orizon S.A | M23: =VLOOKUP(A23,BBDD!$1:$1048653,4,0) -> F4 | N23: =VLOOKUP(A23,BBDD!$1:$1048653,5,0) -> JAVIERFUENTEALBA303@GMAIL.COM | O23: 45953 | P23: Oficina | Q23: Contrato | R23: Cargar en Buk | T23: Cerrado
A24: 20512923 | B24: =VLOOKUP(A24,BBDD!$1:$1048653,2,0) -> 20.512.923-5 | C24: =VLOOKUP(A24,BBDD!$1:$1048653,7,0) -> Morales Alvarez Carlos Patricio | D24: =VLOOKUP(A24,BBDD!$1:$1048653,8,0) -> Operario Apoyo Elaboracion | E24: =VLOOKUP(A24,BBDD!$1:$1048653,10,0) -> Gerencia Producción Pesca | F24: =VLOOKUP(A24,BBDD!$1:$1048653,11,0) -> Plazo fijo | G24: =VLOOKUP(A24,BBDD!$1:$1048653,13,0) -> Coronel Rol Eventual | H24: =VLOOKUP(A24,BBDD!$1:$1048653,14,0) -> Gerencia Corp. Negocio Seafood | I24: =VLOOKUP(A24,BBDD!$1:$1048653,16,0) -> Temporada (Con ocasión Temporada de Pesca) | J24: =VLOOKUP(A24,BBDD!$1:$1048653,17,0) | K24: =VLOOKUP(A24,BBDD!$1:$1048653,12,0) -> 45940 | L24: =VLOOKUP(A24,BBDD!$1:$1048653,3,0) -> Orizon S.A | M24: =VLOOKUP(A24,BBDD!$1:$1048653,4,0) -> F2 | N24: =VLOOKUP(A24,BBDD!$1:$1048653,5,0) -> cm0828458@gmail.com | O24: 45953 | P24: Oficina | Q24: Asistencia | R24: No puede marcar | S24: Derivado a control tiempo | T24: Cerrado
A25: 16009687 | B25: =VLOOKUP(A25,BBDD!$1:$1048653,2,0) -> 16.009.687-k | C25: =VLOOKUP(A25,BBDD!$1:$1048653,7,0) -> Muñoz Muñoz Viviana Elizabeth | D25: =VLOOKUP(A25,BBDD!$1:$1048653,8,0) -> Operario Apoyo Elaboracion | E25: =VLOOKUP(A25,BBDD!$1:$1048653,10,0) -> Gerencia Producción Pesca | F25: =VLOOKUP(A25,BBDD!$1:$1048653,11,0) -> Plazo fijo | G25: =VLOOKUP(A25,BBDD!$1:$1048653,13,0) -> Coronel Rol Eventual | H25: =VLOOKUP(A25,BBDD!$1:$1048653,14,0) -> Gerencia Corp. Negocio Seafood | I25: =VLOOKUP(A25,BBDD!$1:$1048653,16,0) -> Temporada (Con ocasión Temporada de Pesca) | J25: =VLOOKUP(A25,BBDD!$1:$1048653,17,0) | K25: =VLOOKUP(A25,BBDD!$1:$1048653,12,0) -> 45942 | L25: =VLOOKUP(A25,BBDD!$1:$1048653,3,0) -> Orizon S.A | M25: =VLOOKUP(A25,BBDD!$1:$1048653,4,0) -> F3 | N25: =VLOOKUP(A25,BBDD!$1:$1048653,5,0) -> x.abrazame@hotmail.com | O25: 45953 | P25: Oficina | Q25: Asignación Familiar | R25: Incorporación de carga | S25: Pendiente documentación trbajador | T25: Abierto
A26: 27046927 | B26: =VLOOKUP(A26,BBDD!$1:$1048653,2,0) -> 27.046.927-2 | C26: =VLOOKUP(A26,BBDD!$1:$1048653,7,0) -> Colina Atacho Henyerber Jose | D26: =VLOOKUP(A26,BBDD!$1:$1048653,8,0) -> Operario Apoyo Elaboracion | E26: =VLOOKUP(A26,BBDD!$1:$1048653,10,0) -> Gerencia Producción Pesca | F26: =VLOOKUP(A26,BBDD!$1:$1048653,11,0) -> Plazo fijo | G26: =VLOOKUP(A26,BBDD!$1:$1048653,13,0) -> Coronel Rol Eventual | H26: =VLOOKUP(A26,BBDD!$1:$1048653,14,0) -> Gerencia Corp. Negocio Seafood | I26: =VLOOKUP(A26,BBDD!$1:$1048653,16,0) -> Temporada (Con ocasión Temporada de Pesca) | J26: =VLOOKUP(A26,BBDD!$1:$1048653,17,0) | K26: =VLOOKUP(A26,BBDD!$1:$1048653,12,0) -> 45931 | L26: =VLOOKUP(A26,BBDD!$1:$1048653,3,0) -> Orizon S.A | M26: =VLOOKUP(A26,BBDD!$1:$1048653,4,0) -> F2 | N26: =VLOOKUP(A26,BBDD!$1:$1048653,5,0) -> chuchocolina@gmail.com | O26: 45953 | P26: Oficina | Q26: Asistencia | R26: No puede marcar reloj de la consera | S26: Seguira marcando en reloj del hall | T26: Cerrado
A27: 20785939 | B27: =VLOOKUP(A27,BBDD!$1:$1048653,2,0) -> 20.785.939-7 | C27: =VLOOKUP(A27,BBDD!$1:$1048653,7,0) -> Palma Elevancin Hector Juan Pablo | D27: =VLOOKUP(A27,BBDD!$1:$1048653,8,0) -> Operador Control Producción | E27: =VLOOKUP(A27,BBDD!$1:$1048653,10,0) -> Gerencia Producción Pesca | F27: =VLOOKUP(A27,BBDD!$1:$1048653,11,0) -> Plazo fijo | G27: =VLOOKUP(A27,BBDD!$1:$1048653,13,0) -> Coronel Rol Eventual | H27: =VLOOKUP(A27,BBDD!$1:$1048653,14,0) -> Gerencia Corp. Negocio Seafood | I27: =VLOOKUP(A27,BBDD!$1:$1048653,16,0) -> Temporada (Con ocasión Temporada de Pesca) | J27: =VLOOKUP(A27,BBDD!$1:$1048653,17,0) | K27: =VLOOKUP(A27,BBDD!$1:$1048653,12,0) -> 45950 | L27: =VLOOKUP(A27,BBDD!$1:$1048653,3,0) -> Orizon S.A | M27: =VLOOKUP(A27,BBDD!$1:$1048653,4,0) -> F1 | N27: =VLOOKUP(A27,BBDD!$1:$1048653,5,0) -> Palmaelevancin0@gmail.com | O27: 45953 | P27: Oficina | Q27: Contrato | T27: Cerrado
A28: 17571642 | B28: =VLOOKUP(A28,BBDD!$1:$1048653,2,0) -> 17.571.642-4 | C28: =VLOOKUP(A28,BBDD!$1:$1048653,7,0) -> Bermedo Vargas Ninoska Alejandra | D28: =VLOOKUP(A28,BBDD!$1:$1048653,8,0) -> Operario Apoyo Elaboracion | E28: =VLOOKUP(A28,BBDD!$1:$1048653,10,0) -> Gerencia Producción Pesca | F28: =VLOOKUP(A28,BBDD!$1:$1048653,11,0) -> Plazo fijo | G28: =VLOOKUP(A28,BBDD!$1:$1048653,13,0) -> Coronel Rol Eventual | H28: =VLOOKUP(A28,BBDD!$1:$1048653,14,0) -> Gerencia Corp. Negocio Seafood | I28: =VLOOKUP(A28,BBDD!$1:$1048653,16,0) -> Temporada (Con ocasión Temporada de Pesca) | J28: =VLOOKUP(A28,BBDD!$1:$1048653,17,0) | K28: =VLOOKUP(A28,BBDD!$1:$1048653,12,0) -> 45931 | L28: =VLOOKUP(A28,BBDD!$1:$1048653,3,0) -> Orizon S.A | M28: =VLOOKUP(A28,BBDD!$1:$1048653,4,0) -> F4 | N28: =VLOOKUP(A28,BBDD!$1:$1048653,5,0) -> nino.bermedo@hotmail.com | O28: 45953 | P28: E-mail | Q28: Asistencia | R28: Trabajador informa de ausencia por asalto mientras iba a tomar transporte | S28: PSG ,dja constacia en carabineros | T28: Cerrado
A29: 1 | B29: =VLOOKUP(A29,BBDD!$1:$1048653,2,0) -> Usuario Externo | C29: =VLOOKUP(A29,BBDD!$1:$1048653,7,0) -> Usuario Externo | D29: =VLOOKUP(A29,BBDD!$1:$1048653,8,0) -> Usuario Externo | E29: =VLOOKUP(A29,BBDD!$1:$1048653,10,0) -> Usuario Externo | F29: =VLOOKUP(A29,BBDD!$1:$1048653,11,0) -> Usuario Externo | G29: =VLOOKUP(A29,BBDD!$1:$1048653,13,0) -> Usuario Externo | H29: =VLOOKUP(A29,BBDD!$1:$1048653,14,0) -> Usuario Externo | I29: =VLOOKUP(A29,BBDD!$1:$1048653,16,0) -> Usuario Externo | J29: =VLOOKUP(A29,BBDD!$1:$1048653,17,0) | K29: =VLOOKUP(A29,BBDD!$1:$1048653,12,0) -> Usuario Externo | L29: =VLOOKUP(A29,BBDD!$1:$1048653,3,0) -> Usuario Externo | M29: =VLOOKUP(A29,BBDD!$1:$1048653,4,0) -> Usuario Externo | N29: =VLOOKUP(A29,BBDD!$1:$1048653,5,0) -> Usuario Externo | O29: 45953 | P29: Teléfono | Q29: Otro | R29: Trabajador informa que aplicación de buk le señala Adriana Katherine | T29: Abierto
A30: 14361771 | B30: =VLOOKUP(A30,BBDD!$1:$1048653,2,0) -> 14.361.771-8 | C30: =VLOOKUP(A30,BBDD!$1:$1048653,7,0) -> Flores Abarca Araceli De Las Mercedes | D30: =VLOOKUP(A30,BBDD!$1:$1048653,8,0) -> Operario Apoyo Elaboracion | E30: =VLOOKUP(A30,BBDD!$1:$1048653,10,0) -> Gerencia Producción Pesca | F30: =VLOOKUP(A30,BBDD!$1:$1048653,11,0) -> Plazo fijo | G30: =VLOOKUP(A30,BBDD!$1:$1048653,13,0) -> Coronel Rol Eventual | H30: =VLOOKUP(A30,BBDD!$1:$1048653,14,0) -> Gerencia Corp. Negocio Seafood | I30: =VLOOKUP(A30,BBDD!$1:$1048653,16,0) -> Temporada (Con ocasión Temporada de Pesca) | J30: =VLOOKUP(A30,BBDD!$1:$1048653,17,0) | K30: =VLOOKUP(A30,BBDD!$1:$1048653,12,0) -> 45931 | L30: =VLOOKUP(A30,BBDD!$1:$1048653,3,0) -> Orizon S.A | M30: =VLOOKUP(A30,BBDD!$1:$1048653,4,0) -> F3 | N30: =VLOOKUP(A30,BBDD!$1:$1048653,5,0) -> araceli.10abarca@gmail.com | O30: 45954 | P30: Oficina | Q30: Asistencia | R30: Entrega documeto por inasistencia | T30: Cerrado
A31: 20613170 | B31: =VLOOKUP(A31,BBDD!$1:$1048653,2,0) -> 20.613.170-5 | C31: =VLOOKUP(A31,BBDD!$1:$1048653,7,0) -> Carrasco Copelli Valentin Patricio | D31: =VLOOKUP(A31,BBDD!$1:$1048653,8,0) -> Operador De Autoclaves | E31: =VLOOKUP(A31,BBDD!$1:$1048653,10,0) -> Gerencia Producción Pesca | F31: =VLOOKUP(A31,BBDD!$1:$1048653,11,0) -> Indefinido | G31: =VLOOKUP(A31,BBDD!$1:$1048653,13,0) -> Coronel Rol Tierra | H31: =VLOOKUP(A31,BBDD!$1:$1048653,14,0) -> Gerencia Corp. Negocio Seafood | I31: =VLOOKUP(A31,BBDD!$1:$1048653,16,0) -> Rol General (Cargo permanente o proyección indefinido) | J31: =VLOOKUP(A31,BBDD!$1:$1048653,17,0) | K31: =VLOOKUP(A31,BBDD!$1:$1048653,12,0) -> 44531 | L31: =VLOOKUP(A31,BBDD!$1:$1048653,3,0) -> Orizon S.A | M31: =VLOOKUP(A31,BBDD!$1:$1048653,4,0) -> F1 | N31: =VLOOKUP(A31,BBDD!$1:$1048653,5,0) -> valentincarrascocopelli1010@gmail.com | O31: 45954 | P31: Oficina | Q31: Asistencia | T31: Cerrado
A32: 1 | B32: =VLOOKUP(A32,BBDD!$1:$1048653,2,0) -> Usuario Externo | C32: =VLOOKUP(A32,BBDD!$1:$1048653,7,0) -> Usuario Externo | D32: =VLOOKUP(A32,BBDD!$1:$1048653,8,0) -> Usuario Externo | E32: =VLOOKUP(A32,BBDD!$1:$1048653,10,0) -> Usuario Externo | F32: =VLOOKUP(A32,BBDD!$1:$1048653,11,0) -> Usuario Externo | G32: =VLOOKUP(A32,BBDD!$1:$1048653,13,0) -> Usuario Externo | H32: =VLOOKUP(A32,BBDD!$1:$1048653,14,0) -> Usuario Externo | I32: =VLOOKUP(A32,BBDD!$1:$1048653,16,0) -> Usuario Externo | J32: =VLOOKUP(A32,BBDD!$1:$1048653,17,0) | K32: =VLOOKUP(A32,BBDD!$1:$1048653,12,0) -> Usuario Externo | L32: =VLOOKUP(A32,BBDD!$1:$1048653,3,0) -> Usuario Externo | M32: =VLOOKUP(A32,BBDD!$1:$1048653,4,0) -> Usuario Externo | N32: =VLOOKUP(A32,BBDD!$1:$1048653,5,0) -> Usuario Externo | O32: 45954 | P32: Oficina | Q32: Asistencia | T32: Cerrado
A33: 1 | B33: =VLOOKUP(A33,BBDD!$1:$1048653,2,0) -> Usuario Externo | C33: =VLOOKUP(A33,BBDD!$1:$1048653,7,0) -> Usuario Externo | D33: =VLOOKUP(A33,BBDD!$1:$1048653,8,0) -> Usuario Externo | E33: =VLOOKUP(A33,BBDD!$1:$1048653,10,0) -> Usuario Externo | F33: =VLOOKUP(A33,BBDD!$1:$1048653,11,0) -> Usuario Externo | G33: =VLOOKUP(A33,BBDD!$1:$1048653,13,0) -> Usuario Externo | H33: =VLOOKUP(A33,BBDD!$1:$1048653,14,0) -> Usuario Externo | I33: =VLOOKUP(A33,BBDD!$1:$1048653,16,0) -> Usuario Externo | J33: =VLOOKUP(A33,BBDD!$1:$1048653,17,0) | K33: =VLOOKUP(A33,BBDD!$1:$1048653,12,0) -> Usuario Externo | L33: =VLOOKUP(A33,BBDD!$1:$1048653,3,0) -> Usuario Externo | M33: =VLOOKUP(A33,BBDD!$1:$1048653,4,0) -> Usuario Externo | N33: =VLOOKUP(A33,BBDD!$1:$1048653,5,0) -> Usuario Externo | O33: 45954 | P33: Oficina | Q33: Contrato | R33: Pendiente Jonathan Mella | T33: Abierto
A34: 17690284 | B34: =VLOOKUP(A34,BBDD!$1:$1048653,2,0) -> 17.690.284-1 | C34: =VLOOKUP(A34,BBDD!$1:$1048653,7,0) -> Navarro Marmiez Stephanie Nicole | D34: =VLOOKUP(A34,BBDD!$1:$1048653,8,0) -> Encargado(A) Logistico I | E34: =VLOOKUP(A34,BBDD!$1:$1048653,10,0) -> Gerencia Logistica | F34: =VLOOKUP(A34,BBDD!$1:$1048653,11,0) -> Indefinido | G34: =VLOOKUP(A34,BBDD!$1:$1048653,13,0) -> Coronel Rol Tierra | H34: =VLOOKUP(A34,BBDD!$1:$1048653,14,0) -> Gerencia Corp. Supply Chain | I34: =VLOOKUP(A34,BBDD!$1:$1048653,16,0) -> Rol General (Cargo permanente o proyección indefinido) | J34: =VLOOKUP(A34,BBDD!$1:$1048653,17,0) | K34: =VLOOKUP(A34,BBDD!$1:$1048653,12,0) -> 42736 | L34: =VLOOKUP(A34,BBDD!$1:$1048653,3,0) -> Orizon S.A | M34: =VLOOKUP(A34,BBDD!$1:$1048653,4,0) -> F1 | N34: =VLOOKUP(A34,BBDD!$1:$1048653,5,0) -> stephanie.navarro@orizon.cl | O34: 45954 | P34: Oficina | Q34: Credencial | R34: Solicita Credencial para su equipo, no hay impresora | S34: Esperar a que lleguen insumos y actualizar sus fotos de equipo | T34: Abierto
A35: 10072688 | B35: =VLOOKUP(A35,BBDD!$1:$1048653,2,0) -> 10.072.688-2 | C35: =VLOOKUP(A35,BBDD!$1:$1048653,7,0) -> Bustos Delgado Elbert Billy | D35: =VLOOKUP(A35,BBDD!$1:$1048653,8,0) -> Tripulante | E35: =VLOOKUP(A35,BBDD!$1:$1048653,10,0) -> Gerencia de Flota y Abastecimiento de Materias Primas | F35: =VLOOKUP(A35,BBDD!$1:$1048653,11,0) -> Indefinido | G35: =VLOOKUP(A35,BBDD!$1:$1048653,13,0) -> Coronel Rol Flota | H35: =VLOOKUP(A35,BBDD!$1:$1048653,14,0) -> Gerencia Corp. Negocio Seafood | I35: =VLOOKUP(A35,BBDD!$1:$1048653,16,0) -> Rol General (Cargo permanente o proyección indefinido) | J35: =VLOOKUP(A35,BBDD!$1:$1048653,17,0) | K35: =VLOOKUP(A35,BBDD!$1:$1048653,12,0) -> 45603 | L35: =VLOOKUP(A35,BBDD!$1:$1048653,3,0) -> Orizon S.A | M35: =VLOOKUP(A35,BBDD!$1:$1048653,4,0) -> F1 | N35: =VLOOKUP(A35,BBDD!$1:$1048653,5,0) -> billylosrios2@gmail.com | O35: 45954 | P35: Oficina | Q35: Seguro de Salud | R35: Solicita informacion de beneficios y incorporacion del seguro | S35: se envio informacion para incorporacion a euroamerica | T35: Abierto
A36: 12703195 | B36: =VLOOKUP(A36,BBDD!$1:$1048653,2,0) -> 12.703.195-9 | C36: =VLOOKUP(A36,BBDD!$1:$1048653,7,0) -> Rios Soto Angelo Enrique | D36: =VLOOKUP(A36,BBDD!$1:$1048653,8,0) -> Monitor(A) De Calidad | E36: =VLOOKUP(A36,BBDD!$1:$1048653,10,0) -> Gerencia Gestión Integrada y Calidad | F36: =VLOOKUP(A36,BBDD!$1:$1048653,11,0) -> Indefinido | G36: =VLOOKUP(A36,BBDD!$1:$1048653,13,0) -> Coronel Rol Tierra | H36: =VLOOKUP(A36,BBDD!$1:$1048653,14,0) -> Gerencia Corp. Negocio Seafood | I36: =VLOOKUP(A36,BBDD!$1:$1048653,16,0) -> Rol General (Cargo permanente o proyección indefinido) | J36: =VLOOKUP(A36,BBDD!$1:$1048653,17,0) | K36: =VLOOKUP(A36,BBDD!$1:$1048653,12,0) -> 42618 | L36: =VLOOKUP(A36,BBDD!$1:$1048653,3,0) -> Orizon S.A | M36: =VLOOKUP(A36,BBDD!$1:$1048653,4,0) -> F1 | N36: =VLOOKUP(A36,BBDD!$1:$1048653,5,0) -> foxtrot.angers@gmail.com | O36: 45954 | P36: Oficina | Q36: Vestimenta y EPP | R36: cambio de talla | T36: Cerrado
A37: 1 | B37: =VLOOKUP(A37,BBDD!$1:$1048653,2,0) -> Usuario Externo | C37: =VLOOKUP(A37,BBDD!$1:$1048653,7,0) -> Usuario Externo | D37: =VLOOKUP(A37,BBDD!$1:$1048653,8,0) -> Usuario Externo | E37: =VLOOKUP(A37,BBDD!$1:$1048653,10,0) -> Usuario Externo | F37: =VLOOKUP(A37,BBDD!$1:$1048653,11,0) -> Usuario Externo | G37: =VLOOKUP(A37,BBDD!$1:$1048653,13,0) -> Usuario Externo | H37: =VLOOKUP(A37,BBDD!$1:$1048653,14,0) -> Usuario Externo | I37: =VLOOKUP(A37,BBDD!$1:$1048653,16,0) -> Usuario Externo | J37: =VLOOKUP(A37,BBDD!$1:$1048653,17,0) | K37: =VLOOKUP(A37,BBDD!$1:$1048653,12,0) -> Usuario Externo | L37: =VLOOKUP(A37,BBDD!$1:$1048653,3,0) -> Usuario Externo | M37: =VLOOKUP(A37,BBDD!$1:$1048653,4,0) -> Usuario Externo | N37: =VLOOKUP(A37,BBDD!$1:$1048653,5,0) -> Usuario Externo | O37: 45954 | P37: Oficina | Q37: Reclutamiento y Selección | R37: Consulta por personal de reclutamiento | S37: Se indica correo de reclutamiento | T37: Cerrado
A38: 1 | B38: =VLOOKUP(A38,BBDD!$1:$1048653,2,0) -> Usuario Externo | C38: =VLOOKUP(A38,BBDD!$1:$1048653,7,0) -> Usuario Externo | D38: =VLOOKUP(A38,BBDD!$1:$1048653,8,0) -> Usuario Externo | E38: =VLOOKUP(A38,BBDD!$1:$1048653,10,0) -> Usuario Externo | F38: =VLOOKUP(A38,BBDD!$1:$1048653,11,0) -> Usuario Externo | G38: =VLOOKUP(A38,BBDD!$1:$1048653,13,0) -> Usuario Externo | H38: =VLOOKUP(A38,BBDD!$1:$1048653,14,0) -> Usuario Externo | I38: =VLOOKUP(A38,BBDD!$1:$1048653,16,0) -> Usuario Externo | J38: =VLOOKUP(A38,BBDD!$1:$1048653,17,0) | K38: =VLOOKUP(A38,BBDD!$1:$1048653,12,0) -> Usuario Externo | L38: =VLOOKUP(A38,BBDD!$1:$1048653,3,0) -> Usuario Externo | M38: =VLOOKUP(A38,BBDD!$1:$1048653,4,0) -> Usuario Externo | N38: =VLOOKUP(A38,BBDD!$1:$1048653,5,0) -> Usuario Externo | O38: 45954 | P38: Oficina | Q38: Reclutamiento y Selección | R38: consulta por practica laboral | S38: Derivado a Karina Cruces | T38: Cerrado
A39: 16039446 | B39: =VLOOKUP(A39,BBDD!$1:$1048653,2,0) -> 16.039.446-3 | C39: =VLOOKUP(A39,BBDD!$1:$1048653,7,0) -> Bastias Quezada Francisco Andres | D39: =VLOOKUP(A39,BBDD!$1:$1048653,8,0) -> Motorista | E39: =VLOOKUP(A39,BBDD!$1:$1048653,10,0) -> Gerencia de Flota y Abastecimiento de Materias Primas | F39: =VLOOKUP(A39,BBDD!$1:$1048653,11,0) -> Indefinido | G39: =VLOOKUP(A39,BBDD!$1:$1048653,13,0) -> Coronel Rol Flota | H39: =VLOOKUP(A39,BBDD!$1:$1048653,14,0) -> Gerencia Corp. Negocio Seafood | I39: =VLOOKUP(A39,BBDD!$1:$1048653,16,0) -> Rol General (Cargo permanente o proyección indefinido) | J39: =VLOOKUP(A39,BBDD!$1:$1048653,17,0) | K39: =VLOOKUP(A39,BBDD!$1:$1048653,12,0) -> 41047 | L39: =VLOOKUP(A39,BBDD!$1:$1048653,3,0) -> Orizon S.A | M39: =VLOOKUP(A39,BBDD!$1:$1048653,4,0) -> F1 | N39: =VLOOKUP(A39,BBDD!$1:$1048653,5,0) -> francisco.bastias19@gmail.com | O39: 45954 | P39: Teléfono | Q39: Beneficios | R39: Acceso portal Mirax, elección de regalo | S39: Enviar correo a personas.biobio@nutrisco.com | T39: Cerrado
A40: 1 | B40: 16328477-4 | C40: =VLOOKUP(A40,BBDD!$1:$1048653,7,0) -> Usuario Externo | D40: =VLOOKUP(A40,BBDD!$1:$1048653,8,0) -> Usuario Externo | E40: =VLOOKUP(A40,BBDD!$1:$1048653,10,0) -> Usuario Externo | F40: =VLOOKUP(A40,BBDD!$1:$1048653,11,0) -> Usuario Externo | G40: =VLOOKUP(A40,BBDD!$1:$1048653,13,0) -> Usuario Externo | H40: =VLOOKUP(A40,BBDD!$1:$1048653,14,0) -> Usuario Externo | I40: =VLOOKUP(A40,BBDD!$1:$1048653,16,0) -> Usuario Externo | J40: =VLOOKUP(A40,BBDD!$1:$1048653,17,0) | K40: =VLOOKUP(A40,BBDD!$1:$1048653,12,0) -> Usuario Externo | L40: =VLOOKUP(A40,BBDD!$1:$1048653,3,0) -> Usuario Externo | M40: =VLOOKUP(A40,BBDD!$1:$1048653,4,0) -> Usuario Externo | N40: =VLOOKUP(A40,BBDD!$1:$1048653,5,0) -> Usuario Externo | O40: 45954 | P40: Oficina | Q40: Asistencia | R40: Horas extras y cambio de empresa | S40: enviada la informacion de las horas y cambio de empresa EST | T40: Cerrado
A41: 1 | B41: 13311551-k | C41: =VLOOKUP(A41,BBDD!$1:$1048653,7,0) -> Usuario Externo | D41: =VLOOKUP(A41,BBDD!$1:$1048653,8,0) -> Usuario Externo | E41: =VLOOKUP(A41,BBDD!$1:$1048653,10,0) -> Usuario Externo | F41: =VLOOKUP(A41,BBDD!$1:$1048653,11,0) -> Usuario Externo | G41: =VLOOKUP(A41,BBDD!$1:$1048653,13,0) -> Usuario Externo | H41: =VLOOKUP(A41,BBDD!$1:$1048653,14,0) -> Usuario Externo | I41: =VLOOKUP(A41,BBDD!$1:$1048653,16,0) -> Usuario Externo | J41: =VLOOKUP(A41,BBDD!$1:$1048653,17,0) | K41: =VLOOKUP(A41,BBDD!$1:$1048653,12,0) -> Usuario Externo | L41: =VLOOKUP(A41,BBDD!$1:$1048653,3,0) -> Usuario Externo | M41: =VLOOKUP(A41,BBDD!$1:$1048653,4,0) -> Usuario Externo | N41: =VLOOKUP(A41,BBDD!$1:$1048653,5,0) -> Usuario Externo | O41: 45954 | P41: Oficina | Q41: Remuneraciones | R41: Horas extras y cambio de empresa | S41: enviada la informacion de las horas y cambio de empresa EST | T41: Cerrado
A42: 19578476 | B42: =VLOOKUP(A42,BBDD!$1:$1048653,2,0) -> 19.578.476-0 | C42: =VLOOKUP(A42,BBDD!$1:$1048653,7,0) -> Salazar Parra Daniela Andrea | D42: =VLOOKUP(A42,BBDD!$1:$1048653,8,0) -> Operario Apoyo Elaboracion | E42: =VLOOKUP(A42,BBDD!$1:$1048653,10,0) -> Gerencia Producción Pesca | F42: =VLOOKUP(A42,BBDD!$1:$1048653,11,0) -> Plazo fijo | G42: =VLOOKUP(A42,BBDD!$1:$1048653,13,0) -> Coronel Rol Eventual | H42: =VLOOKUP(A42,BBDD!$1:$1048653,14,0) -> Gerencia Corp. Negocio Seafood | I42: =VLOOKUP(A42,BBDD!$1:$1048653,16,0) -> Temporada (Con ocasión Temporada de Pesca) | J42: =VLOOKUP(A42,BBDD!$1:$1048653,17,0) | K42: =VLOOKUP(A42,BBDD!$1:$1048653,12,0) -> 45945 | L42: =VLOOKUP(A42,BBDD!$1:$1048653,3,0) -> Orizon S.A | M42: =VLOOKUP(A42,BBDD!$1:$1048653,4,0) -> F4 | N42: =VLOOKUP(A42,BBDD!$1:$1048653,5,0) -> PARRAS241@GMAIL.COM | O42: 45954 | P42: Oficina | Q42: Beneficios | R42: Despacharon antes y requiere saber si puede esperar el movil | S42: Derivada al encargado de transporte Ruben Montaña | T42: Cerrado
A43: 19521124 | B43: 19521124-8 | C43: sepulveda flores franco | D43: Aspirante a tripulante | E43: =VLOOKUP(A43,BBDD!$1:$1048653,10,0) -> #N/A | F43: =VLOOKUP(A43,BBDD!$1:$1048653,11,0) -> #N/A | G43: =VLOOKUP(A43,BBDD!$1:$1048653,13,0) -> #N/A | H43: =VLOOKUP(A43,BBDD!$1:$1048653,14,0) -> #N/A | I43: =VLOOKUP(A43,BBDD!$1:$1048653,16,0) -> #N/A | J43: =VLOOKUP(A43,BBDD!$1:$1048653,17,0) -> #N/A | K43: =VLOOKUP(A43,BBDD!$1:$1048653,12,0) -> #N/A | L43: =VLOOKUP(A43,BBDD!$1:$1048653,3,0) -> #N/A | M43: =VLOOKUP(A43,BBDD!$1:$1048653,4,0) -> #N/A | N43: francoe.sflores@gmail.com | O43: 45954 | P43: Oficina | Q43: Contrato | R43: Activacion de cuenta y firna de documentos | S43: activacion y firma de documentos | T43: Cerrado
A44: 10109970 | B44: =VLOOKUP(A44,BBDD!$1:$1048653,2,0) -> 10.109.970-9 | C44: =VLOOKUP(A44,BBDD!$1:$1048653,7,0) -> Paredes Gutierrez Luis Octavio | D44: =VLOOKUP(A44,BBDD!$1:$1048653,8,0) -> Electrico De Turno | E44: =VLOOKUP(A44,BBDD!$1:$1048653,10,0) -> Departamento Ingeniería | F44: =VLOOKUP(A44,BBDD!$1:$1048653,11,0) -> Indefinido | G44: =VLOOKUP(A44,BBDD!$1:$1048653,13,0) -> Coronel Rol Tierra | H44: =VLOOKUP(A44,BBDD!$1:$1048653,14,0) -> Gerencia Corp. Negocio Seafood | I44: =VLOOKUP(A44,BBDD!$1:$1048653,16,0) -> Rol General (Cargo permanente o proyección indefinido) | J44: =VLOOKUP(A44,BBDD!$1:$1048653,17,0) | K44: =VLOOKUP(A44,BBDD!$1:$1048653,12,0) -> 40513 | L44: =VLOOKUP(A44,BBDD!$1:$1048653,3,0) -> Orizon S.A | M44: =VLOOKUP(A44,BBDD!$1:$1048653,4,0) -> F1 | N44: =VLOOKUP(A44,BBDD!$1:$1048653,5,0) -> luisparedesgut.lp@gmail.com | O44: 45954 | P44: Oficina | Q44: Vestimenta y EPP | R44: recuperacion de codigo ropa | T44: Cerrado
A45: 7392021 | B45: =VLOOKUP(A45,BBDD!$1:$1048653,2,0) -> 7.392.021-3 | C45: =VLOOKUP(A45,BBDD!$1:$1048653,7,0) -> Carrillo Baeza Alex Alejandro | D45: =VLOOKUP(A45,BBDD!$1:$1048653,8,0) -> Piloto | E45: =VLOOKUP(A45,BBDD!$1:$1048653,10,0) -> Gerencia de Flota y Abastecimiento de Materias Primas | F45: =VLOOKUP(A45,BBDD!$1:$1048653,11,0) -> Indefinido | G45: =VLOOKUP(A45,BBDD!$1:$1048653,13,0) -> Coronel Rol Flota | H45: =VLOOKUP(A45,BBDD!$1:$1048653,14,0) -> Gerencia Corp. Negocio Seafood | I45: =VLOOKUP(A45,BBDD!$1:$1048653,16,0) -> Rol General (Cargo permanente o proyección indefinido) | J45: =VLOOKUP(A45,BBDD!$1:$1048653,17,0) | K45: =VLOOKUP(A45,BBDD!$1:$1048653,12,0) -> 40513 | L45: =VLOOKUP(A45,BBDD!$1:$1048653,3,0) -> Orizon S.A | M45: =VLOOKUP(A45,BBDD!$1:$1048653,4,0) -> F1 | N45: =VLOOKUP(A45,BBDD!$1:$1048653,5,0) -> alex.carrillo@orizon.cl | O45: 45954 | P45: Oficina | Q45: Vestimenta y EPP | R45: Desbloquear reserva caducada | T45: Cerrado
A46: 15193397 | B46: =VLOOKUP(A46,BBDD!$1:$1048653,2,0) -> 15.193.397-1 | C46: =VLOOKUP(A46,BBDD!$1:$1048653,7,0) -> Vasquez Molina Jose Luis | D46: =VLOOKUP(A46,BBDD!$1:$1048653,8,0) -> Operario Apoyo Elaboracion | E46: =VLOOKUP(A46,BBDD!$1:$1048653,10,0) -> Gerencia Producción Pesca | F46: =VLOOKUP(A46,BBDD!$1:$1048653,11,0) -> Plazo fijo | G46: =VLOOKUP(A46,BBDD!$1:$1048653,13,0) -> Coronel Rol Eventual | H46: =VLOOKUP(A46,BBDD!$1:$1048653,14,0) -> Gerencia Corp. Negocio Seafood | I46: =VLOOKUP(A46,BBDD!$1:$1048653,16,0) -> Temporada (Con ocasión Temporada de Pesca) | J46: =VLOOKUP(A46,BBDD!$1:$1048653,17,0) | K46: =VLOOKUP(A46,BBDD!$1:$1048653,12,0) -> 45941 | L46: =VLOOKUP(A46,BBDD!$1:$1048653,3,0) -> Orizon S.A | M46: =VLOOKUP(A46,BBDD!$1:$1048653,4,0) -> F1 | N46: =VLOOKUP(A46,BBDD!$1:$1048653,5,0) -> vasquez.molina.joseluis10@gmail.com | O46: 45954 | P46: Oficina | Q46: Documentos | R46: Declaración de opción de exención de cotizar | T46: Cerrado
A47: 18815806 | B47: =VLOOKUP(A47,BBDD!$1:$1048653,2,0) -> 18.815.806-4 | C47: =VLOOKUP(A47,BBDD!$1:$1048653,7,0) -> Sanhueza Leal Angel Belen | D47: =VLOOKUP(A47,BBDD!$1:$1048653,8,0) -> Operario Apoyo Elaboracion | E47: =VLOOKUP(A47,BBDD!$1:$1048653,10,0) -> Gerencia Producción Pesca | F47: =VLOOKUP(A47,BBDD!$1:$1048653,11,0) -> Plazo fijo | G47: =VLOOKUP(A47,BBDD!$1:$1048653,13,0) -> Coronel Rol Eventual | H47: =VLOOKUP(A47,BBDD!$1:$1048653,14,0) -> Gerencia Corp. Negocio Seafood | I47: =VLOOKUP(A47,BBDD!$1:$1048653,16,0) -> Temporada (Con ocasión Temporada de Pesca) | J47: =VLOOKUP(A47,BBDD!$1:$1048653,17,0) | K47: =VLOOKUP(A47,BBDD!$1:$1048653,12,0) -> 45931 | L47: =VLOOKUP(A47,BBDD!$1:$1048653,3,0) -> Orizon S.A | M47: =VLOOKUP(A47,BBDD!$1:$1048653,4,0) -> F3 | N47: =VLOOKUP(A47,BBDD!$1:$1048653,5,0) -> belensanhueza145@hotmail.com | O47: 45954 | P47: Oficina | Q47: Asistencia | R47: Entrega de documento medico por falta de día 23 de octubre | T47: Cerrado
A48: 17789509 | B48: =VLOOKUP(A48,BBDD!$1:$1048653,2,0) -> 17.789.509-1 | C48: =VLOOKUP(A48,BBDD!$1:$1048653,7,0) -> Ferreira Arratia Valeria Andrea | D48: =VLOOKUP(A48,BBDD!$1:$1048653,8,0) -> Operario Apoyo Elaboracion | E48: =VLOOKUP(A48,BBDD!$1:$1048653,10,0) -> Gerencia Producción Pesca | F48: =VLOOKUP(A48,BBDD!$1:$1048653,11,0) -> Plazo fijo | G48: =VLOOKUP(A48,BBDD!$1:$1048653,13,0) -> Coronel Rol Eventual | H48: =VLOOKUP(A48,BBDD!$1:$1048653,14,0) -> Gerencia Corp. Negocio Seafood | I48: =VLOOKUP(A48,BBDD!$1:$1048653,16,0) -> Temporada (Con ocasión Temporada de Pesca) | J48: =VLOOKUP(A48,BBDD!$1:$1048653,17,0) | K48: =VLOOKUP(A48,BBDD!$1:$1048653,12,0) -> 45931 | L48: =VLOOKUP(A48,BBDD!$1:$1048653,3,0) -> Orizon S.A | M48: =VLOOKUP(A48,BBDD!$1:$1048653,4,0) -> F4 | N48: =VLOOKUP(A48,BBDD!$1:$1048653,5,0) -> ferreiravaleria550@gmail.com | O48: 45957 | P48: Oficina | Q48: Asistencia | R48: Consulta por descanso cuando trabaja el domingo | S48: Se le indica que como no debe hacer 7 dias seguidos trabajando debe descansar antes. | T48: Cerrado
A49: 14390883 | B49: =VLOOKUP(A49,BBDD!$1:$1048653,2,0) -> 14.390.883-6 | C49: =VLOOKUP(A49,BBDD!$1:$1048653,7,0) -> Medina Escobar Osvaldo Jose | D49: =VLOOKUP(A49,BBDD!$1:$1048653,8,0) -> Tripulante | E49: =VLOOKUP(A49,BBDD!$1:$1048653,10,0) -> Gerencia de Flota y Abastecimiento de Materias Primas | F49: =VLOOKUP(A49,BBDD!$1:$1048653,11,0) -> Indefinido | G49: =VLOOKUP(A49,BBDD!$1:$1048653,13,0) -> Coronel Rol Flota | H49: =VLOOKUP(A49,BBDD!$1:$1048653,14,0) -> Gerencia Corp. Negocio Seafood | I49: =VLOOKUP(A49,BBDD!$1:$1048653,16,0) -> Rol General (Cargo permanente o proyección indefinido) | J49: =VLOOKUP(A49,BBDD!$1:$1048653,17,0) | K49: =VLOOKUP(A49,BBDD!$1:$1048653,12,0) -> 45729 | L49: =VLOOKUP(A49,BBDD!$1:$1048653,3,0) -> Orizon S.A | M49: =VLOOKUP(A49,BBDD!$1:$1048653,4,0) -> F2 | N49: =VLOOKUP(A49,BBDD!$1:$1048653,5,0) -> osvaldojose123@gmail.com | O49: 45957 | P49: Oficina | Q49: Vestimenta y EPP | R49: Consulta por numero de reserva | S49: Derivado a Rachel | T49: Cerrado
A50: 9312597 | B50: =VLOOKUP(A50,BBDD!$1:$1048653,2,0) -> 9.312.597-5 | C50: =VLOOKUP(A50,BBDD!$1:$1048653,7,0) -> Andreu Riveros Julio Cesar | D50: =VLOOKUP(A50,BBDD!$1:$1048653,8,0) -> Tripulante | E50: =VLOOKUP(A50,BBDD!$1:$1048653,10,0) -> Gerencia de Flota y Abastecimiento de Materias Primas | F50: =VLOOKUP(A50,BBDD!$1:$1048653,11,0) -> Indefinido | G50: =VLOOKUP(A50,BBDD!$1:$1048653,13,0) -> Coronel Rol Flota | H50: =VLOOKUP(A50,BBDD!$1:$1048653,14,0) -> Gerencia Corp. Negocio Seafood | I50: =VLOOKUP(A50,BBDD!$1:$1048653,16,0) -> Rol General (Cargo permanente o proyección indefinido) | J50: =VLOOKUP(A50,BBDD!$1:$1048653,17,0) | K50: =VLOOKUP(A50,BBDD!$1:$1048653,12,0) -> 40513 | L50: =VLOOKUP(A50,BBDD!$1:$1048653,3,0) -> Orizon S.A | M50: =VLOOKUP(A50,BBDD!$1:$1048653,4,0) -> F1 | N50: =VLOOKUP(A50,BBDD!$1:$1048653,5,0) -> julioandreu57@gmail.com | O50: 45957 | P50: Oficina | Q50: Beneficios | R50: Consulta como ver regalos de navidad | S50: Se entrega información y se guia para acceder a pagina | T50: Cerrado
A51: 11498484 | B51: =VLOOKUP(A51,BBDD!$1:$1048653,2,0) -> 11.498.484-1 | C51: =VLOOKUP(A51,BBDD!$1:$1048653,7,0) -> Sanhueza Fernandez Victor Manuel | D51: =VLOOKUP(A51,BBDD!$1:$1048653,8,0) -> Operador Grua Horquilla | E51: =VLOOKUP(A51,BBDD!$1:$1048653,10,0) -> Gerencia Producción Pesca | F51: =VLOOKUP(A51,BBDD!$1:$1048653,11,0) -> Indefinido | G51: =VLOOKUP(A51,BBDD!$1:$1048653,13,0) -> Coronel Rol Tierra | H51: =VLOOKUP(A51,BBDD!$1:$1048653,14,0) -> Gerencia Corp. Negocio Seafood | I51: =VLOOKUP(A51,BBDD!$1:$1048653,16,0) -> Rol General (Cargo permanente o proyección indefinido) | J51: =VLOOKUP(A51,BBDD!$1:$1048653,17,0) | K51: =VLOOKUP(A51,BBDD!$1:$1048653,12,0) -> 44805 | L51: =VLOOKUP(A51,BBDD!$1:$1048653,3,0) -> Orizon S.A | M51: =VLOOKUP(A51,BBDD!$1:$1048653,4,0) -> F1 | N51: =VLOOKUP(A51,BBDD!$1:$1048653,5,0) -> victormanuelsanhueza69@gmail.com | O51: 45957 | P51: Oficina | Q51: Asignación Familiar | R51: Consulta horario de ejecutiva euroamerica | T51: Cerrado
A52: 9391260 | B52: =VLOOKUP(A52,BBDD!$1:$1048653,2,0) -> 9.391.260-8 | C52: =VLOOKUP(A52,BBDD!$1:$1048653,7,0) -> Puentes Burgos Oscar Manuel | D52: =VLOOKUP(A52,BBDD!$1:$1048653,8,0) -> Tripulante | E52: =VLOOKUP(A52,BBDD!$1:$1048653,10,0) -> Gerencia de Flota y Abastecimiento de Materias Primas | F52: =VLOOKUP(A52,BBDD!$1:$1048653,11,0) -> Indefinido | G52: =VLOOKUP(A52,BBDD!$1:$1048653,13,0) -> Coronel Rol Flota | H52: =VLOOKUP(A52,BBDD!$1:$1048653,14,0) -> Gerencia Corp. Negocio Seafood | I52: =VLOOKUP(A52,BBDD!$1:$1048653,16,0) -> Rol General (Cargo permanente o proyección indefinido) | J52: =VLOOKUP(A52,BBDD!$1:$1048653,17,0) | K52: =VLOOKUP(A52,BBDD!$1:$1048653,12,0) -> 40513 | L52: =VLOOKUP(A52,BBDD!$1:$1048653,3,0) -> Orizon S.A | M52: =VLOOKUP(A52,BBDD!$1:$1048653,4,0) -> F1 | N52: =VLOOKUP(A52,BBDD!$1:$1048653,5,0) -> oscar24puentes@gmail.com | O52: 45957 | P52: Oficina | Q52: Documentos | R52: Vacaciones | T52: Cerrado
A53: 13899807 | B53: =VLOOKUP(A53,BBDD!$1:$1048653,2,0) -> 13.899.807-k | C53: =VLOOKUP(A53,BBDD!$1:$1048653,7,0) -> Godoy Bononato Cesar Mauricio | D53: =VLOOKUP(A53,BBDD!$1:$1048653,8,0) -> Supervisor(A) Mantencion Flota | E53: =VLOOKUP(A53,BBDD!$1:$1048653,10,0) -> Gerencia de Flota y Abastecimiento de Materias Primas | F53: =VLOOKUP(A53,BBDD!$1:$1048653,11,0) -> Indefinido | G53: =VLOOKUP(A53,BBDD!$1:$1048653,13,0) -> Coronel Rol Tierra | H53: =VLOOKUP(A53,BBDD!$1:$1048653,14,0) -> Gerencia Corp. Negocio Seafood | I53: =VLOOKUP(A53,BBDD!$1:$1048653,16,0) -> Rol General (Cargo permanente o proyección indefinido) | J53: =VLOOKUP(A53,BBDD!$1:$1048653,17,0) | K53: =VLOOKUP(A53,BBDD!$1:$1048653,12,0) -> 42723 | L53: =VLOOKUP(A53,BBDD!$1:$1048653,3,0) -> Orizon S.A | M53: =VLOOKUP(A53,BBDD!$1:$1048653,4,0) -> F1 | N53: =VLOOKUP(A53,BBDD!$1:$1048653,5,0) -> cesar.godoy@orizon.cl | O53: 45957 | P53: Teléfono | Q53: Beneficios | R53: Consulta cobertura FALP | S53: Se deriva a ejecutiva FALP | T53: Cerrado
A54: 20116576 | B54: =VLOOKUP(A54,BBDD!$1:$1048653,2,0) -> 20.116.576-8 | C54: =VLOOKUP(A54,BBDD!$1:$1048653,7,0) -> Ñanco Payllacan Victor Patricio | D54: =VLOOKUP(A54,BBDD!$1:$1048653,8,0) -> Operador Agua Mar | E54: =VLOOKUP(A54,BBDD!$1:$1048653,10,0) -> Departamento Ingeniería | F54: =VLOOKUP(A54,BBDD!$1:$1048653,11,0) -> Indefinido | G54: =VLOOKUP(A54,BBDD!$1:$1048653,13,0) -> Coronel Rol Tierra | H54: =VLOOKUP(A54,BBDD!$1:$1048653,14,0) -> Gerencia Corp. Negocio Seafood | I54: =VLOOKUP(A54,BBDD!$1:$1048653,16,0) -> Rol General (Cargo permanente o proyección indefinido) | J54: =VLOOKUP(A54,BBDD!$1:$1048653,17,0) | K54: =VLOOKUP(A54,BBDD!$1:$1048653,12,0) -> 44743 | L54: =VLOOKUP(A54,BBDD!$1:$1048653,3,0) -> Orizon S.A | M54: =VLOOKUP(A54,BBDD!$1:$1048653,4,0) -> F1 | N54: =VLOOKUP(A54,BBDD!$1:$1048653,5,0) -> victor12payllacan@gmail.com | O54: 45957 | P54: Oficina | Q54: Asignación Familiar | S54: Enviado | T54: Cerrado
A55: 9520956 | B55: =VLOOKUP(A55,BBDD!$1:$1048653,2,0) -> 9.520.956-4 | C55: =VLOOKUP(A55,BBDD!$1:$1048653,7,0) -> Villagra Umara Marco Antonio | D55: =VLOOKUP(A55,BBDD!$1:$1048653,8,0) -> Logistico Junior | E55: =VLOOKUP(A55,BBDD!$1:$1048653,10,0) -> Gerencia Abastecimiento | F55: =VLOOKUP(A55,BBDD!$1:$1048653,11,0) -> Plazo fijo | G55: =VLOOKUP(A55,BBDD!$1:$1048653,13,0) -> Coronel Rol Tierra | H55: =VLOOKUP(A55,BBDD!$1:$1048653,14,0) -> Gerencia Corp. Supply Chain | I55: =VLOOKUP(A55,BBDD!$1:$1048653,16,0) -> Temporada (Con ocasión Temporada de Pesca) | J55: =VLOOKUP(A55,BBDD!$1:$1048653,17,0) | K55: =VLOOKUP(A55,BBDD!$1:$1048653,12,0) -> 45922 | L55: =VLOOKUP(A55,BBDD!$1:$1048653,3,0) -> Orizon S.A | M55: =VLOOKUP(A55,BBDD!$1:$1048653,4,0) -> F2 | N55: =VLOOKUP(A55,BBDD!$1:$1048653,5,0) -> m.villagra64@gmail.com | O55: 45957 | P55: Oficina | Q55: Documentos | R55: Consulta por Buk y documentos pendientes | S55: Documentos firmados y activacion de Buk | T55: Cerrado
A56: 17444551 | B56: =VLOOKUP(A56,BBDD!$1:$1048653,2,0) -> 17.444.551-6 | C56: =VLOOKUP(A56,BBDD!$1:$1048653,7,0) -> Gonzalez Palma Cristian Giovanni | D56: =VLOOKUP(A56,BBDD!$1:$1048653,8,0) -> Operador Grupo Generadores | E56: =VLOOKUP(A56,BBDD!$1:$1048653,10,0) -> Departamento Ingeniería | F56: =VLOOKUP(A56,BBDD!$1:$1048653,11,0) -> Indefinido | G56: =VLOOKUP(A56,BBDD!$1:$1048653,13,0) -> Coronel Rol Tierra | H56: =VLOOKUP(A56,BBDD!$1:$1048653,14,0) -> Gerencia Corp. Negocio Seafood | I56: =VLOOKUP(A56,BBDD!$1:$1048653,16,0) -> Rol General (Cargo permanente o proyección indefinido) | J56: =VLOOKUP(A56,BBDD!$1:$1048653,17,0) | K56: =VLOOKUP(A56,BBDD!$1:$1048653,12,0) -> 45689 | L56: =VLOOKUP(A56,BBDD!$1:$1048653,3,0) -> Orizon S.A | M56: =VLOOKUP(A56,BBDD!$1:$1048653,4,0) -> F1 | N56: =VLOOKUP(A56,BBDD!$1:$1048653,5,0) -> cg.gonzalez8912@gmail.com | O56: 45957 | P56: Oficina | Q56: Asignación Familiar | S56: Enviando a CCAF | T56: Abierto
A57: 10186425 | B57: =VLOOKUP(A57,BBDD!$1:$1048653,2,0) -> 10.186.425-1 | C57: =VLOOKUP(A57,BBDD!$1:$1048653,7,0) -> Elmes Leal Oscar Alejandro | D57: =VLOOKUP(A57,BBDD!$1:$1048653,8,0) -> Motorista | E57: =VLOOKUP(A57,BBDD!$1:$1048653,10,0) -> Gerencia de Flota y Abastecimiento de Materias Primas | F57: =VLOOKUP(A57,BBDD!$1:$1048653,11,0) -> Indefinido | G57: =VLOOKUP(A57,BBDD!$1:$1048653,13,0) -> Coronel Rol Flota | H57: =VLOOKUP(A57,BBDD!$1:$1048653,14,0) -> Gerencia Corp. Negocio Seafood | I57: =VLOOKUP(A57,BBDD!$1:$1048653,16,0) -> Rol General (Cargo permanente o proyección indefinido) | J57: =VLOOKUP(A57,BBDD!$1:$1048653,17,0) | K57: =VLOOKUP(A57,BBDD!$1:$1048653,12,0) -> 40513 | L57: =VLOOKUP(A57,BBDD!$1:$1048653,3,0) -> Orizon S.A | M57: =VLOOKUP(A57,BBDD!$1:$1048653,4,0) -> F1 | N57: =VLOOKUP(A57,BBDD!$1:$1048653,5,0) -> oscar_elmes_leal@hotmail.com | O57: 45957 | P57: Oficina | Q57: Vestimenta y EPP | R57: Consulta por stock y fecha de entrega pendiente para motoristas | T57: Cerrado
A58: 15955471 | B58: Usuario Externo | C58: Usuario Externo | D58: Usuario Externo | E58: =VLOOKUP(A58,BBDD!$1:$1048653,10,0) -> #N/A | F58: =VLOOKUP(A58,BBDD!$1:$1048653,11,0) -> #N/A | G58: =VLOOKUP(A58,BBDD!$1:$1048653,13,0) -> #N/A | H58: =VLOOKUP(A58,BBDD!$1:$1048653,14,0) -> #N/A | I58: =VLOOKUP(A58,BBDD!$1:$1048653,16,0) -> #N/A | J58: =VLOOKUP(A58,BBDD!$1:$1048653,17,0) -> #N/A | K58: =VLOOKUP(A58,BBDD!$1:$1048653,12,0) -> #N/A | L58: =VLOOKUP(A58,BBDD!$1:$1048653,3,0) -> #N/A | M58: =VLOOKUP(A58,BBDD!$1:$1048653,4,0) -> #N/A | N58: Usuario Externo | O58: 45957 | P58: Oficina | Q58: Reclutamiento y Selección | R58: Solicita cambiar datos de contacto | S58: Deriado a Reclutamiento y selección | T58: Cerrado
A59: 15153174 | B59: =VLOOKUP(A59,BBDD!$1:$1048653,2,0) -> 15.153.174-1 | C59: =VLOOKUP(A59,BBDD!$1:$1048653,7,0) -> Duran Barria Cristian Ariel | D59: =VLOOKUP(A59,BBDD!$1:$1048653,8,0) -> Ito Mecanico Piping | E59: =VLOOKUP(A59,BBDD!$1:$1048653,10,0) -> Departamento Ingeniería | F59: =VLOOKUP(A59,BBDD!$1:$1048653,11,0) -> Obra | G59: =VLOOKUP(A59,BBDD!$1:$1048653,13,0) -> Coronel Rol Tierra | H59: =VLOOKUP(A59,BBDD!$1:$1048653,14,0) -> Gerencia Corp. Negocio Seafood | I59: =VLOOKUP(A59,BBDD!$1:$1048653,16,0) -> Eventual (Reemplazo LM - Proyecto - Faena 4E Conservas) | J59: =VLOOKUP(A59,BBDD!$1:$1048653,17,0) | K59: =VLOOKUP(A59,BBDD!$1:$1048653,12,0) -> 45870 | L59: =VLOOKUP(A59,BBDD!$1:$1048653,3,0) -> Orizon S.A | M59: =VLOOKUP(A59,BBDD!$1:$1048653,4,0) -> F1 | N59: =VLOOKUP(A59,BBDD!$1:$1048653,5,0) -> cristian.duran.barria@gmail.com | O59: 45957 | P59: Oficina | Q59: Asistencia | R59: Informa que durante los dias 22,23,24 de octubre no marco por que estaba trabajando en coquimbo | S59: Derivado a control tiempo | T59: Cerrado
A60: 17862768 | B60: =VLOOKUP(A60,BBDD!$1:$1048653,2,0) -> 17.862.768-6 | C60: =VLOOKUP(A60,BBDD!$1:$1048653,7,0) -> Ojeda Chávez Ingrid Leticia | D60: =VLOOKUP(A60,BBDD!$1:$1048653,8,0) -> Operario Apoyo Elaboracion | E60: =VLOOKUP(A60,BBDD!$1:$1048653,10,0) -> Gerencia Producción Pesca | F60: =VLOOKUP(A60,BBDD!$1:$1048653,11,0) -> Obra | G60: =VLOOKUP(A60,BBDD!$1:$1048653,13,0) -> Coronel Rol Eventual | H60: =VLOOKUP(A60,BBDD!$1:$1048653,14,0) -> Gerencia Corp. Negocio Seafood | I60: =VLOOKUP(A60,BBDD!$1:$1048653,16,0) -> Temporada (Con ocasión Temporada de Pesca) | J60: =VLOOKUP(A60,BBDD!$1:$1048653,17,0) | K60: =VLOOKUP(A60,BBDD!$1:$1048653,12,0) -> 45600 | L60: =VLOOKUP(A60,BBDD!$1:$1048653,3,0) -> Orizon S.A | M60: =VLOOKUP(A60,BBDD!$1:$1048653,4,0) -> F3 | N60: =VLOOKUP(A60,BBDD!$1:$1048653,5,0) -> INGRIDOJEDACH@LIVE.CL | O60: 45957 | P60: E-mail | Q60: Asignación Familiar | R60: Consulta si llego documento de caja 18 | S60: Confirma que ya esta ok | T60: Cerrado
A61: 11153045 | B61: =VLOOKUP(A61,BBDD!$1:$1048653,2,0) -> 11.153.045-9 | C61: =VLOOKUP(A61,BBDD!$1:$1048653,7,0) -> Espina Rios Aida Aureliana | D61: =VLOOKUP(A61,BBDD!$1:$1048653,8,0) -> Operador Elaboracion | E61: =VLOOKUP(A61,BBDD!$1:$1048653,10,0) -> Gerencia Producción Pesca | F61: =VLOOKUP(A61,BBDD!$1:$1048653,11,0) -> Indefinido | G61: =VLOOKUP(A61,BBDD!$1:$1048653,13,0) -> Coronel Rol Tierra | H61: =VLOOKUP(A61,BBDD!$1:$1048653,14,0) -> Gerencia Corp. Negocio Seafood | I61: =VLOOKUP(A61,BBDD!$1:$1048653,16,0) -> Rol General (Cargo permanente o proyección indefinido) | J61: =VLOOKUP(A61,BBDD!$1:$1048653,17,0) | K61: =VLOOKUP(A61,BBDD!$1:$1048653,12,0) -> 42676 | L61: =VLOOKUP(A61,BBDD!$1:$1048653,3,0) -> Orizon S.A | M61: =VLOOKUP(A61,BBDD!$1:$1048653,4,0) -> F1 | N61: =VLOOKUP(A61,BBDD!$1:$1048653,5,0) -> espinariosaida@gmail.com | O61: 45957 | P61: Oficina | Q61: Asistencia | R61: Documento permiso | T61: Cerrado
A62: 18626410 | B62: =VLOOKUP(A62,BBDD!$1:$1048653,2,0) -> 18.626.410-k | C62: =VLOOKUP(A62,BBDD!$1:$1048653,7,0) -> Albornoz Sepulveda Elizabeth Andrea | D62: =VLOOKUP(A62,BBDD!$1:$1048653,8,0) -> Operario Apoyo Elaboracion | E62: =VLOOKUP(A62,BBDD!$1:$1048653,10,0) -> Gerencia Producción Pesca | F62: =VLOOKUP(A62,BBDD!$1:$1048653,11,0) -> Obra | G62: =VLOOKUP(A62,BBDD!$1:$1048653,13,0) -> Coronel Rol Eventual | H62: =VLOOKUP(A62,BBDD!$1:$1048653,14,0) -> Gerencia Corp. Negocio Seafood | I62: =VLOOKUP(A62,BBDD!$1:$1048653,16,0) -> Temporada (Con ocasión Temporada de Pesca) | J62: =VLOOKUP(A62,BBDD!$1:$1048653,17,0) | K62: =VLOOKUP(A62,BBDD!$1:$1048653,12,0) -> 45621 | L62: =VLOOKUP(A62,BBDD!$1:$1048653,3,0) -> Orizon S.A | M62: =VLOOKUP(A62,BBDD!$1:$1048653,4,0) -> F3 | N62: =VLOOKUP(A62,BBDD!$1:$1048653,5,0) -> ALBORNOZELIZABETH24@GMAIL.COM | O62: 45957 | P62: Otro | Q62: Asistencia | R62: Informa que no pdo presentarse a trabajar el dia sábado | T62: Cerrado
A63: 1 | B63: =VLOOKUP(A63,BBDD!$1:$1048653,2,0) -> Usuario Externo | C63: =VLOOKUP(A63,BBDD!$1:$1048653,7,0) -> Usuario Externo | D63: =VLOOKUP(A63,BBDD!$1:$1048653,8,0) -> Usuario Externo | E63: =VLOOKUP(A63,BBDD!$1:$1048653,10,0) -> Usuario Externo | F63: =VLOOKUP(A63,BBDD!$1:$1048653,11,0) -> Usuario Externo | G63: =VLOOKUP(A63,BBDD!$1:$1048653,13,0) -> Usuario Externo | H63: =VLOOKUP(A63,BBDD!$1:$1048653,14,0) -> Usuario Externo | I63: =VLOOKUP(A63,BBDD!$1:$1048653,16,0) -> Usuario Externo | J63: =VLOOKUP(A63,BBDD!$1:$1048653,17,0) | K63: =VLOOKUP(A63,BBDD!$1:$1048653,12,0) -> Usuario Externo | L63: =VLOOKUP(A63,BBDD!$1:$1048653,3,0) -> Usuario Externo | M63: =VLOOKUP(A63,BBDD!$1:$1048653,4,0) -> Usuario Externo | N63: =VLOOKUP(A63,BBDD!$1:$1048653,5,0) -> Usuario Externo | O63: 45957 | P63: Teléfono | Q63: Reclutamiento y Selección | R63: Se deriva a reclutamiento@nutrisco.com | T63: Cerrado
A64: 1 | B64: =VLOOKUP(A64,BBDD!$1:$1048653,2,0) -> Usuario Externo | C64: =VLOOKUP(A64,BBDD!$1:$1048653,7,0) -> Usuario Externo | D64: =VLOOKUP(A64,BBDD!$1:$1048653,8,0) -> Usuario Externo | E64: =VLOOKUP(A64,BBDD!$1:$1048653,10,0) -> Usuario Externo | F64: =VLOOKUP(A64,BBDD!$1:$1048653,11,0) -> Usuario Externo | G64: =VLOOKUP(A64,BBDD!$1:$1048653,13,0) -> Usuario Externo | H64: =VLOOKUP(A64,BBDD!$1:$1048653,14,0) -> Usuario Externo | I64: =VLOOKUP(A64,BBDD!$1:$1048653,16,0) -> Usuario Externo | J64: =VLOOKUP(A64,BBDD!$1:$1048653,17,0) | K64: =VLOOKUP(A64,BBDD!$1:$1048653,12,0) -> Usuario Externo | L64: =VLOOKUP(A64,BBDD!$1:$1048653,3,0) -> Usuario Externo | M64: =VLOOKUP(A64,BBDD!$1:$1048653,4,0) -> Usuario Externo | N64: =VLOOKUP(A64,BBDD!$1:$1048653,5,0) -> Usuario Externo | O64: 45957 | P64: Oficina | Q64: Reclutamiento y Selección | R64: Se deriva al area de reclutamiento | T64: Cerrado
A65: 1 | B65: =VLOOKUP(A65,BBDD!$1:$1048653,2,0) -> Usuario Externo | C65: =VLOOKUP(A65,BBDD!$1:$1048653,7,0) -> Usuario Externo | D65: =VLOOKUP(A65,BBDD!$1:$1048653,8,0) -> Usuario Externo | E65: =VLOOKUP(A65,BBDD!$1:$1048653,10,0) -> Usuario Externo | F65: =VLOOKUP(A65,BBDD!$1:$1048653,11,0) -> Usuario Externo | G65: =VLOOKUP(A65,BBDD!$1:$1048653,13,0) -> Usuario Externo | H65: =VLOOKUP(A65,BBDD!$1:$1048653,14,0) -> Usuario Externo | I65: =VLOOKUP(A65,BBDD!$1:$1048653,16,0) -> Usuario Externo | J65: =VLOOKUP(A65,BBDD!$1:$1048653,17,0) | K65: =VLOOKUP(A65,BBDD!$1:$1048653,12,0) -> Usuario Externo | L65: =VLOOKUP(A65,BBDD!$1:$1048653,3,0) -> Usuario Externo | M65: =VLOOKUP(A65,BBDD!$1:$1048653,4,0) -> Usuario Externo | N65: =VLOOKUP(A65,BBDD!$1:$1048653,5,0) -> Usuario Externo | O65: 45957 | P65: Oficina | Q65: Reclutamiento y Selección | R65: Se deriva a reclutamiento@nutrisco.com | T65: Cerrado
A66: 1 | B66: =VLOOKUP(A66,BBDD!$1:$1048653,2,0) -> Usuario Externo | C66: =VLOOKUP(A66,BBDD!$1:$1048653,7,0) -> Usuario Externo | D66: =VLOOKUP(A66,BBDD!$1:$1048653,8,0) -> Usuario Externo | E66: =VLOOKUP(A66,BBDD!$1:$1048653,10,0) -> Usuario Externo | F66: =VLOOKUP(A66,BBDD!$1:$1048653,11,0) -> Usuario Externo | G66: =VLOOKUP(A66,BBDD!$1:$1048653,13,0) -> Usuario Externo | H66: =VLOOKUP(A66,BBDD!$1:$1048653,14,0) -> Usuario Externo | I66: =VLOOKUP(A66,BBDD!$1:$1048653,16,0) -> Usuario Externo | J66: =VLOOKUP(A66,BBDD!$1:$1048653,17,0) | K66: =VLOOKUP(A66,BBDD!$1:$1048653,12,0) -> Usuario Externo | L66: =VLOOKUP(A66,BBDD!$1:$1048653,3,0) -> Usuario Externo | M66: =VLOOKUP(A66,BBDD!$1:$1048653,4,0) -> Usuario Externo | N66: =VLOOKUP(A66,BBDD!$1:$1048653,5,0) -> Usuario Externo | O66: 45957 | P66: Oficina | Q66: Reclutamiento y Selección | R66: Se deriva a reclutamiento@nutrisco.com | T66: Cerrado
A67: 10957792 | B67: =VLOOKUP(A67,BBDD!$1:$1048653,2,0) -> 10.957.792-8 | C67: =VLOOKUP(A67,BBDD!$1:$1048653,7,0) -> Hidalgo Saez Jose Luis | D67: =VLOOKUP(A67,BBDD!$1:$1048653,8,0) -> Tripulante | E67: =VLOOKUP(A67,BBDD!$1:$1048653,10,0) -> Gerencia de Flota y Abastecimiento de Materias Primas | F67: =VLOOKUP(A67,BBDD!$1:$1048653,11,0) -> Indefinido | G67: =VLOOKUP(A67,BBDD!$1:$1048653,13,0) -> Coronel Rol Flota | H67: =VLOOKUP(A67,BBDD!$1:$1048653,14,0) -> Gerencia Corp. Negocio Seafood | I67: =VLOOKUP(A67,BBDD!$1:$1048653,16,0) -> Rol General (Cargo permanente o proyección indefinido) | J67: =VLOOKUP(A67,BBDD!$1:$1048653,17,0) | K67: =VLOOKUP(A67,BBDD!$1:$1048653,12,0) -> 45612 | L67: =VLOOKUP(A67,BBDD!$1:$1048653,3,0) -> Orizon S.A | M67: =VLOOKUP(A67,BBDD!$1:$1048653,4,0) -> F2 | N67: =VLOOKUP(A67,BBDD!$1:$1048653,5,0) -> cvillarroelamelia@gmail.com | O67: 45957 | P67: Oficina | Q67: Vestimenta y EPP | R67: Solicita cambio de talla | T67: Cerrado
A68: 10957792 | B68: =VLOOKUP(A68,BBDD!$1:$1048653,2,0) -> 10.957.792-8 | C68: =VLOOKUP(A68,BBDD!$1:$1048653,7,0) -> Hidalgo Saez Jose Luis | D68: =VLOOKUP(A68,BBDD!$1:$1048653,8,0) -> Tripulante | E68: =VLOOKUP(A68,BBDD!$1:$1048653,10,0) -> Gerencia de Flota y Abastecimiento de Materias Primas | F68: =VLOOKUP(A68,BBDD!$1:$1048653,11,0) -> Indefinido | G68: =VLOOKUP(A68,BBDD!$1:$1048653,13,0) -> Coronel Rol Flota | H68: =VLOOKUP(A68,BBDD!$1:$1048653,14,0) -> Gerencia Corp. Negocio Seafood | I68: =VLOOKUP(A68,BBDD!$1:$1048653,16,0) -> Rol General (Cargo permanente o proyección indefinido) | J68: =VLOOKUP(A68,BBDD!$1:$1048653,17,0) | K68: =VLOOKUP(A68,BBDD!$1:$1048653,12,0) -> 45612 | L68: =VLOOKUP(A68,BBDD!$1:$1048653,3,0) -> Orizon S.A | M68: =VLOOKUP(A68,BBDD!$1:$1048653,4,0) -> F2 | N68: =VLOOKUP(A68,BBDD!$1:$1048653,5,0) -> cvillarroelamelia@gmail.com | O68: 45957 | P68: Oficina | Q68: Vestimenta y EPP | R68: Solicita cambio de talla | T68: Cerrado
A69: 18413121 | B69: =VLOOKUP(A69,BBDD!$1:$1048653,2,0) -> 18.413.121-8 | C69: =VLOOKUP(A69,BBDD!$1:$1048653,7,0) -> Letelier Letelier Teresa Andrea | D69: =VLOOKUP(A69,BBDD!$1:$1048653,8,0) -> Comprador(A) Servicios | E69: =VLOOKUP(A69,BBDD!$1:$1048653,10,0) -> Gerencia Abastecimiento | F69: =VLOOKUP(A69,BBDD!$1:$1048653,11,0) -> Indefinido | G69: =VLOOKUP(A69,BBDD!$1:$1048653,13,0) -> Nutrisco SA | H69: =VLOOKUP(A69,BBDD!$1:$1048653,14,0) -> Gerencia Corp. Supply Chain | I69: =VLOOKUP(A69,BBDD!$1:$1048653,16,0) -> Rol General (Cargo permanente o proyección indefinido) | J69: =VLOOKUP(A69,BBDD!$1:$1048653,17,0) | K69: =VLOOKUP(A69,BBDD!$1:$1048653,12,0) -> 45726 | L69: =VLOOKUP(A69,BBDD!$1:$1048653,3,0) -> Nutrisco S.A. | M69: =VLOOKUP(A69,BBDD!$1:$1048653,4,0) -> F1 | N69: =VLOOKUP(A69,BBDD!$1:$1048653,5,0) -> teresa.letelier@nutrisco.com | O69: 45957 | P69: Oficina | Q69: Credencial | R69: Se entrega Lanyard | T69: Cerrado
A70: 13957760 | B70: =VLOOKUP(A70,BBDD!$1:$1048653,2,0) -> 13.957.760-4 | C70: =VLOOKUP(A70,BBDD!$1:$1048653,7,0) -> Araneda Espinoza Robert Javier | D70: =VLOOKUP(A70,BBDD!$1:$1048653,8,0) -> Tripulante | E70: =VLOOKUP(A70,BBDD!$1:$1048653,10,0) -> Gerencia de Flota y Abastecimiento de Materias Primas | F70: =VLOOKUP(A70,BBDD!$1:$1048653,11,0) -> Indefinido | G70: =VLOOKUP(A70,BBDD!$1:$1048653,13,0) -> Coronel Rol Flota | H70: =VLOOKUP(A70,BBDD!$1:$1048653,14,0) -> Gerencia Corp. Negocio Seafood | I70: =VLOOKUP(A70,BBDD!$1:$1048653,16,0) -> Rol General (Cargo permanente o proyección indefinido) | J70: =VLOOKUP(A70,BBDD!$1:$1048653,17,0) | K70: =VLOOKUP(A70,BBDD!$1:$1048653,12,0) -> 43812 | L70: =VLOOKUP(A70,BBDD!$1:$1048653,3,0) -> Orizon S.A | M70: =VLOOKUP(A70,BBDD!$1:$1048653,4,0) -> F1 | N70: =VLOOKUP(A70,BBDD!$1:$1048653,5,0) -> raraneda69@gmail.com | O70: 45957 | P70: Oficina | Q70: Documentos | R70: solicitud de firma PAD fonasa | T70: Cerrado
A71: 27046927 | B71: =VLOOKUP(A71,BBDD!$1:$1048653,2,0) -> 27.046.927-2 | C71: =VLOOKUP(A71,BBDD!$1:$1048653,7,0) -> Colina Atacho Henyerber Jose | D71: =VLOOKUP(A71,BBDD!$1:$1048653,8,0) -> Operario Apoyo Elaboracion | E71: =VLOOKUP(A71,BBDD!$1:$1048653,10,0) -> Gerencia Producción Pesca | F71: =VLOOKUP(A71,BBDD!$1:$1048653,11,0) -> Plazo fijo | G71: =VLOOKUP(A71,BBDD!$1:$1048653,13,0) -> Coronel Rol Eventual | H71: =VLOOKUP(A71,BBDD!$1:$1048653,14,0) -> Gerencia Corp. Negocio Seafood | I71: =VLOOKUP(A71,BBDD!$1:$1048653,16,0) -> Temporada (Con ocasión Temporada de Pesca) | J71: =VLOOKUP(A71,BBDD!$1:$1048653,17,0) | K71: =VLOOKUP(A71,BBDD!$1:$1048653,12,0) -> 45931 | L71: =VLOOKUP(A71,BBDD!$1:$1048653,3,0) -> Orizon S.A | M71: =VLOOKUP(A71,BBDD!$1:$1048653,4,0) -> F2 | N71: =VLOOKUP(A71,BBDD!$1:$1048653,5,0) -> chuchocolina@gmail.com | O71: 45958 | P71: Oficina | Q71: Asistencia | R71: Consulta por desgloce de permisos en buk | T71: Cerrado
A72: 1 | B72: =VLOOKUP(A72,BBDD!$1:$1048653,2,0) -> Usuario Externo | C72: =VLOOKUP(A72,BBDD!$1:$1048653,7,0) -> Usuario Externo | D72: =VLOOKUP(A72,BBDD!$1:$1048653,8,0) -> Usuario Externo | E72: =VLOOKUP(A72,BBDD!$1:$1048653,10,0) -> Usuario Externo | F72: =VLOOKUP(A72,BBDD!$1:$1048653,11,0) -> Usuario Externo | G72: =VLOOKUP(A72,BBDD!$1:$1048653,13,0) -> Usuario Externo | H72: =VLOOKUP(A72,BBDD!$1:$1048653,14,0) -> Usuario Externo | I72: =VLOOKUP(A72,BBDD!$1:$1048653,16,0) -> Usuario Externo | J72: =VLOOKUP(A72,BBDD!$1:$1048653,17,0) | K72: =VLOOKUP(A72,BBDD!$1:$1048653,12,0) -> Usuario Externo | L72: =VLOOKUP(A72,BBDD!$1:$1048653,3,0) -> Usuario Externo | M72: =VLOOKUP(A72,BBDD!$1:$1048653,4,0) -> Usuario Externo | N72: =VLOOKUP(A72,BBDD!$1:$1048653,5,0) -> Usuario Externo | O72: 45958 | P72: Oficina | Q72: Reclutamiento y Selección | R72: Derivada Reclutamiento | T72: Cerrado
A73: 1 | B73: =VLOOKUP(A73,BBDD!$1:$1048653,2,0) -> Usuario Externo | C73: =VLOOKUP(A73,BBDD!$1:$1048653,7,0) -> Usuario Externo | D73: =VLOOKUP(A73,BBDD!$1:$1048653,8,0) -> Usuario Externo | E73: =VLOOKUP(A73,BBDD!$1:$1048653,10,0) -> Usuario Externo | F73: =VLOOKUP(A73,BBDD!$1:$1048653,11,0) -> Usuario Externo | G73: =VLOOKUP(A73,BBDD!$1:$1048653,13,0) -> Usuario Externo | H73: =VLOOKUP(A73,BBDD!$1:$1048653,14,0) -> Usuario Externo | I73: =VLOOKUP(A73,BBDD!$1:$1048653,16,0) -> Usuario Externo | J73: =VLOOKUP(A73,BBDD!$1:$1048653,17,0) | K73: =VLOOKUP(A73,BBDD!$1:$1048653,12,0) -> Usuario Externo | L73: =VLOOKUP(A73,BBDD!$1:$1048653,3,0) -> Usuario Externo | M73: =VLOOKUP(A73,BBDD!$1:$1048653,4,0) -> Usuario Externo | N73: =VLOOKUP(A73,BBDD!$1:$1048653,5,0) -> Usuario Externo | O73: 45958 | P73: Oficina | Q73: Asistencia | R73: Trabajador indica que no tiene marcas de ingreso y salida dia 2 de octubre, pero si asistio a trabajar | S73: Derivado a encargado empresa transitoria | T73: Cerrado
A74: 10803779 | B74: =VLOOKUP(A74,BBDD!$1:$1048653,2,0) -> 10.803.779-2 | C74: =VLOOKUP(A74,BBDD!$1:$1048653,7,0) -> Acosta Soto Claudio Javier | D74: =VLOOKUP(A74,BBDD!$1:$1048653,8,0) -> Electrico De Turno | E74: =VLOOKUP(A74,BBDD!$1:$1048653,10,0) -> Departamento Ingeniería | F74: =VLOOKUP(A74,BBDD!$1:$1048653,11,0) -> Indefinido | G74: =VLOOKUP(A74,BBDD!$1:$1048653,13,0) -> Coronel Rol Tierra | H74: =VLOOKUP(A74,BBDD!$1:$1048653,14,0) -> Gerencia Corp. Negocio Seafood | I74: =VLOOKUP(A74,BBDD!$1:$1048653,16,0) -> Rol General (Cargo permanente o proyección indefinido) | J74: =VLOOKUP(A74,BBDD!$1:$1048653,17,0) | K74: =VLOOKUP(A74,BBDD!$1:$1048653,12,0) -> 44204 | L74: =VLOOKUP(A74,BBDD!$1:$1048653,3,0) -> Orizon S.A | M74: =VLOOKUP(A74,BBDD!$1:$1048653,4,0) -> F1 | N74: =VLOOKUP(A74,BBDD!$1:$1048653,5,0) -> claudio.acosta@orizon.cl | O74: 45958 | P74: Oficina | Q74: Buk | R74: Trabajador no puede ingresar aplicación | S74: Se le guia para cambiar contraseña | T74: Cerrado
A75: 13957760 | B75: =VLOOKUP(A75,BBDD!$1:$1048653,2,0) -> 13.957.760-4 | C75: =VLOOKUP(A75,BBDD!$1:$1048653,7,0) -> Araneda Espinoza Robert Javier | D75: =VLOOKUP(A75,BBDD!$1:$1048653,8,0) -> Tripulante | E75: =VLOOKUP(A75,BBDD!$1:$1048653,10,0) -> Gerencia de Flota y Abastecimiento de Materias Primas | F75: =VLOOKUP(A75,BBDD!$1:$1048653,11,0) -> Indefinido | G75: =VLOOKUP(A75,BBDD!$1:$1048653,13,0) -> Coronel Rol Flota | H75: =VLOOKUP(A75,BBDD!$1:$1048653,14,0) -> Gerencia Corp. Negocio Seafood | I75: =VLOOKUP(A75,BBDD!$1:$1048653,16,0) -> Rol General (Cargo permanente o proyección indefinido) | J75: =VLOOKUP(A75,BBDD!$1:$1048653,17,0) | K75: =VLOOKUP(A75,BBDD!$1:$1048653,12,0) -> 43812 | L75: =VLOOKUP(A75,BBDD!$1:$1048653,3,0) -> Orizon S.A | M75: =VLOOKUP(A75,BBDD!$1:$1048653,4,0) -> F1 | N75: =VLOOKUP(A75,BBDD!$1:$1048653,5,0) -> raraneda69@gmail.com | O75: 45958 | P75: Oficina | Q75: Documentos | R75: Se firma documentos PAD Fonasa Linda | T75: Cerrado
A76: 13899807 | B76: =VLOOKUP(A76,BBDD!$1:$1048653,2,0) -> 13.899.807-k | C76: =VLOOKUP(A76,BBDD!$1:$1048653,7,0) -> Godoy Bononato Cesar Mauricio | D76: =VLOOKUP(A76,BBDD!$1:$1048653,8,0) -> Supervisor(A) Mantencion Flota | E76: =VLOOKUP(A76,BBDD!$1:$1048653,10,0) -> Gerencia de Flota y Abastecimiento de Materias Primas | F76: =VLOOKUP(A76,BBDD!$1:$1048653,11,0) -> Indefinido | G76: =VLOOKUP(A76,BBDD!$1:$1048653,13,0) -> Coronel Rol Tierra | H76: =VLOOKUP(A76,BBDD!$1:$1048653,14,0) -> Gerencia Corp. Negocio Seafood | I76: =VLOOKUP(A76,BBDD!$1:$1048653,16,0) -> Rol General (Cargo permanente o proyección indefinido) | J76: =VLOOKUP(A76,BBDD!$1:$1048653,17,0) | K76: =VLOOKUP(A76,BBDD!$1:$1048653,12,0) -> 42723 | L76: =VLOOKUP(A76,BBDD!$1:$1048653,3,0) -> Orizon S.A | M76: =VLOOKUP(A76,BBDD!$1:$1048653,4,0) -> F1 | N76: =VLOOKUP(A76,BBDD!$1:$1048653,5,0) -> cesar.godoy@orizon.cl | O76: 45958 | P76: Oficina | Q76: Remuneraciones | R76: Vacaciones progresivas | S76: Enviado a remu | T76: Cerrado
A77: 20116576 | B77: =VLOOKUP(A77,BBDD!$1:$1048653,2,0) -> 20.116.576-8 | C77: =VLOOKUP(A77,BBDD!$1:$1048653,7,0) -> Ñanco Payllacan Victor Patricio | D77: =VLOOKUP(A77,BBDD!$1:$1048653,8,0) -> Operador Agua Mar | E77: =VLOOKUP(A77,BBDD!$1:$1048653,10,0) -> Departamento Ingeniería | F77: =VLOOKUP(A77,BBDD!$1:$1048653,11,0) -> Indefinido | G77: =VLOOKUP(A77,BBDD!$1:$1048653,13,0) -> Coronel Rol Tierra | H77: =VLOOKUP(A77,BBDD!$1:$1048653,14,0) -> Gerencia Corp. Negocio Seafood | I77: =VLOOKUP(A77,BBDD!$1:$1048653,16,0) -> Rol General (Cargo permanente o proyección indefinido) | J77: =VLOOKUP(A77,BBDD!$1:$1048653,17,0) | K77: =VLOOKUP(A77,BBDD!$1:$1048653,12,0) -> 44743 | L77: =VLOOKUP(A77,BBDD!$1:$1048653,3,0) -> Orizon S.A | M77: =VLOOKUP(A77,BBDD!$1:$1048653,4,0) -> F1 | N77: =VLOOKUP(A77,BBDD!$1:$1048653,5,0) -> victor12payllacan@gmail.com | O77: 45958 | P77: Oficina | Q77: Seguro de Salud | R77: Seguro de Salud, documento incorporación | S77: Se entrega documento | T77: Cerrado
A78: 1 | B78: =VLOOKUP(A78,BBDD!$1:$1048653,2,0) -> Usuario Externo | C78: =VLOOKUP(A78,BBDD!$1:$1048653,7,0) -> Usuario Externo | D78: =VLOOKUP(A78,BBDD!$1:$1048653,8,0) -> Usuario Externo | E78: =VLOOKUP(A78,BBDD!$1:$1048653,10,0) -> Usuario Externo | F78: =VLOOKUP(A78,BBDD!$1:$1048653,11,0) -> Usuario Externo | G78: =VLOOKUP(A78,BBDD!$1:$1048653,13,0) -> Usuario Externo | H78: =VLOOKUP(A78,BBDD!$1:$1048653,14,0) -> Usuario Externo | I78: =VLOOKUP(A78,BBDD!$1:$1048653,16,0) -> Usuario Externo | J78: =VLOOKUP(A78,BBDD!$1:$1048653,17,0) | K78: =VLOOKUP(A78,BBDD!$1:$1048653,12,0) -> Usuario Externo | L78: =VLOOKUP(A78,BBDD!$1:$1048653,3,0) -> Usuario Externo | M78: =VLOOKUP(A78,BBDD!$1:$1048653,4,0) -> Usuario Externo | N78: =VLOOKUP(A78,BBDD!$1:$1048653,5,0) -> Usuario Externo | O78: 45958 | P78: Oficina | Q78: Remuneraciones | R78: Consulta por finiquito de su padre que trabajo en el 2021(flota) Luis Peña (RUT: 6.908.624-1) | S78: Se le indica que se revisara la información y le informaremos pasos a seguir | T78: Abierto
A79: 11493997 | B79: =VLOOKUP(A79,BBDD!$1:$1048653,2,0) -> 11.493.997-8 | C79: =VLOOKUP(A79,BBDD!$1:$1048653,7,0) -> Toledo Cerda Felix Antonio | D79: =VLOOKUP(A79,BBDD!$1:$1048653,8,0) -> Tripulante | E79: =VLOOKUP(A79,BBDD!$1:$1048653,10,0) -> Gerencia de Flota y Abastecimiento de Materias Primas | F79: =VLOOKUP(A79,BBDD!$1:$1048653,11,0) -> Indefinido | G79: =VLOOKUP(A79,BBDD!$1:$1048653,13,0) -> Coronel Rol Flota | H79: =VLOOKUP(A79,BBDD!$1:$1048653,14,0) -> Gerencia Corp. Negocio Seafood | I79: =VLOOKUP(A79,BBDD!$1:$1048653,16,0) -> Rol General (Cargo permanente o proyección indefinido) | J79: =VLOOKUP(A79,BBDD!$1:$1048653,17,0) | K79: =VLOOKUP(A79,BBDD!$1:$1048653,12,0) -> 40513 | L79: =VLOOKUP(A79,BBDD!$1:$1048653,3,0) -> Orizon S.A | M79: =VLOOKUP(A79,BBDD!$1:$1048653,4,0) -> F1 | N79: =VLOOKUP(A79,BBDD!$1:$1048653,5,0) -> felixantoniotc25@gmail.com | O79: 45958 | P79: Oficina | Q79: Beneficios | R79: Firma Bono PAD | T79: Cerrado
A80: 18333448 | B80: =VLOOKUP(A80,BBDD!$1:$1048653,2,0) -> 18.333.448-4 | C80: =VLOOKUP(A80,BBDD!$1:$1048653,7,0) -> Leal Canteros Fabiola Andrea | D80: =VLOOKUP(A80,BBDD!$1:$1048653,8,0) -> Operario Apoyo Elaboracion | E80: =VLOOKUP(A80,BBDD!$1:$1048653,10,0) -> Gerencia Producción Pesca | F80: =VLOOKUP(A80,BBDD!$1:$1048653,11,0) -> Obra | G80: =VLOOKUP(A80,BBDD!$1:$1048653,13,0) -> Coronel Rol Eventual | H80: =VLOOKUP(A80,BBDD!$1:$1048653,14,0) -> Gerencia Corp. Negocio Seafood | I80: =VLOOKUP(A80,BBDD!$1:$1048653,16,0) -> Temporada (Con ocasión Temporada de Pesca) | J80: =VLOOKUP(A80,BBDD!$1:$1048653,17,0) | K80: =VLOOKUP(A80,BBDD!$1:$1048653,12,0) -> 45663 | L80: =VLOOKUP(A80,BBDD!$1:$1048653,3,0) -> Orizon S.A | M80: =VLOOKUP(A80,BBDD!$1:$1048653,4,0) -> F2 | N80: =VLOOKUP(A80,BBDD!$1:$1048653,5,0) -> FABIOLAANDREALEALCANTEROS@GMAIL.COM | O80: 45958 | P80: E-mail | Q80: Licencia Médica | R80: Consulta para acceder a Permiso Postnatal Parental Completo | S80: Se le indica como obtener documentación para que presente en la empresa | T80: Abierto
A81: 1 | B81: =VLOOKUP(A81,BBDD!$1:$1048653,2,0) -> Usuario Externo | C81: =VLOOKUP(A81,BBDD!$1:$1048653,7,0) -> Usuario Externo | D81: =VLOOKUP(A81,BBDD!$1:$1048653,8,0) -> Usuario Externo | E81: =VLOOKUP(A81,BBDD!$1:$1048653,10,0) -> Usuario Externo | F81: =VLOOKUP(A81,BBDD!$1:$1048653,11,0) -> Usuario Externo | G81: =VLOOKUP(A81,BBDD!$1:$1048653,13,0) -> Usuario Externo | H81: =VLOOKUP(A81,BBDD!$1:$1048653,14,0) -> Usuario Externo | I81: =VLOOKUP(A81,BBDD!$1:$1048653,16,0) -> Usuario Externo | J81: =VLOOKUP(A81,BBDD!$1:$1048653,17,0) | K81: =VLOOKUP(A81,BBDD!$1:$1048653,12,0) -> Usuario Externo | L81: =VLOOKUP(A81,BBDD!$1:$1048653,3,0) -> Usuario Externo | M81: =VLOOKUP(A81,BBDD!$1:$1048653,4,0) -> Usuario Externo | N81: =VLOOKUP(A81,BBDD!$1:$1048653,5,0) -> Usuario Externo | O81: 45958 | P81: Oficina | Q81: Finiquito | R81: Solicita copia de finiquito | S81: Samuel Fuentealba | T81: Abierto
A82: 15211865 | B82: =VLOOKUP(A82,BBDD!$1:$1048653,2,0) -> 15.211.865-1 | C82: =VLOOKUP(A82,BBDD!$1:$1048653,7,0) -> Garcias Riffo Miguel Angel | D82: =VLOOKUP(A82,BBDD!$1:$1048653,8,0) -> Tripulante | E82: =VLOOKUP(A82,BBDD!$1:$1048653,10,0) -> Gerencia de Flota y Abastecimiento de Materias Primas | F82: =VLOOKUP(A82,BBDD!$1:$1048653,11,0) -> Indefinido | G82: =VLOOKUP(A82,BBDD!$1:$1048653,13,0) -> Coronel Rol Flota | H82: =VLOOKUP(A82,BBDD!$1:$1048653,14,0) -> Gerencia Corp. Negocio Seafood | I82: =VLOOKUP(A82,BBDD!$1:$1048653,16,0) -> Rol General (Cargo permanente o proyección indefinido) | J82: =VLOOKUP(A82,BBDD!$1:$1048653,17,0) | K82: =VLOOKUP(A82,BBDD!$1:$1048653,12,0) -> 45749 | L82: =VLOOKUP(A82,BBDD!$1:$1048653,3,0) -> Orizon S.A | M82: =VLOOKUP(A82,BBDD!$1:$1048653,4,0) -> F1 | N82: =VLOOKUP(A82,BBDD!$1:$1048653,5,0) -> miguelgarcias3777@gmail.com | O82: 45958 | P82: E-mail | Q82: Beneficios | R82: solicita informacion respecto a prestamos para construccion de vivienda | S82: se deriva con Marlene Cartes | T82: Cerrado
A83: 9363315 | B83: =VLOOKUP(A83,BBDD!$1:$1048653,2,0) -> 9.363.315-6 | C83: =VLOOKUP(A83,BBDD!$1:$1048653,7,0) -> Medina Martinez Victor Manuel | D83: =VLOOKUP(A83,BBDD!$1:$1048653,8,0) -> Mecanico De Turno | E83: =VLOOKUP(A83,BBDD!$1:$1048653,10,0) -> Departamento Ingeniería | F83: =VLOOKUP(A83,BBDD!$1:$1048653,11,0) -> Indefinido | G83: =VLOOKUP(A83,BBDD!$1:$1048653,13,0) -> Coronel Rol Tierra | H83: =VLOOKUP(A83,BBDD!$1:$1048653,14,0) -> Gerencia Corp. Negocio Seafood | I83: =VLOOKUP(A83,BBDD!$1:$1048653,16,0) -> Rol General (Cargo permanente o proyección indefinido) | J83: =VLOOKUP(A83,BBDD!$1:$1048653,17,0) | K83: =VLOOKUP(A83,BBDD!$1:$1048653,12,0) -> 40513 | L83: =VLOOKUP(A83,BBDD!$1:$1048653,3,0) -> Orizon S.A | M83: =VLOOKUP(A83,BBDD!$1:$1048653,4,0) -> F1 | N83: =VLOOKUP(A83,BBDD!$1:$1048653,5,0) -> vicmedinamartinez@gmail.com | O83: 45958 | P83: Oficina | Q83: Otro | R83: Solicita firma de apelacion mutual a experto SST | S83: Se deriva a SST | T83: Cerrado
A84: 15528827 | B84: =VLOOKUP(A84,BBDD!$1:$1048653,2,0) -> 15.528.827-2 | C84: =VLOOKUP(A84,BBDD!$1:$1048653,7,0) -> Quezada Araneda Vladimir Orlando | D84: =VLOOKUP(A84,BBDD!$1:$1048653,8,0) -> Mecanico Frigorista | E84: =VLOOKUP(A84,BBDD!$1:$1048653,10,0) -> Departamento Ingeniería | F84: =VLOOKUP(A84,BBDD!$1:$1048653,11,0) -> Indefinido | G84: =VLOOKUP(A84,BBDD!$1:$1048653,13,0) -> Coronel Rol Tierra | H84: =VLOOKUP(A84,BBDD!$1:$1048653,14,0) -> Gerencia Corp. Negocio Seafood | I84: =VLOOKUP(A84,BBDD!$1:$1048653,16,0) -> Rol General (Cargo permanente o proyección indefinido) | J84: =VLOOKUP(A84,BBDD!$1:$1048653,17,0) | K84: =VLOOKUP(A84,BBDD!$1:$1048653,12,0) -> 44531 | L84: =VLOOKUP(A84,BBDD!$1:$1048653,3,0) -> Orizon S.A | M84: =VLOOKUP(A84,BBDD!$1:$1048653,4,0) -> F1 | N84: =VLOOKUP(A84,BBDD!$1:$1048653,5,0) -> voquezad@gmail.com | O84: 45958 | P84: Oficina | Q84: Vestimenta y EPP | R84: Solicita n° reserva | S84: Entregado | T84: Cerrado
A85: 8885420 | B85: =VLOOKUP(A85,BBDD!$1:$1048653,2,0) -> 8.885.420-9 | C85: =VLOOKUP(A85,BBDD!$1:$1048653,7,0) -> Vargas Jerez Ricardo Segundo | D85: =VLOOKUP(A85,BBDD!$1:$1048653,8,0) -> Operario Apoyo Elaboracion | E85: =VLOOKUP(A85,BBDD!$1:$1048653,10,0) -> Gerencia Producción Pesca | F85: =VLOOKUP(A85,BBDD!$1:$1048653,11,0) -> Plazo fijo | G85: =VLOOKUP(A85,BBDD!$1:$1048653,13,0) -> Coronel Rol Eventual | H85: =VLOOKUP(A85,BBDD!$1:$1048653,14,0) -> Gerencia Corp. Negocio Seafood | I85: =VLOOKUP(A85,BBDD!$1:$1048653,16,0) -> Temporada (Con ocasión Temporada de Pesca) | J85: =VLOOKUP(A85,BBDD!$1:$1048653,17,0) | K85: =VLOOKUP(A85,BBDD!$1:$1048653,12,0) -> 45931 | L85: =VLOOKUP(A85,BBDD!$1:$1048653,3,0) -> Orizon S.A | M85: =VLOOKUP(A85,BBDD!$1:$1048653,4,0) -> F3 | N85: =VLOOKUP(A85,BBDD!$1:$1048653,5,0) -> ricardovargasjerez.777@gmail.com | O85: 45958 | P85: Oficina | Q85: Remuneraciones | R85: Solicita revisar asistencia | S85: Se informa que no tiene compensado | T85: Cerrado
A86: 20149400 | B86: =VLOOKUP(A86,BBDD!$1:$1048653,2,0) -> 20.149.400-1 | C86: =VLOOKUP(A86,BBDD!$1:$1048653,7,0) -> Sanchez Ruiz Javiera Ignacia | D86: =VLOOKUP(A86,BBDD!$1:$1048653,8,0) -> Operario Apoyo Elaboracion | E86: =VLOOKUP(A86,BBDD!$1:$1048653,10,0) -> Gerencia Producción Pesca | F86: =VLOOKUP(A86,BBDD!$1:$1048653,11,0) -> Plazo fijo | G86: =VLOOKUP(A86,BBDD!$1:$1048653,13,0) -> Coronel Rol Eventual | H86: =VLOOKUP(A86,BBDD!$1:$1048653,14,0) -> Gerencia Corp. Negocio Seafood | I86: =VLOOKUP(A86,BBDD!$1:$1048653,16,0) -> Temporada (Con ocasión Temporada de Pesca) | J86: =VLOOKUP(A86,BBDD!$1:$1048653,17,0) | K86: =VLOOKUP(A86,BBDD!$1:$1048653,12,0) -> 45931 | L86: =VLOOKUP(A86,BBDD!$1:$1048653,3,0) -> Orizon S.A | M86: =VLOOKUP(A86,BBDD!$1:$1048653,4,0) -> F5 | N86: =VLOOKUP(A86,BBDD!$1:$1048653,5,0) -> jjjavi.rra23@gmail.com | O86: 45958 | P86: Oficina | Q86: Asistencia | R86: Informa que no marco entrada, pero si la salida | S86: Estefi valida asistencia con supervisor | T86: Cerrado
A87: 9459618 | B87: =VLOOKUP(A87,BBDD!$1:$1048653,2,0) -> 9.459.618-1 | C87: =VLOOKUP(A87,BBDD!$1:$1048653,7,0) -> Paz Ruiz Pedro Arturo | D87: =VLOOKUP(A87,BBDD!$1:$1048653,8,0) -> Operador Grupo Generadores | E87: =VLOOKUP(A87,BBDD!$1:$1048653,10,0) -> Departamento Ingeniería | F87: =VLOOKUP(A87,BBDD!$1:$1048653,11,0) -> Indefinido | G87: =VLOOKUP(A87,BBDD!$1:$1048653,13,0) -> Coronel Rol Tierra | H87: =VLOOKUP(A87,BBDD!$1:$1048653,14,0) -> Gerencia Corp. Negocio Seafood | I87: =VLOOKUP(A87,BBDD!$1:$1048653,16,0) -> Rol General (Cargo permanente o proyección indefinido) | J87: =VLOOKUP(A87,BBDD!$1:$1048653,17,0) | K87: =VLOOKUP(A87,BBDD!$1:$1048653,12,0) -> 45432 | L87: =VLOOKUP(A87,BBDD!$1:$1048653,3,0) -> Orizon S.A | M87: =VLOOKUP(A87,BBDD!$1:$1048653,4,0) -> F1 | N87: =VLOOKUP(A87,BBDD!$1:$1048653,5,0) -> p.paz963@gmail.com | O87: 45959 | P87: Oficina | Q87: Seguro de Salud | R87: Consulta por telefono de ejecutiva de seguro | S87: Se deriva a correo de Karen Anacona | T87: Cerrado
A88: 1 | B88: =VLOOKUP(A88,BBDD!$1:$1048653,2,0) -> Usuario Externo | C88: =VLOOKUP(A88,BBDD!$1:$1048653,7,0) -> Usuario Externo | D88: =VLOOKUP(A88,BBDD!$1:$1048653,8,0) -> Usuario Externo | E88: =VLOOKUP(A88,BBDD!$1:$1048653,10,0) -> Usuario Externo | F88: =VLOOKUP(A88,BBDD!$1:$1048653,11,0) -> Usuario Externo | G88: =VLOOKUP(A88,BBDD!$1:$1048653,13,0) -> Usuario Externo | H88: =VLOOKUP(A88,BBDD!$1:$1048653,14,0) -> Usuario Externo | I88: =VLOOKUP(A88,BBDD!$1:$1048653,16,0) -> Usuario Externo | J88: =VLOOKUP(A88,BBDD!$1:$1048653,17,0) | K88: =VLOOKUP(A88,BBDD!$1:$1048653,12,0) -> Usuario Externo | L88: =VLOOKUP(A88,BBDD!$1:$1048653,3,0) -> Usuario Externo | M88: =VLOOKUP(A88,BBDD!$1:$1048653,4,0) -> Usuario Externo | N88: =VLOOKUP(A88,BBDD!$1:$1048653,5,0) -> Usuario Externo | O88: 45959 | P88: Oficina | Q88: Finiquito | R88: Consulta por finiquito Jonathan Delgado | S88: Se entrega copia | T88: Cerrado
A89: 8493006 | B89: =VLOOKUP(A89,BBDD!$1:$1048653,2,0) -> 8.493.006-7 | C89: =VLOOKUP(A89,BBDD!$1:$1048653,7,0) -> Ortiz Ruiz Graciela Emperatriz | D89: =VLOOKUP(A89,BBDD!$1:$1048653,8,0) -> Operario Apoyo Elaboracion | E89: =VLOOKUP(A89,BBDD!$1:$1048653,10,0) -> Gerencia Producción Pesca | F89: =VLOOKUP(A89,BBDD!$1:$1048653,11,0) -> Plazo fijo | G89: =VLOOKUP(A89,BBDD!$1:$1048653,13,0) -> Coronel Rol Eventual | H89: =VLOOKUP(A89,BBDD!$1:$1048653,14,0) -> Gerencia Corp. Negocio Seafood | I89: =VLOOKUP(A89,BBDD!$1:$1048653,16,0) -> Eventual (Reemplazo LM - Proyecto - Faena 4E Conservas) | J89: =VLOOKUP(A89,BBDD!$1:$1048653,17,0) | K89: =VLOOKUP(A89,BBDD!$1:$1048653,12,0) -> 45925 | L89: =VLOOKUP(A89,BBDD!$1:$1048653,3,0) -> Orizon S.A | M89: =VLOOKUP(A89,BBDD!$1:$1048653,4,0) -> F5 | N89: =VLOOKUP(A89,BBDD!$1:$1048653,5,0) -> emperatrizortiz1968@gmail.com | O89: 45959 | P89: E-mail | Q89: Contrato | R89: Firma pendiente | T89: Abierto
A90: 17594144 | B90: =VLOOKUP(A90,BBDD!$1:$1048653,2,0) -> 17.594.144-4 | C90: =VLOOKUP(A90,BBDD!$1:$1048653,7,0) -> Malbrán Paredes Julia Paz | D90: =VLOOKUP(A90,BBDD!$1:$1048653,8,0) -> Operario Apoyo Elaboracion | E90: =VLOOKUP(A90,BBDD!$1:$1048653,10,0) -> Gerencia Producción Pesca | F90: =VLOOKUP(A90,BBDD!$1:$1048653,11,0) -> Plazo fijo | G90: =VLOOKUP(A90,BBDD!$1:$1048653,13,0) -> Coronel Rol Eventual | H90: =VLOOKUP(A90,BBDD!$1:$1048653,14,0) -> Gerencia Corp. Negocio Seafood | I90: =VLOOKUP(A90,BBDD!$1:$1048653,16,0) -> Temporada (Con ocasión Temporada de Pesca) | J90: =VLOOKUP(A90,BBDD!$1:$1048653,17,0) | K90: =VLOOKUP(A90,BBDD!$1:$1048653,12,0) -> 45931 | L90: =VLOOKUP(A90,BBDD!$1:$1048653,3,0) -> Orizon S.A | M90: =VLOOKUP(A90,BBDD!$1:$1048653,4,0) -> F2 | N90: =VLOOKUP(A90,BBDD!$1:$1048653,5,0) -> pazmalbrann@gmail.com | O90: 45959 | P90: Oficina | Q90: Asistencia | R90: Consulta por asistencia | S90: Estefi indica que se encuentra ok | T90: Cerrado
A91: 17204236 | B91: =VLOOKUP(A91,BBDD!$1:$1048653,2,0) -> 17.204.236-8 | C91: =VLOOKUP(A91,BBDD!$1:$1048653,7,0) -> Sanchez Torres Lorena Del Carmen | D91: =VLOOKUP(A91,BBDD!$1:$1048653,8,0) -> Operario Apoyo Elaboracion | E91: =VLOOKUP(A91,BBDD!$1:$1048653,10,0) -> Gerencia Producción Pesca | F91: =VLOOKUP(A91,BBDD!$1:$1048653,11,0) -> Plazo fijo | G91: =VLOOKUP(A91,BBDD!$1:$1048653,13,0) -> Coronel Rol Eventual | H91: =VLOOKUP(A91,BBDD!$1:$1048653,14,0) -> Gerencia Corp. Negocio Seafood | I91: =VLOOKUP(A91,BBDD!$1:$1048653,16,0) -> Temporada (Con ocasión Temporada de Pesca) | J91: =VLOOKUP(A91,BBDD!$1:$1048653,17,0) | K91: =VLOOKUP(A91,BBDD!$1:$1048653,12,0) -> 45931 | L91: =VLOOKUP(A91,BBDD!$1:$1048653,3,0) -> Orizon S.A | M91: =VLOOKUP(A91,BBDD!$1:$1048653,4,0) -> F3 | N91: =VLOOKUP(A91,BBDD!$1:$1048653,5,0) -> sanchez288210@gmail.com | O91: 45959 | P91: Oficina | Q91: Remuneraciones | R91: Bonos de Fisherman | T91: Cerrado
A92: 10862869 | B92: =VLOOKUP(A92,BBDD!$1:$1048653,2,0) -> 10.862.869-3 | C92: =VLOOKUP(A92,BBDD!$1:$1048653,7,0) -> Beltran Vega Hector Luis | D92: =VLOOKUP(A92,BBDD!$1:$1048653,8,0) -> Operador Grua Horquilla | E92: =VLOOKUP(A92,BBDD!$1:$1048653,10,0) -> Gerencia Producción Pesca | F92: =VLOOKUP(A92,BBDD!$1:$1048653,11,0) -> Plazo fijo | G92: =VLOOKUP(A92,BBDD!$1:$1048653,13,0) -> Coronel Rol Eventual | H92: =VLOOKUP(A92,BBDD!$1:$1048653,14,0) -> Gerencia Corp. Negocio Seafood | I92: =VLOOKUP(A92,BBDD!$1:$1048653,16,0) -> Temporada (Con ocasión Temporada de Pesca) | J92: =VLOOKUP(A92,BBDD!$1:$1048653,17,0) | K92: =VLOOKUP(A92,BBDD!$1:$1048653,12,0) -> 45940 | L92: =VLOOKUP(A92,BBDD!$1:$1048653,3,0) -> Orizon S.A | M92: =VLOOKUP(A92,BBDD!$1:$1048653,4,0) -> F4 | N92: =VLOOKUP(A92,BBDD!$1:$1048653,5,0) -> HECTOR.LUISBELTRAN1409@GMAIL.COM | O92: 45960 | P92: Oficina | Q92: Documentos | S92: Cargar Anexo bonos | T92: Abierto
A93: 18821604 | B93: =VLOOKUP(A93,BBDD!$1:$1048653,2,0) -> 18.821.604-8 | C93: =VLOOKUP(A93,BBDD!$1:$1048653,7,0) -> Garrido Bustos Pedro Ignacio | D93: =VLOOKUP(A93,BBDD!$1:$1048653,8,0) -> Operario Apoyo Elaboracion | E93: =VLOOKUP(A93,BBDD!$1:$1048653,10,0) -> Gerencia Producción Pesca | F93: =VLOOKUP(A93,BBDD!$1:$1048653,11,0) -> Plazo fijo | G93: =VLOOKUP(A93,BBDD!$1:$1048653,13,0) -> Coronel Rol Eventual | H93: =VLOOKUP(A93,BBDD!$1:$1048653,14,0) -> Gerencia Corp. Negocio Seafood | I93: =VLOOKUP(A93,BBDD!$1:$1048653,16,0) -> Temporada (Con ocasión Temporada de Pesca) | J93: =VLOOKUP(A93,BBDD!$1:$1048653,17,0) | K93: =VLOOKUP(A93,BBDD!$1:$1048653,12,0) -> 45941 | L93: =VLOOKUP(A93,BBDD!$1:$1048653,3,0) -> Orizon S.A | M93: =VLOOKUP(A93,BBDD!$1:$1048653,4,0) -> F1 | N93: =VLOOKUP(A93,BBDD!$1:$1048653,5,0) -> pegarridoblizzard@gmail.com | O93: 45960 | P93: Oficina | Q93: Asistencia | R93: Indica que no marco la entrada pero si salida | T93: Cerrado
A94: 14435836 | B94: =VLOOKUP(A94,BBDD!$1:$1048653,2,0) -> 14.435.836-8 | C94: =VLOOKUP(A94,BBDD!$1:$1048653,7,0) -> Fuentealba Avendaño Luis Hernan | D94: =VLOOKUP(A94,BBDD!$1:$1048653,8,0) -> Tripulante | E94: =VLOOKUP(A94,BBDD!$1:$1048653,10,0) -> Gerencia de Flota y Abastecimiento de Materias Primas | F94: =VLOOKUP(A94,BBDD!$1:$1048653,11,0) -> Indefinido | G94: =VLOOKUP(A94,BBDD!$1:$1048653,13,0) -> Coronel Rol Flota | H94: =VLOOKUP(A94,BBDD!$1:$1048653,14,0) -> Gerencia Corp. Negocio Seafood | I94: =VLOOKUP(A94,BBDD!$1:$1048653,16,0) -> Rol General (Cargo permanente o proyección indefinido) | J94: =VLOOKUP(A94,BBDD!$1:$1048653,17,0) | K94: =VLOOKUP(A94,BBDD!$1:$1048653,12,0) -> 44106 | L94: =VLOOKUP(A94,BBDD!$1:$1048653,3,0) -> Orizon S.A | M94: =VLOOKUP(A94,BBDD!$1:$1048653,4,0) -> F1 | N94: =VLOOKUP(A94,BBDD!$1:$1048653,5,0) -> luisfuentealba266@gmail.com | O94: 45960 | P94: Oficina | Q94: Asignación Familiar | R94: Se entrega formularios para actualizar carga familiar y se presenta a su coordinador | T94: Abierto
A95: 9750485 | B95: =VLOOKUP(A95,BBDD!$1:$1048653,2,0) -> 9.750.485-7 | C95: =VLOOKUP(A95,BBDD!$1:$1048653,7,0) -> Ramirez Parada Luis Raul | D95: =VLOOKUP(A95,BBDD!$1:$1048653,8,0) -> Jefe Mantención Mecánica | E95: =VLOOKUP(A95,BBDD!$1:$1048653,10,0) -> Departamento Ingeniería | F95: =VLOOKUP(A95,BBDD!$1:$1048653,11,0) -> Indefinido | G95: =VLOOKUP(A95,BBDD!$1:$1048653,13,0) -> Coronel Rol Tierra | H95: =VLOOKUP(A95,BBDD!$1:$1048653,14,0) -> Gerencia Corp. Negocio Seafood | I95: =VLOOKUP(A95,BBDD!$1:$1048653,16,0) -> Rol General (Cargo permanente o proyección indefinido) | J95: =VLOOKUP(A95,BBDD!$1:$1048653,17,0) | K95: =VLOOKUP(A95,BBDD!$1:$1048653,12,0) -> 45264 | L95: =VLOOKUP(A95,BBDD!$1:$1048653,3,0) -> Orizon S.A | M95: =VLOOKUP(A95,BBDD!$1:$1048653,4,0) -> F1 | N95: =VLOOKUP(A95,BBDD!$1:$1048653,5,0) -> luis.ramirez@orizon.cl | O95: 45960 | P95: Teléfono | Q95: Otro | R95: Acceso y Ingresos de personal EST- Sin creacion en pronexo | S95: Se esta gestionando y creando personal en pronexo por parte de la EST | T95: Abierto
A96: 19108626 | B96: =VLOOKUP(A96,BBDD!$1:$1048653,2,0) -> 19.108.626-0 | C96: =VLOOKUP(A96,BBDD!$1:$1048653,7,0) -> Bustos Jara Ivette Angelica | D96: =VLOOKUP(A96,BBDD!$1:$1048653,8,0) -> Encargado(A) Logistico Iii | E96: =VLOOKUP(A96,BBDD!$1:$1048653,10,0) -> Gerencia Logistica | F96: =VLOOKUP(A96,BBDD!$1:$1048653,11,0) -> Indefinido | G96: =VLOOKUP(A96,BBDD!$1:$1048653,13,0) -> Coronel Rol Tierra | H96: =VLOOKUP(A96,BBDD!$1:$1048653,14,0) -> Gerencia Corp. Supply Chain | I96: =VLOOKUP(A96,BBDD!$1:$1048653,16,0) -> Rol General (Cargo permanente o proyección indefinido) | J96: =VLOOKUP(A96,BBDD!$1:$1048653,17,0) | K96: =VLOOKUP(A96,BBDD!$1:$1048653,12,0) -> 44652 | L96: =VLOOKUP(A96,BBDD!$1:$1048653,3,0) -> Orizon S.A | M96: =VLOOKUP(A96,BBDD!$1:$1048653,4,0) -> F1 | N96: =VLOOKUP(A96,BBDD!$1:$1048653,5,0) -> ivette.bustos@orizon.cl | O96: 45960 | P96: Teléfono | Q96: Asistencia | R96: Ingreso de trabajador EST- | S96: se gestiono la autorizacion de ingreso, mientras se regulariza la activacion de pronexo
A97: 21416270 | B97: =VLOOKUP(A97,BBDD!$1:$1048653,2,0) -> 21.416.270-9 | C97: =VLOOKUP(A97,BBDD!$1:$1048653,7,0) -> Soto Soto Sarai Monserrat | D97: =VLOOKUP(A97,BBDD!$1:$1048653,8,0) -> Operario Apoyo Elaboracion | E97: =VLOOKUP(A97,BBDD!$1:$1048653,10,0) -> Gerencia Producción Pesca | F97: =VLOOKUP(A97,BBDD!$1:$1048653,11,0) -> Plazo fijo | G97: =VLOOKUP(A97,BBDD!$1:$1048653,13,0) -> Coronel Rol Eventual | H97: =VLOOKUP(A97,BBDD!$1:$1048653,14,0) -> Gerencia Corp. Negocio Seafood | I97: =VLOOKUP(A97,BBDD!$1:$1048653,16,0) -> Temporada (Con ocasión Temporada de Pesca) | J97: =VLOOKUP(A97,BBDD!$1:$1048653,17,0) | K97: =VLOOKUP(A97,BBDD!$1:$1048653,12,0) -> 45941 | L97: =VLOOKUP(A97,BBDD!$1:$1048653,3,0) -> Orizon S.A | M97: =VLOOKUP(A97,BBDD!$1:$1048653,4,0) -> F1 | N97: =VLOOKUP(A97,BBDD!$1:$1048653,5,0) -> sarai.monse2003@gmail.com | O97: 45960 | P97: Oficina | Q97: Licencia Médica | R97: informa y deja LM | S97: se recibe | T97: Cerrado
A98: 13132449 | B98: =VLOOKUP(A98,BBDD!$1:$1048653,2,0) -> 13.132.449-9 | C98: =VLOOKUP(A98,BBDD!$1:$1048653,7,0) -> Alarcón Reyes Cesar Alexis | D98: =VLOOKUP(A98,BBDD!$1:$1048653,8,0) -> Tripulante | E98: =VLOOKUP(A98,BBDD!$1:$1048653,10,0) -> Gerencia de Flota y Abastecimiento de Materias Primas | F98: =VLOOKUP(A98,BBDD!$1:$1048653,11,0) -> Indefinido | G98: =VLOOKUP(A98,BBDD!$1:$1048653,13,0) -> Coronel Rol flota | H98: =VLOOKUP(A98,BBDD!$1:$1048653,14,0) -> Gerencia Corp. Negocio Seafood | I98: =VLOOKUP(A98,BBDD!$1:$1048653,16,0) -> Rol General (Cargo permanente o proyección indefinido) | J98: =VLOOKUP(A98,BBDD!$1:$1048653,17,0) | K98: =VLOOKUP(A98,BBDD!$1:$1048653,12,0) -> 45570 | L98: =VLOOKUP(A98,BBDD!$1:$1048653,3,0) -> Orizon S.A | M98: =VLOOKUP(A98,BBDD!$1:$1048653,4,0) -> F2 | N98: =VLOOKUP(A98,BBDD!$1:$1048653,5,0) -> alexalarcon2129@gmail.com | O98: 45960 | P98: Oficina | Q98: Buk | R98: firma de documentos y activacion de buk- incorporacion al seguro de salud | S98: se activa y entrega informacion | T98: Abierto
A99: 15756187 | B99: =VLOOKUP(A99,BBDD!$1:$1048653,2,0) -> 15756187-1 | C99: =VLOOKUP(A99,BBDD!$1:$1048653,7,0) -> Benavides Luna Rómulo | D99: =VLOOKUP(A99,BBDD!$1:$1048653,8,0) -> MANTENEDOR MECÁNICO | E99: =VLOOKUP(A99,BBDD!$1:$1048653,10,0) -> Mantención Plantas | F99: =VLOOKUP(A99,BBDD!$1:$1048653,11,0) -> Plazo fijo | G99: =VLOOKUP(A99,BBDD!$1:$1048653,13,0) -> EST | H99: =VLOOKUP(A99,BBDD!$1:$1048653,14,0) -> Gerencia Corp. Seafood | I99: =VLOOKUP(A99,BBDD!$1:$1048653,16,0) | J99: =VLOOKUP(A99,BBDD!$1:$1048653,17,0) | K99: =VLOOKUP(A99,BBDD!$1:$1048653,12,0) -> 45870 | L99: =VLOOKUP(A99,BBDD!$1:$1048653,3,0) -> EST | M99: =VLOOKUP(A99,BBDD!$1:$1048653,4,0) -> F1 | N99: =VLOOKUP(A99,BBDD!$1:$1048653,5,0) | O99: 45959 | P99: Oficina | Q99: EST | R99: consultan por su renovacion en EST | S99: se le informo que supervisor debe entregar esa informacion | T99: Cerrado
A100: 18137625 | B100: =VLOOKUP(A100,BBDD!$1:$1048653,2,0) -> 18137625-2 | C100: =VLOOKUP(A100,BBDD!$1:$1048653,7,0) -> Herrera Carrasco Jean | D100: =VLOOKUP(A100,BBDD!$1:$1048653,8,0) -> MANTENEDOR ELECTROCONTROL | E100: =VLOOKUP(A100,BBDD!$1:$1048653,10,0) -> Mantención Eléctrica | F100: =VLOOKUP(A100,BBDD!$1:$1048653,11,0) -> Plazo fijo | G100: =VLOOKUP(A100,BBDD!$1:$1048653,13,0) -> EST | H100: =VLOOKUP(A100,BBDD!$1:$1048653,14,0) -> Gerencia Corp. Seafood | I100: =VLOOKUP(A100,BBDD!$1:$1048653,16,0) | J100: =VLOOKUP(A100,BBDD!$1:$1048653,17,0) | K100: =VLOOKUP(A100,BBDD!$1:$1048653,12,0) -> 45873 | L100: =VLOOKUP(A100,BBDD!$1:$1048653,3,0) -> EST | M100: =VLOOKUP(A100,BBDD!$1:$1048653,4,0) -> F1 | N100: =VLOOKUP(A100,BBDD!$1:$1048653,5,0) | O100: 45959 | P100: Oficina | Q100: EST | R100: consultan por su renovacion en EST | S100: se le informo que supervisor debe entregar esa informacion | T100: Cerrado
...

Sheet Lista desplegable
D1: Oficina | F1: Remuneraciones | I1: Abierto
D2: Teléfono | F2: Asistencia | I2: Cerrado
D3: E-mail | F3: Contrato
D4: Otro | F4: Documentos
F5: Finiquito
F6: Vacaciones
F7: Fotografía
F8: Beneficios
F9: Licencia Médica
F10: Asignación Familiar
F11: Seguro de Salud
F12: EST
F13: Vestimenta y EPP
F14: Credencial
F15: Buk
F16: Reclutamiento y Selección
F17: Otro
